Workbook

Sheet 封面
A1: 中国建筑 项目管理表格
A2: 项目成本分析报告 | F2: 模板编号
F3: CSCECXJ-BM-M005
B5: 工程名称： | C5: XXX项目
B6: 工程地点： | C6: 龙岗区宝龙街道宝龙二路与高科大道交汇处西南侧
B7: 结构形式： | C7: 框架剪力墙结构
B8: 建筑面积： | C8: 45127.93m3
B9: 累计预算收入： | C9: =+汇总表!D21 -> 1.1111371e+08
B10: 累计责任成本： | C10: =+汇总表!E21 -> 1.1107911e+08
B11: 累计计划成本： | C11: =+C10 -> 1.1107911e+08
B12: 累计实际成本： | C12: =+汇总表!L21 -> 47000639
B13: 编 制 人： | C13: 朱雪晴
B14: 审 核 人： | C14: 胡凯
B15: 编制单位： | C15: XXX项目
B16: 编制日期： | C16: 45407

Sheet 填报说明
A1: 填报说明：
A2: 1、汇总表中数据是由14个分表组成（人工费、材料费、机械费、专业分包费、周转料具、安全文明施工费、施工措施费、现场经费、管理费利润规费税金、让利、总包服务费、指定分包（含税）、其它、开源效益）。信息化中的汇总表连接各相关分表，信息系统自动提取，不需填制。
A3: 2、13个分表三大列（预计工程竣工数据统计、本期数据统计、累计数据统计）中的收入、成本，简化列项，可仅列一行合计。其中人工费、专业分包费、机械费、周转料具、指定分包成本：可按分包队伍列项，涉及到安全文明施工费、施工措施费摘出来单列。
A4: 3、材料费中的主材分析，要与手册成本篇中成本控制主要目标的材料种类、物资篇主材耗量数据分析统计表相匹配，物资篇主材耗量数据分析统计表中采购数量、成本半成本数量、库存原材数量、废旧（待）处理数量、调入数量、调出数量由物资工程师提供，商务把对应的预算量提供给物资，这样主材分析完全一致；物资篇主材耗量数据分析统计表做为附件上传。
A5: 4、开源效益表必须按表格中的内容详细填写，并做为内审检查依据。
A6: 5、把两算相关的支撑资料、详细计算表格作为附件上传。
A7: 6、营改增后，对于新项目，收入成本均不含税，但业主应收款要录含税的，分包报量的应付款也是录含税的。
A8: 7、现场经费明细已完全与财务科目对应

Sheet 汇总表
A1: 工程项目“两算”对比分析汇总表
A2: 工程名称：XXX项目
A3: 序号 | B3: 费用名称 | C3: 单位 | D3: 预计工程竣工数据统计 | G3: 本期数据统计 | K3: 累计数据统计 | O3: 备注
D4: 预计总收入 | E4: 预计总成本 | F4: 差额（预计总收入-预计总成本） | G4: 预算收入 | H4: 实际成本 | I4: 差额（预算收入-实际成本） | J4: 节(+)超(-)(%) | K4: 预算收入 | L4: 实际成本 | M4: 差额（预算收入-实际成本） | N4: 节(+)超(-)(%)
A5: 1 | B5: 人工费 | C5: 元 | D5: =+人工费!G282 -> 6552396.2 | E5: =+人工费!J282 -> 7593488.5 | F5: =D5-E5 -> -1041092.2 | G5: =+人工费!M282 -> 343218.91 | H5: =+人工费!P282 -> 335618.08 | I5: =+G5-H5 -> 7600.8233 | J5: =I5/G5 -> 0.022145701 | K5: =+人工费!S282 -> 4279381.3 | L5: =+人工费!V282 -> 4368817.1 | M5: =+K5-L5 -> -89435.814 | N5: =M5/K5 -> -0.02089924
A6: 2 | B6: 材料费 | C6: 元 | D6: =+材料费!G283 -> 27372618 | E6: =+材料费!J283 -> 21407207 | F6: =D6-E6 -> 5965411 | G6: =+材料费!M283 -> 1142978.8 | H6: =+材料费!P283 -> 2726428.2 | I6: =+G6-H6 -> -1583449.4 | J6: =I6/G6 -> -1.3853707 | K6: =+材料费!S283 -> 19534317 | L6: =+材料费!V283 -> 16261971 | M6: =+K6-L6 -> 3272346.4 | N6: =M6/K6 -> 0.16751782
A7: 3 | B7: 机械费 | C7: 元 | D7: =+机械费!F26 -> 2908349.7 | E7: =+机械费!I26 -> 5310305.5 | F7: =D7-E7 -> -2401955.8 | G7: =+机械费!L26 -> 112946.82 | H7: =+机械费!P26 -> 317779.39 | I7: =+G7-H7 -> -204832.57 | J7: =I7/G7 -> -1.8135312 | K7: =+机械费!S26 -> 1292176.1 | L7: =+机械费!W26 -> 2222622.6 | M7: =+K7-L7 -> -930446.45 | N7: =M7/K7 -> -0.72006163
A8: 4 | B8: 专业分包费 | C8: 元 | D8: =+专业分包费!G582 -> 36605672 | E8: =+专业分包费!J582 -> 41376861 | F8: =D8-E8 -> -4771189 | G8: =+专业分包费!M582 -> -594003.69 | H8: =+专业分包费!P582 -> -51802.339 | I8: =+G8-H8 -> -542201.35 | J8: =I8/G8 -> 0.91279122 | K8: =+专业分包费!S582 -> 5450338.2 | L8: =+专业分包费!V582 -> 6581032.5 | M8: =+K8-L8 -> -1130694.3 | N8: =M8/K8 -> -0.20745397
A9: 5 | B9: 周转料具 | C9: 元 | D9: =+周转料具!G153 -> 14850944 | E9: =+周转料具!J153 -> 15189226 | F9: =D9-E9 -> -338282.24 | G9: =+周转料具!M153 -> 2428271.4 | H9: =+周转料具!P153 -> 881602.17 | I9: =+G9-H9 -> 1546669.2 | J9: =I9/G9 -> 0.63694249 | K9: =+周转料具!S153 -> 8875550.7 | L9: =+周转料具!V153 -> 7555071.6 | M9: =+K9-L9 -> 1320479 | N9: =M9/K9 -> 0.14877714
A10: 6 | B10: 安全文明施工费 | C10: 元 | D10: =+安全文明施工费!E36 -> 3721871.1 | E10: =+安全文明施工费!G36 -> 4196897.5 | F10: =D10-E10 -> -475026.44 | G10: =+安全文明施工费!I36 -> 144735.76 | H10: =+安全文明施工费!L36 -> 363412.05 | I10: =+G10-H10 -> -218676.29 | J10: =I10/G10 -> -1.5108656 | K10: =+安全文明施工费!N36 -> 1524999.2 | L10: =+安全文明施工费!Q36 -> 4162523.7 | M10: =+K10-L10 -> -2637524.5 | N10: =M10/K10 -> -1.7295252
A11: 7 | B11: 施工措施费 | C11: 元 | D11: 0 | E11: =+施工措施费!E22 -> 1656710 | F11: =D11-E11 -> -1656710 | G11: =+施工措施费!G22 -> 0 | H11: =+施工措施费!J22 -> 8867.93 | I11: =+G11-H11 -> -8867.93 | J11: =I11/G11 -> #DIV/0! | K11: =+施工措施费!L22 -> 0 | L11: =+施工措施费!O22 -> 1088344.4 | M11: =+K11-L11 -> -1088344.4 | N11: =M11/K11 -> #DIV/0!
A12: 8 | B12: 现场管理费 | C12: 元 | D12: =+'管理费、利润、规费、税金'!D5 -> 4884475.9 | E12: =+'管理费、利润、规费、税金'!E5 -> 13200702 | F12: =D12-E12 -> -8316226.5 | G12: =+'管理费、利润、规费、税金'!F5 -> 189947.03 | H12: =+'管理费、利润、规费、税金'!G5 -> -728996.59 | I12: =+G12-H12 -> 918943.62 | J12: =I12/G12 -> 4.8378941 | K12: =+'管理费、利润、规费、税金'!H5 -> 2001364.8 | L12: =+'管理费、利润、规费、税金'!I5 -> 4785734.2 | M12: =+K12-L12 -> -2784369.4 | N12: =M12/K12 -> -1.3912353
A13: 9 | B13: 利 润 | C13: 元 | D13: =+'管理费、利润、规费、税金'!D6 -> 4867994.6 | E13: 0 | F13: =D13-E13 -> 4867994.6 | G13: =+'管理费、利润、规费、税金'!F6 -> 189306.11 | H13: =+'管理费、利润、规费、税金'!G6 -> 0 | I13: =+G13-H13 -> 189306.11 | J13: =I13/G13 -> 1 | K13: =+'管理费、利润、规费、税金'!H6 -> 1994611.8 | L13: =+'管理费、利润、规费、税金'!I6 -> 0 | M13: =+K13-L13 -> 1994611.8 | N13: =M13/K13 -> 1
A14: 10 | B14: 规 费 | C14: 元 | D14: =+'管理费、利润、规费、税金'!D7 -> 5142966.4 | E14: 0 | F14: =D14-E14 -> 5142966.4 | G14: =+'管理费、利润、规费、税金'!F7 -> 199999.18 | H14: =+'管理费、利润、规费、税金'!G7 -> 0 | I14: =+G14-H14 -> 199999.18 | J14: =I14/G14 -> 1 | K14: =+'管理费、利润、规费、税金'!H7 -> 2107278.7 | L14: =+'管理费、利润、规费、税金'!I7 -> 0 | M14: =+K14-L14 -> 2107278.7 | N14: =M14/K14 -> 1
A15: 11 | B15: 税 金 | C15: 元 | D15: 0 | E15: 0 | F15: =D15-E15 -> 0 | G15: =+'管理费、利润、规费、税金'!F8 -> 0 | H15: =+'管理费、利润、规费、税金'!G8 -> 0 | I15: =+G15-H15 -> 0 | J15: =I15/G15 -> #DIV/0! | K15: =+'管理费、利润、规费、税金'!H8 -> 0 | L15: =+'管理费、利润、规费、税金'!I8 -> 0 | M15: =+K15-L15 -> 0 | N15: =M15/K15 -> #DIV/0!
A16: 12 | B16: 让 利 | C16: 元 | D16: 0 | E16: 0 | F16: =D16-E16 -> 0 | G16: =+让利!H17 -> 0 | H16: =+让利!I17 -> 0 | I16: =+G16-H16 -> 0 | J16: =I16/G16 -> #DIV/0! | K16: =+让利!K17 -> 0 | L16: =+让利!L17 -> 0 | M16: =+K16-L16 -> 0 | N16: =M16/K16 -> #DIV/0!
A17: 13 | B17: 指定分包 | C17: 元 | D17: 0 | E17: 0 | F17: =D17-E17 -> 0 | G17: =+指定分包!G13 -> 0 | H17: =+指定分包!H13 -> 0 | I17: =+G17-H17 -> 0 | J17: =I17/G17 -> #DIV/0! | K17: =+指定分包!J13 -> 0 | L17: =+指定分包!K13 -> 0 | M17: =+K17-L17 -> 0 | N17: =M17/K17 -> #DIV/0!
A18: 14 | B18: 总包服务费 | C18: 元 | D18: =895000/1.09 -> 821100.92 | E18: =-32982357.59/1.09*3.5% -> -1059066.5 | F18: =D18-E18 -> 1880167.4 | G18: =+总包服务费!H17 -> 0 | H18: =+总包服务费!I17 -> 15870.872 | I18: =+G18-H18 -> -15870.872 | J18: =I18/G18 -> #DIV/0! | K18: =+总包服务费!K17 -> 0 | L18: =+总包服务费!L17 -> -25477.751 | M18: =+K18-L18 -> 25477.751 | N18: =M18/K18 -> #DIV/0!
A19: 15 | B19: 其 它 | C19: 元 | D19: =其它!F22 -> 3385321.1 | E19: =其它!I22 -> 4496458.2 | F19: =D19-E19 -> -1111137.1 | G19: =+其它!L22 -> 0 | H19: =+其它!O22 -> 0 | I19: =+G19-H19 -> 0 | J19: =I19/G19 -> #DIV/0! | K19: =+其它!R22 -> 0 | L19: =+其它!U22 -> 0 | M19: =+K19-L19 -> 0 | N19: =M19/K19 -> #DIV/0!
A20: 16 | B20: 开源效益 | C20: 元 | D20: 0 | E20: -2289682.9 | F20: =D20-E20 -> 2289682.9 | I20: =+G20-H20 -> 0 | J20: =I20/G20 -> #DIV/0! | M20: =+K20-L20 -> 0 | N20: =M20/K20 -> #DIV/0!
B21: 合计 | C21: 元 | D21: =SUM(D5:D20) -> 1.1111371e+08 | E21: =SUM(E5:E20) -> 1.1107911e+08 | F21: =D21-E21 -> 34603.047 | G21: =SUM(G5:G20) -> 4157400.4 | H21: =SUM(H5:H20) -> 3868779.8 | I21: =G21-H21 -> 288620.55 | J21: =I21/G21 -> 0.069423325 | K21: =SUM(K5:K20) -> 47060018 | L21: =SUM(L5:L20) -> 47000639 | M21: =K21-L21 -> 59378.693 | N21: =M21/K21 -> 0.0012617652
A22: 备注：1.“预测工程竣工数据统计”数据原则上每季度调整一次。2.“预测工程竣工数据统计”中“开源效益”数据填净利润，在前期不确定增加收入时，可根据开源效益目标将该数值填入计划成本中，为负值冲减成本。3.“安全文明施工费”根据《建设工程工程量清单计价规范》GB 50500—2013规定进行数据归口。4.“开源效益”数据来源“开源效益计算表”中的“未实施部分”。
D23: （营改增后一般计税项目，价税分离，税金不列，下同）
D25: =D5+D6+D7+D8+D9 -> 88289980 | G25: =G5+G6+G7+G8+G9 -> 3433412.3 | K25: =(K5+K6+K7+K8+K9)/1.09 -> 36175930
I28: 土建数据 | J28: 本期 | K28: 累计
I29: 预算收入 | J29: =+G21-专业分包费!M581 -> 4302401.7 | K29: =+K21-专业分包费!S581 -> 46043006
I30: 实际成本 | J30: =+H21-专业分包费!P581 -> 4662323.4 | K30: =+L21-专业分包费!V581 -> 45726752
I31: 安装数据 | J31: 本期 | K31: 累计
I32: 预算收入 | J32: =+专业分包费!M581 -> -145001.38 | K32: =+专业分包费!S581 -> 1017011.9
I33: 实际成本 | J33: =+专业分包费!P581 -> -793543.58 | K33: =+专业分包费!V581 -> 1273887.6

Sheet 本期分析及总结
A1: 本期分析及总结
A2: 一、 | B2: 本期完成工程描述及累计形象部位
A3: 1 | B3: 地下室：
A4: 1.1 | B4: 地下室主体结构封顶
A5: 1.2 | B5: 地下室砌筑完成
A6: 1.3 | B6: 地下室外墙防水施工完成
A7: 1.4 | B7: 地上外墙防水：1号楼完成3-12层，2号楼完成3-12层
A8: 1.5 | B8: 地上1号楼、2号楼完成17层结构
A10: 二、 | B10: 本期项目成本情况
A11: 1 | B11: 项目成本收入数据是截止2024年4月15日
A12: 2 | B12: 实际累计产值 | C12: =+汇总表!K21/10000 -> 4706.0018 | D12: 万元
A13: 3 | B13: 实际累计成本 | C13: =+汇总表!L21/10000 -> 4700.0639 | D13: 万元
A15: 三、 | B15: 总结及纠偏措施
A16: 1 | B16: 目前项目施工阶段处于1#、2#塔楼主体施工阶段，地下室处于砌筑阶段，预测6月30日之前主体封顶；
A17: 2 | B17: 临设费用较高，由于场地限制，目前项目只能租房，后续准备主体结构封顶在首层规划临建，降低成本；

Sheet 人工费
A1: 工程项目人工费计算表
A2: 工程名称： XXX项目
A3: 序号 | B3: 分部分项名称 | C3: 项目特征 | D3: 单位 | E3: 预测工程竣工数据统计 | K3: 本期数据统计 | Q3: 累计数据统计 | W3: 备注 | Z3: 上次累计数据统计
E4: 预算收入 | H4: 计划成本 | K4: 预算收入 | N4: 实际成本 | Q4: 预算收入 | T4: 实际成本 | Z4: 预算收入
E5: 工程量 | F5: 单价 | G5: 合价 | H5: 工程量 | I5: 单价 | J5: 合计 | K5: 工程量 | L5: 单价 | M5: 合价 | N5: 工程量 | O5: 单价 | P5: 合价 | Q5: 工程量 | R5: 单价 | S5: 合价 | T5: 工程量 | U5: 单价 | V5: 合价 | Z5: 工程量
A6: 一 | B6: 地下室结构 | G6: 2347723.9 | J6: 2769234.9 | M6: =+M7+M33 -> -45348.832 | P6: =+P7+P33 -> -64500 | S6: =+S7+S33 -> 2297592.5 | V6: =+V7+V33 -> 2434226.2
A7: 1 | B7: 钢筋混凝土工程（地下） | M7: =SUM(M8:M32) -> 0 | P7: =SUM(P8:P32) -> 0 | S7: =SUM(S8:S32) -> 770848.74 | V7: =SUM(V8:V32) -> 612004.43
A8: 1.1 | B8: 垫层 C20 | C8: (1)混凝土强度等级:C20泵送商品混凝土_x000D_ (2)满足设计图纸、相关规范、招标文件及技术要求 | D8: m3 | E8: 530.03 | F8: 44.018139 | G8: 23330.934 | H8: 530.03 | I8: 180 | J8: 95405.4 | K8: =+Q8-Z8 -> 0 | L8: =+F8 -> 44.018139 | M8: =+L8*K8 -> 0 | N8: =+K8 -> 0 | O8: =+U8 -> 150 | P8: =+O8*N8 -> 0 | Q8: 530.03 | R8: =+F8 -> 44.018139 | S8: =+R8*Q8 -> 23330.934 | T8: =+Q8 -> 530.03 | U8: 150 | V8: =+U8*T8 -> 79504.5 | Z8: 530.03
A9: 1.2 | B9: 基础（筏板、柱墩、桩承台、基础梁、集水坑） C35P10 | C9: (1)混凝土强度等级:C35泵送商品混凝土，抗渗P10_x000D_ (2)补偿收缩混凝土，补偿收缩时≥0.02%_x000D_ (3)满足设计图纸、相关规范、招标文件及技术要求 | D9: m3 | E9: 3895.64 | F9: 47.755081 | G9: 186036.6 | H9: 3895.64 | I9: 48.5 | J9: 188938.54 | K9: =+Q9-Z9 -> 0 | L9: =+F9 -> 47.755081 | M9: =+L9*K9 -> 0 | N9: =+K9 -> 0 | O9: =+U9 -> 48.5 | P9: =+O9*N9 -> 0 | Q9: 3895.64 | R9: =+F9 -> 47.755081 | S9: =+R9*Q9 -> 186036.6 | T9: =+Q9 -> 3895.64 | U9: 48.5 | V9: =+U9*T9 -> 188938.54 | Z9: 3895.64
A10: 1.3 | B10: 砼墙、柱 C60 | C10: (1)混凝土强度等级:C60泵送商品混凝土_x000D_ (2)满足设计图纸、相关规范、招标文件及技术要求 | D10: m3 | E10: 1201.57 | F10: 80.439095 | G10: 96653.203 | H10: 1201.57 | I10: 48.5 | J10: 58276.145 | K10: =+Q10-Z10 -> 0 | L10: =+F10 -> 80.439095 | M10: =+L10*K10 -> 0 | N10: =+K10 -> 0 | O10: =+U10 -> 48.5 | P10: =+O10*N10 -> 0 | Q10: 1201.57 | R10: =+F10 -> 80.439095 | S10: =+R10*Q10 -> 96653.203 | T10: =+Q10 -> 1201.57 | U10: 48.5 | V10: =+U10*T10 -> 58276.145 | Z10: 1201.57
A11: 1.4 | B11: 砼墙、柱 C40 | C11: (1)混凝土强度等级:C40泵送商品混凝土_x000D_ (2)满足设计图纸、相关规范、招标文件及技术要求 | D11: m3 | E11: 182.21 | F11: 80.439095 | G11: 14656.807 | H11: 182.21 | I11: 48.5 | J11: 8837.185 | K11: =+Q11-Z11 -> 0 | L11: =+F11 -> 80.439095 | M11: =+L11*K11 -> 0 | N11: =+K11 -> 0 | O11: =+U11 -> 48.5 | P11: =+O11*N11 -> 0 | Q11: 182.21 | R11: =+F11 -> 80.439095 | S11: =+R11*Q11 -> 14656.807 | T11: =+Q11 -> 182.21 | U11: 48.5 | V11: =+U11*T11 -> 8837.185 | Z11: 182.21
A12: 1.5 | B12: 砼墙、柱 C35P10_x000D_ | C12: (1)混凝土强度等级:C35泵送商品混凝土，抗渗P10_x000D_ (2)补偿收缩混凝土，补偿收缩时≥0.02%_x000D_ (3)满足设计图纸、相关规范、招标文件及技术要求 | D12: m3 | E12: 481.52 | F12: 80.439095 | G12: 38733.033 | H12: 481.52 | I12: 48.5 | J12: 23353.72 | K12: =+Q12-Z12 -> 0 | L12: =+F12 -> 80.439095 | M12: =+L12*K12 -> 0 | N12: =+K12 -> 0 | O12: =+U12 -> 48.5 | P12: =+O12*N12 -> 0 | Q12: 481.52 | R12: =+F12 -> 80.439095 | S12: =+R12*Q12 -> 38733.033 | T12: =+Q12 -> 481.52 | U12: 48.5 | V12: =+U12*T12 -> 23353.72 | Z12: 481.52
A13: 1.6 | B13: 砼墙、柱 C35P8_x000D_ | C13: (1)混凝土强度等级:C35泵送商品混凝土，抗渗P8_x000D_ (2)补偿收缩混凝土，补偿收缩时≥0.02%_x000D_ (3)满足设计图纸、相关规范、招标文件及技术要求 | D13: m3 | E13: 394.28 | F13: 80.439095 | G13: 31715.526 | H13: 394.28 | I13: 48.5 | J13: 19122.58 | K13: =+Q13-Z13 -> 0 | L13: =+F13 -> 80.439095 | M13: =+L13*K13 -> 0 | N13: =+K13 -> 0 | O13: =+U13 -> 48.5 | P13: =+O13*N13 -> 0 | Q13: 394.28 | R13: =+F13 -> 80.439095 | S13: =+R13*Q13 -> 31715.526 | T13: =+Q13 -> 394.28 | U13: 48.5 | V13: =+U13*T13 -> 19122.58 | Z13: 394.28
A14: 1.7 | B14: 砼墙、柱 C35P6_x000D_ | C14: (1)混凝土强度等级:C35泵送商品混凝土，抗渗P6_x000D_ (2)补偿收缩混凝土，补偿收缩时≥0.02%_x000D_ (3)满足设计图纸、相关规范、招标文件及技术要求 | D14: m3 | E14: 560.18 | F14: 80.439095 | G14: 45060.372 | H14: 560.18 | I14: 48.5 | J14: 27168.73 | K14: =+Q14-Z14 -> 0 | L14: =+F14 -> 80.439095 | M14: =+L14*K14 -> 0 | N14: =+K14 -> 0 | O14: =+U14 -> 48.5 | P14: =+O14*N14 -> 0 | Q14: 560.18 | R14: =+F14 -> 80.439095 | S14: =+R14*Q14 -> 45060.372 | T14: =+Q14 -> 560.18 | U14: 48.5 | V14: =+U14*T14 -> 27168.73 | Z14: 560.18
A15: 1.8 | B15: 砼墙、柱 C35_x000D_ | C15: (1)混凝土强度等级:C35泵送商品混凝土_x000D_ (2)满足设计图纸、相关规范、招标文件及技术要求 | D15: m3 | E15: 335.64 | F15: 80.439095 | G15: 26998.578 | H15: 335.64 | I15: 48.5 | J15: 16278.54 | K15: =+Q15-Z15 -> 0 | L15: =+F15 -> 80.439095 | M15: =+L15*K15 -> 0 | N15: =+K15 -> 0 | O15: =+U15 -> 48.5 | P15: =+O15*N15 -> 0 | Q15: 335.64 | R15: =+F15 -> 80.439095 | S15: =+R15*Q15 -> 26998.578 | T15: =+Q15 -> 335.64 | U15: 48.5 | V15: =+U15*T15 -> 16278.54 | Z15: 335.64
A16: 1.9 | B16: 矩形柱 C35 | C16: (1)混凝土强度等级:C35泵送商品混凝土_x000D_ (2)满足设计图纸、相关规范、招标文件及技术要求 | D16: m3 | E16: 39.15 | F16: 80.439095 | G16: 3149.1906 | H16: 39.15 | I16: 48.5 | J16: 1898.775 | K16: =+Q16-Z16 -> 0 | L16: =+F16 -> 80.439095 | M16: =+L16*K16 -> 0 | N16: =+K16 -> 0 | O16: =+U16 -> 48.5 | P16: =+O16*N16 -> 0 | Q16: 39.15 | R16: =+F16 -> 80.439095 | S16: =+R16*Q16 -> 3149.1906 | T16: =+Q16 -> 39.15 | U16: 48.5 | V16: =+U16*T16 -> 1898.775 | Z16: 39.15
A17: 1.1 | B17: 有梁板 (梁、板) C35P6 | C17: (1)混凝土强度等级:C35泵送商品混凝土,P6_x000D_ (2)补偿收缩混凝土，补偿收缩时≥0.02%_x000D_ (3)满足设计图纸、相关规范、招标文件及技术要求 | D17: m3 | E17: 1349.99 | F17: 73.230781 | G17: 98860.822 | H17: 1349.99 | I17: 48.5 | J17: 65474.515 | K17: =+Q17-Z17 -> 0 | L17: =+F17 -> 73.230781 | M17: =+L17*K17 -> 0 | N17: =+K17 -> 0 | O17: =+U17 -> 48.5 | P17: =+O17*N17 -> 0 | Q17: 1349.99 | R17: =+F17 -> 73.230781 | S17: =+R17*Q17 -> 98860.822 | T17: =+Q17 -> 1349.99 | U17: 48.5 | V17: =+U17*T17 -> 65474.515 | Z17: 1349.99
A18: 1.11 | B18: 有梁板 (梁、板) C35 | C18: (1)混凝土强度等级:C35泵送商品混凝土_x000D_ (2)满足设计图纸、相关规范、招标文件及技术要求 | D18: m3 | E18: 1871.42 | F18: 73.230781 | G18: 137045.55 | H18: 1871.42 | I18: 48.5 | J18: 90763.87 | K18: =+Q18-Z18 -> 0 | L18: =+F18 -> 73.230781 | M18: =+L18*K18 -> 0 | N18: =+K18 -> 0 | O18: =+U18 -> 48.5 | P18: =+O18*N18 -> 0 | Q18: 1871.42 | R18: =+F18 -> 73.230781 | S18: =+R18*Q18 -> 137045.55 | T18: =+Q18 -> 1871.42 | U18: 48.5 | V18: =+U18*T18 -> 90763.87 | Z18: 1871.42
A19: 1.12 | B19: 有梁板 (梁、板)坡道 C35 | C19: (1)混凝土强度等级:C35泵送商品混凝土_x000D_ (2)满足设计图纸、相关规范、招标文件及技术要求 | D19: m3 | E19: 155.94 | F19: 73.230781 | G19: 11419.608 | H19: 155.94 | I19: 48.5 | J19: 7563.09 | K19: =+Q19-Z19 -> 0 | L19: =+F19 -> 73.230781 | M19: =+L19*K19 -> 0 | N19: =+K19 -> 0 | O19: =+U19 -> 48.5 | P19: =+O19*N19 -> 0 | Q19: 155.94 | R19: =+F19 -> 73.230781 | S19: =+R19*Q19 -> 11419.608 | T19: =+Q19 -> 155.94 | U19: 48.5 | V19: =+U19*T19 -> 7563.09 | Z19: 155.94
... A31: 1.24 | B31: C20素混凝土（坡道位置）_x000D_ | C31: (1)C20素混凝土_x000D_ (2)满足设计图纸、相关规范、招标文件及技术要求 | D31: m3 | E31: 44.04 | F31: 52.772447 | G31: 2324.0986 | H31: 44.04 | I31: 50 | J31: 2202 | K31: =+Q31-Z31 -> 0 | L31: =+F31 -> 52.772447 | M31: =+L31*K31 -> 0 | N31: =+K31 -> 0 | O31: =+U31 -> 48.5 | P31: =+O31*N31 -> 0 | Q31: 0 | R31: =+F31 -> 52.772447 | S31: =+R31*Q31 -> 0 | T31: =+Q31 -> 0 | U31: 48.5 | V31: =+U31*T31 -> 0 | Z31: 0
A32: 1.25 | B32: 混凝土泵送费扣减 | D32: 项 | E32: 1 | F32: -68531.026 | G32: -68531.026 | H32: 1 | J32: 0 | K32: =+Q32-Z32 -> 0 | N32: =+K32 -> 0 | S32: =+R32*Q32 -> 0 | V32: =+U32*T32 -> 0
A33: 2 | B33: 钢筋工程 | G33: =SUM(G34:G61) -> 1608805 | J33: =SUM(J34:J61) -> 1901636.7 | M33: =SUM(M34:M61) -> -45348.832 | P33: =SUM(P34:P61) -> -64500 | S33: =SUM(S34:S61) -> 1526743.7 | V33: =SUM(V34:V61) -> 1822221.7
A34: 2.1 | B34: 现浇构件钢筋 | C34: (1)钢筋种类、规格:拉结筋制安(HPB300)φ6mm_x000D_ (2)满足设计图纸、相关规范、招标文件及技术要求 | D34: t | E34: 4.5 | F34: 1673.7231 | G34: 7531.754 | H34: 4.5 | I34: 1290 | J34: 5805 | K34: =+Q34-Z34 -> 0 | L34: 1673.7231 | M34: =+L34*K34 -> 0 | N34: =+K34 -> 0 | O34: 1290 | P34: =+O34*N34 -> 0 | R34: 1673.7231 | S34: =+R34*Q34 -> 0 | T34: =+Q34 -> 0 | U34: 1290 | V34: =+U34*T34 -> 0
A35: 2.2 | B35: 现浇构件钢筋 | C35: (1)钢筋种类、规格:圆钢制安 φ6mm_x000D_ (2)满足设计图纸、相关规范、招标文件及技术要求 | D35: t | E35: 0.2 | F35: 1235.7232 | G35: 247.14464 | H35: 0.2 | I35: 1290 | J35: 258 | K35: =+Q35-Z35 -> 0 | L35: 1235.7232 | M35: =+L35*K35 -> 0 | N35: =+K35 -> 0 | O35: 1290 | P35: =+O35*N35 -> 0 | R35: 1235.7232 | S35: =+R35*Q35 -> 0 | T35: =+Q35 -> 0 | U35: 1290 | V35: =+U35*T35 -> 0
A36: 2.3 | B36: 现浇构件钢筋 | C36: (1)钢筋种类、规格:圆钢制安 φ8~10mm以上_x000D_ (2)满足设计图纸、相关规范、招标文件及技术要求 | D36: t | E36: 0.2 | F36: 953.90656 | G36: 190.78131 | H36: 0.2 | I36: 1290 | J36: 258 | K36: =+Q36-Z36 -> 0 | L36: 953.90656 | M36: =+L36*K36 -> 0 | N36: =+K36 -> 0 | O36: 1290 | P36: =+O36*N36 -> 0 | R36: 953.90656 | S36: =+R36*Q36 -> 0 | T36: =+Q36 -> 0 | U36: 1290 | V36: =+U36*T36 -> 0
A37: 2.4 | B37: 现浇构件钢筋 | C37: (1)钢筋种类、规格:螺纹钢制安Ⅲ级(HRB400E)φ6mm_x000D_ (2)满足设计图纸、相关规范、招标文件及技术要求 | D37: t | E37: 0.022 | F37: 1024.4911 | G37: 22.538805 | H37: 0.022 | I37: 1290 | J37: 28.38 | K37: =+Q37-Z37 -> 0 | L37: 1024.4911 | M37: =+L37*K37 -> 0 | N37: =+K37 -> 0 | O37: 1290 | P37: =+O37*N37 -> 0 | R37: 1024.4911 | S37: =+R37*Q37 -> 0 | T37: =+Q37 -> 0 | U37: 1290 | V37: =+U37*T37 -> 0
A38: 2.5 | B38: 现浇构件钢筋 | C38: (1)钢筋种类、规格:螺纹钢制安Ⅲ级(HRB400E)φ8mm_x000D_ (2)满足设计图纸、相关规范、招标文件及技术要求 | D38: t | E38: 36.245 | F38: 1024.4911 | G38: 37132.681 | H38: 36.245 | I38: 1290 | J38: 46756.05 | K38: =+Q38-Z38 -> 0 | L38: 1024.4911 | M38: =+L38*K38 -> 0 | N38: =+K38 -> 0 | O38: 1290 | P38: =+O38*N38 -> 0 | Q38: 36.245 | R38: 1024.4911 | S38: =+R38*Q38 -> 37132.681 | T38: =+Q38 -> 36.245 | U38: 1290 | V38: =+U38*T38 -> 46756.05 | Z38: 36.245
A39: 2.6 | B39: 现浇构件钢筋 | C39: (1)钢筋种类、规格:螺纹钢制安Ⅲ级(HRB400E)φ10mm_x000D_ (2)满足设计图纸、相关规范、招标文件及技术要求 | D39: t | E39: 177.258 | F39: 1024.4911 | G39: 181599.25 | H39: 177.258 | I39: 1290 | J39: 228662.82 | K39: =+Q39-Z39 -> 0 | L39: 1024.4911 | M39: =+L39*K39 -> 0 | N39: =+K39 -> 0 | O39: 1290 | P39: =+O39*N39 -> 0 | Q39: 177.258 | R39: 1024.4911 | S39: =+R39*Q39 -> 181599.25 | T39: =+Q39 -> 177.258 | U39: 1290 | V39: =+U39*T39 -> 228662.82 | Z39: 177.258
A40: 2.7 | B40: 现浇构件钢筋 | C40: (1)钢筋种类、规格:螺纹钢制安Ⅲ级(HRB400E)φ12mm_x000D_ (2)满足设计图纸、相关规范、招标文件及技术要求 | D40: t | E40: 313.589 | F40: 906.97664 | G40: 284417.9 | H40: 313.589 | I40: 1290 | J40: 404529.81 | K40: =+Q40-Z40 -> -50 | L40: 906.97664 | M40: =+L40*K40 -> -45348.832 | N40: =+K40 -> -50 | O40: 1290 | P40: =+O40*N40 -> -64500 | Q40: =313.589-50 -> 263.589 | R40: 906.97664 | S40: =+R40*Q40 -> 239069.07 | T40: =+Q40 -> 263.589 | U40: 1290 | V40: =+U40*T40 -> 340029.81 | Z40: 313.589
A41: 2.8 | B41: 现浇构件钢筋 | C41: (1)钢筋种类、规格:螺纹钢制安Ⅲ级(HRB400E)φ14mm_x000D_ (2)满足设计图纸、相关规范、招标文件及技术要求 | D41: t | E41: 72.128 | F41: 906.97664 | G41: 65418.411 | H41: 72.128 | I41: 1290 | J41: 93045.12 | K41: =+Q41-Z41 -> 0 | L41: 906.97664 | M41: =+L41*K41 -> 0 | N41: =+K41 -> 0 | O41: 1290 | P41: =+O41*N41 -> 0 | Q41: 72.128 | R41: 906.97664 | S41: =+R41*Q41 -> 65418.411 | T41: =+Q41 -> 72.128 | U41: 1290 | V41: =+U41*T41 -> 93045.12 | Z41: 72.128
A42: 2.9 | B42: 现浇构件钢筋 | C42: (1)钢筋种类、规格:螺纹钢制安Ⅲ级(HRB400E)φ16mm_x000D_ (2)满足设计图纸、相关规范、招标文件及技术要求 | D42: t | E42: 320.691 | F42: 906.97664 | G42: 290859.25 | H42: 320.691 | I42: 1290 | J42: 413691.39 | K42: =+Q42-Z42 -> 0 | L42: 906.97664 | M42: =+L42*K42 -> 0 | N42: =+K42 -> 0 | O42: 1290 | P42: =+O42*N42 -> 0 | Q42: 320.691 | R42: 906.97664 | S42: =+R42*Q42 -> 290859.25 | T42: =+Q42 -> 320.691 | U42: 1290 | V42: =+U42*T42 -> 413691.39 | Z42: 320.691
A43: 2.1 | B43: 现浇构件钢筋 | C43: (1)钢筋种类、规格:螺纹钢制安Ⅲ级(HRB400E)φ18mm_x000D_ (2)满足设计图纸、相关规范、招标文件及技术要求 | D43: t | E43: 65.535 | F43: 906.97664 | G43: 59438.714 | H43: 65.535 | I43: 1290 | J43: 84540.15 | K43: =+Q43-Z43 -> 0 | L43: 906.97664 | M43: =+L43*K43 -> 0 | N43: =+K43 -> 0 | O43: 1290 | P43: =+O43*N43 -> 0 | Q43: 65.535 | R43: 906.97664 | S43: =+R43*Q43 -> 59438.714 | T43: =+Q43 -> 65.535 | U43: 1290 | V43: =+U43*T43 -> 84540.15 | Z43: 65.535
A44: 2.11 | B44: 现浇构件钢筋 | C44: (1)钢筋种类、规格:螺纹钢制安Ⅲ级(HRB400E)φ20mm_x000D_ (2)满足设计图纸、相关规范、招标文件及技术要求 | D44: t | E44: 84.293 | F44: 906.97664 | G44: 76451.782 | H44: 84.293 | I44: 1290 | J44: 108737.97 | K44: =+Q44-Z44 -> 0 | L44: 906.97664 | M44: =+L44*K44 -> 0 | N44: =+K44 -> 0 | O44: 1290 | P44: =+O44*N44 -> 0 | Q44: 84.293 | R44: 906.97664 | S44: =+R44*Q44 -> 76451.782 | T44: =+Q44 -> 84.293 | U44: 1290 | V44: =+U44*T44 -> 108737.97 | Z44: 84.293
A45: 2.12 | B45: 现浇构件钢筋 | C45: (1)钢筋种类、规格:螺纹钢制安Ⅲ级(HRB400E)φ22mm_x000D_ (2)满足设计图纸、相关规范、招标文件及技术要求 | D45: t | E45: 59.776 | F45: 906.97664 | G45: 54215.436 | H45: 59.776 | I45: 1290 | J45: 77111.04 | K45: =+Q45-Z45 -> 0 | L45: 906.97664 | M45: =+L45*K45 -> 0 | N45: =+K45 -> 0 | O45: 1290 | P45: =+O45*N45 -> 0 | Q45: 59.776 | R45: 906.97664 | S45: =+R45*Q45 -> 54215.436 | T45: =+Q45 -> 59.776 | U45: 1290 | V45: =+U45*T45 -> 77111.04 | Z45: 59.776
A46: 2.13 | B46: 现浇构件钢筋 | C46: (1)钢筋种类、规格:螺纹钢制安Ⅲ级(HRB400E)φ25mm_x000D_ (2)满足设计图纸、相关规范、招标文件及技术要求 | D46: t | E46: 77.28 | F46: 906.97664 | G46: 70091.155 | H46: 77.28 | I46: 1290 | J46: 99691.2 | K46: =+Q46-Z46 -> 0 | L46: 906.97664 | M46: =+L46*K46 -> 0 | N46: =+K46 -> 0 | O46: 1290 | P46: =+O46*N46 -> 0 | Q46: 77.28 | R46: 906.97664 | S46: =+R46*Q46 -> 70091.155 | T46: =+Q46 -> 77.28 | U46: 1290 | V46: =+U46*T46 -> 99691.2 | Z46: 77.28
A47: 2.14 | B47: 现浇构件钢筋 | C47: (1)钢筋种类、规格:螺纹钢制安Ⅲ级(HRB400E)φ28~32mm_x000D_ (2)满足设计图纸、相关规范、招标文件及技术要求 | D47: t | E47: 10.911 | F47: 805.99385 | G47: 8794.1989 | H47: 10.911 | I47: 1290 | J47: 14075.19 | K47: =+Q47-Z47 -> 0 | L47: 805.99385 | M47: =+L47*K47 -> 0 | N47: =+K47 -> 0 | O47: 1290 | P47: =+O47*N47 -> 0 | Q47: 10.911 | R47: 805.99385 | S47: =+R47*Q47 -> 8794.1989 | T47: =+Q47 -> 10.911 | U47: 1290 | V47: =+U47*T47 -> 14075.19 | Z47: 10.911
A48: 2.15 | B48: 现浇构件钢筋 | C48: (1)钢筋种类、规格:螺纹钢制安Ⅲ级(HRB400E)φ36~40mm_x000D_ (2)满足设计图纸、相关规范、招标文件及技术要求 | D48: t | E48: 0.2 | F48: 805.99385 | G48: 161.19877 | H48: 0.2 | I48: 1290 | J48: 258 | K48: =+Q48-Z48 -> 0 | L48: 805.99385 | M48: =+L48*K48 -> 0 | N48: =+K48 -> 0 | O48: 1290 | P48: =+O48*N48 -> 0 | Q48: 0 | R48: 805.99385 | S48: =+R48*Q48 -> 0 | T48: =+Q48 -> 0 | U48: 1290 | V48: =+U48*T48 -> 0 | Z48: 0
A49: 2.16 | B49: 现浇构件钢筋 （箍筋） | C49: (1)钢筋种类、规格:圆钢制安 φ6mm_x000D_ (2)满足设计图纸、相关规范、招标文件及技术要求 | D49: t | E49: 2.469 | F49: 1706.5494 | G49: 4213.4705 | H49: 2.469 | I49: 1290 | J49: 3185.01 | K49: =+Q49-Z49 -> 0 | L49: 1706.5494 | M49: =+L49*K49 -> 0 | N49: =+K49 -> 0 | O49: 1290 | P49: =+O49*N49 -> 0 | R49: 1706.5494 | S49: =+R49*Q49 -> 0 | T49: =+Q49 -> 0 | U49: 1290 | V49: =+U49*T49 -> 0
A50: 2.17 | B50: 现浇构件钢筋 （箍筋） | C50: (1)钢筋种类、规格:圆钢制安 φ8~10mm_x000D_ (2)满足设计图纸、相关规范、招标文件及技术要求 | D50: t | E50: 1.676 | F50: 1038.8603 | G50: 1741.1299 | H50: 1.676 | I50: 1290 | J50: 2162.04 | K50: =+Q50-Z50 -> 0 | L50: 1038.8603 | M50: =+L50*K50 -> 0 | N50: =+K50 -> 0 | O50: 1290 | P50: =+O50*N50 -> 0 | R50: 1038.8603 | S50: =+R50*Q50 -> 0 | T50: =+Q50 -> 0 | U50: 1290 | V50: =+U50*T50 -> 0
A51: 2.18 | B51: 现浇构件钢筋 （箍筋） | C51: (1)钢筋种类、规格:螺纹钢制安Ⅲ级(HRB400E)φ6mm_x000D_ (2)满足设计图纸、相关规范、招标文件及技术要求 | D51: t | E51: 5.325 | F51: 1706.5494 | G51: 9087.3756 | H51: 5.325 | I51: 1290 | J51: 6869.25 | K51: =+Q51-Z51 -> 0 | L51: 1706.5494 | M51: =+L51*K51 -> 0 | N51: =+K51 -> 0 | O51: 1290 | P51: =+O51*N51 -> 0 | Q51: 5.325 | R51: 1706.5494 | S51: =+R51*Q51 -> 9087.3756 | T51: =+Q51 -> 5.325 | U51: 1290 | V51: =+U51*T51 -> 6869.25 | Z51: 5.325
A52: 2.19 | B52: 现浇构件钢筋 （箍筋） | C52: (1)钢筋种类、规格:螺纹钢制安Ⅲ级(HRB400E)φ8mm_x000D_ (2)满足设计图纸、相关规范、招标文件及技术要求 | D52: t | E52: 30.246 | F52: 1706.5494 | G52: 51616.293 | H52: 30.246 | I52: 1290 | J52: 39017.34 | K52: =+Q52-Z52 -> 0 | L52: 1706.5494 | M52: =+L52*K52 -> 0 | N52: =+K52 -> 0 | O52: 1290 | P52: =+O52*N52 -> 0 | Q52: 30.246 | R52: 1706.5494 | S52: =+R52*Q52 -> 51616.293 | T52: =+Q52 -> 30.246 | U52: 1290 | V52: =+U52*T52 -> 39017.34 | Z52: 30.246
A53: 2.2 | B53: 现浇构件钢筋 （箍筋） | C53: (1)钢筋种类、规格:螺纹钢制安Ⅲ级(HRB400E)φ10mm_x000D_ (2)满足设计图纸、相关规范、招标文件及技术要求 | D53: t | E53: 74.192 | F53: 1706.5494 | G53: 126612.31 | H53: 74.192 | I53: 1290 | J53: 95707.68 | K53: =+Q53-Z53 -> 0 | L53: 1706.5494 | M53: =+L53*K53 -> 0 | N53: =+K53 -> 0 | O53: 1290 | P53: =+O53*N53 -> 0 | Q53: 42.624 | R53: 1706.5494 | S53: =+R53*Q53 -> 72739.962 | T53: =+Q53 -> 42.624 | U53: 1290 | V53: =+U53*T53 -> 54984.96 | Z53: 42.624
A54: 2.21 | B54: 现浇构件钢筋 （箍筋） | C54: (1)钢筋种类、规格:螺纹钢制安Ⅲ级(HRB400E)φ12mm_x000D_ (2)满足设计图纸、相关规范、招标文件及技术要求 | D54: t | E54: 23.106 | F54: 1038.8603 | G54: 24003.907 | H54: 23.106 | I54: 1290 | J54: 29806.74 | K54: =+Q54-Z54 -> 0 | L54: 1038.8603 | M54: =+L54*K54 -> 0 | N54: =+K54 -> 0 | O54: 1290 | P54: =+O54*N54 -> 0 | Q54: 63.069 | R54: 1038.8603 | S54: =+R54*Q54 -> 65519.882 | T54: =+Q54 -> 63.069 | U54: 1290 | V54: =+U54*T54 -> 81359.01 | Z54: 63.069
A55: 2.22 | B55: 现浇构件钢筋 （箍筋） | C55: (1)钢筋种类、规格:螺纹钢制安Ⅲ级(HRB400E)φ14mm_x000D_ (2)满足设计图纸、相关规范、招标文件及技术要求 | D55: t | E55: 18.609 | F55: 1038.8603 | G55: 19332.152 | H55: 18.609 | I55: 1290 | J55: 24005.61 | K55: =+Q55-Z55 -> 0 | L55: 1038.8603 | M55: =+L55*K55 -> 0 | N55: =+K55 -> 0 | O55: 1290 | P55: =+O55*N55 -> 0 | Q55: 17.654 | R55: 1038.8603 | S55: =+R55*Q55 -> 18340.04 | T55: =+Q55 -> 17.654 | U55: 1290 | V55: =+U55*T55 -> 22773.66 | Z55: 17.654
A56: 2.23 | B56: 现浇构件钢筋 （箍筋） | C56: (1)钢筋种类、规格:螺纹钢制安Ⅲ级(HRB400E)φ16mm_x000D_ (2)满足设计图纸、相关规范、招标文件及技术要求 | D56: t | E56: 62.289 | F56: 1038.8603 | G56: 64709.571 | H56: 62.289 | I56: 1290 | J56: 80352.81 | K56: =+Q56-Z56 -> 0 | L56: 1038.8603 | M56: =+L56*K56 -> 0 | N56: =+K56 -> 0 | O56: 1290 | P56: =+O56*N56 -> 0 | Q56: 56.475 | R56: 1038.8603 | S56: =+R56*Q56 -> 58669.637 | T56: =+Q56 -> 56.475 | U56: 1290 | V56: =+U56*T56 -> 72852.75 | Z56: 56.475
A57: 2.24 | B57: 现浇构件钢筋 （箍筋） | C57: (1)钢筋种类、规格:螺纹钢制安Ⅲ级(HRB400E)φ18mm_x000D_ (2)满足设计图纸、相关规范、招标文件及技术要求 | D57: t | E57: 32.457 | F57: 1038.8603 | G57: 33718.29 | H57: 32.457 | I57: 1290 | J57: 41869.53 | K57: =+Q57-Z57 -> 0 | L57: 1038.8603 | M57: =+L57*K57 -> 0 | N57: =+K57 -> 0 | O57: 1290 | P57: =+O57*N57 -> 0 | Q57: 29.476 | R57: 1038.8603 | S57: =+R57*Q57 -> 30621.447 | T57: =+Q57 -> 29.476 | U57: 1290 | V57: =+U57*T57 -> 38024.04 | Z57: 29.476
A58: 2.25 | B58: 现浇构件钢筋 （箍筋） | C58: (1)钢筋种类、规格:螺纹钢制安Ⅲ级(HRB400E)φ20mm_x000D_ (2)满足设计图纸、相关规范、招标文件及技术要求 | D58: t | E58: 0.94 | F58: 1038.8603 | G58: 976.52872 | H58: 0.94 | I58: 1290 | J58: 1212.6 | K58: =+Q58-Z58 -> 0 | L58: 1038.8603 | M58: =+L58*K58 -> 0 | N58: =+K58 -> 0 | O58: 1290 | P58: =+O58*N58 -> 0 | Q58: 0 | R58: 1038.8603 | S58: =+R58*Q58 -> 0 | T58: =+Q58 -> 0 | U58: 1290 | V58: =+U58*T58 -> 0 | Z58: 0
A59: 2.26 | B59: 机械连接 | C59: (1)连接方式:电渣压力焊_x000D_ (2)满足设计图纸、相关规范、招标文件及技术要求 | D59: 个 | E59: 10771 | F59: 7.160891 | G59: 77129.957 | H59: 10771 | I59: 0 | J59: 0 | K59: =+Q59-Z59 -> 0 | L59: 7.160891 | M59: =+L59*K59 -> 0 | N59: =+K59 -> 0 | O59: 0 | P59: =+O59*N59 -> 0 | Q59: 10771 | R59: 7.160891 | S59: =+R59*Q59 -> 77129.957 | T59: =+Q59 -> 10771 | U59: 0 | V59: =+U59*T59 -> 0 | Z59: 10771
A60: 2.27 | B60: 机械连接 | C60: (1)连接方式:套筒直螺纹接头Φ25mm以内_x000D_ (2)满足设计图纸、相关规范、招标文件及技术要求 | D60: 个 | E60: 6466 | F60: 8.8965772 | G60: 57525.268 | H60: 6466 | I60: 0 | J60: 0 | K60: =+Q60-Z60 -> 0 | L60: 8.8965772 | M60: =+L60*K60 -> 0 | N60: =+K60 -> 0 | O60: 0 | P60: =+O60*N60 -> 0 | Q60: 6466 | R60: 8.8965772 | S60: =+R60*Q60 -> 57525.268 | T60: =+Q60 -> 6466 | U60: 0 | V60: =+U60*T60 -> 0 | Z60: 6466
A61: 2.28 | B61: 机械连接 | C61: (1)连接方式:套筒直螺纹接头Φ25mm以外_x000D_ (2)满足设计图纸、相关规范、招标文件及技术要求 | D61: 个 | E61: 148 | F61: 10.58484 | G61: 1566.5564 | H61: 148 | I61: 0 | J61: 0 | K61: =+Q61-Z61 -> 0 | L61: 10.58484 | M61: =+L61*K61 -> 0 | N61: =+K61 -> 0 | O61: 0 | P61: =+O61*N61 -> 0 | Q61: 229 | R61: 10.58484 | S61: =+R61*Q61 -> 2423.9284 | T61: =+Q61 -> 229 | U61: 0 | V61: =+U61*T61 -> 0 | Z61: 229
A62: 二 | B62: 裙楼结构 | G62: 446612.47 | J62: 440819.85 | M62: =+M63+M91 -> 0 | P62: =+P63+P91 -> 0 | S62: =+S63+S91 -> 365302.72 | V62: =+V63+V91 -> 342138.71
A63: 1 | B63: 钢筋工程 | F63: 0 | M63: =SUM(M64:M90) -> 0 | P63: =SUM(P64:P90) -> 0 | S63: =SUM(S64:S90) -> 264735.65 | V63: =SUM(V64:V90) -> 275392.8
A64: 1.1 | B64: 现浇构件钢筋 | C64: (1)钢筋种类、规格:拉结筋制安(HPB300)φ6mm_x000D_ (2)满足设计图纸、相关规范、招标文件及技术要求_x000D_ (3)建筑物超高增加费 | D64: t | E64: 1.743 | F64: 1831.8223 | G64: 3192.8663 | H64: 1.743 | I64: 1480 | J64: 2579.64 | K64: =+Q64-Z64 -> 0 | L64: 1831.8223 | M64: =+L64*K64 -> 0 | N64: =+K64 -> 0 | O64: =+U64 -> 1380 | P64: =+O64*N64 -> 0 | R64: 1831.8223 | S64: =+R64*Q64 -> 0 | T64: =+Q64 -> 0 | U64: 1380 | V64: =+U64*T64 -> 0
A65: 1.2 | B65: 现浇构件钢筋 | C65: (1)钢筋种类、规格:圆钢制安 φ6mm_x000D_ (2)满足设计图纸、相关规范、招标文件及技术要求_x000D_ (3)建筑物超高增加费 | D65: t | E65: 0.2 | F65: 1360.6831 | G65: 272.13662 | H65: 0.2 | I65: 1480 | J65: 296 | K65: =+Q65-Z65 -> 0 | L65: 1360.6831 | M65: =+L65*K65 -> 0 | N65: =+K65 -> 0 | O65: =+U65 -> 1380 | P65: =+O65*N65 -> 0 | R65: 1360.6831 | S65: =+R65*Q65 -> 0 | T65: =+Q65 -> 0 | U65: 1380 | V65: =+U65*T65 -> 0
A66: 1.3 | B66: 现浇构件钢筋 | C66: (1)钢筋种类、规格:圆钢制安 φ8~10mm及以上_x000D_ (2)满足设计图纸、相关规范、招标文件及技术要求_x000D_ (3)建筑物超高增加费 | D66: t | E66: 1.1 | F66: 1052.357 | G66: 1157.5927 | H66: 1.1 | I66: 1480 | J66: 1628 | K66: =+Q66-Z66 -> 0 | L66: 1052.357 | M66: =+L66*K66 -> 0 | N66: =+K66 -> 0 | O66: =+U66 -> 1380 | P66: =+O66*N66 -> 0 | R66: 1052.357 | S66: =+R66*Q66 -> 0 | T66: =+Q66 -> 0 | U66: 1380 | V66: =+U66*T66 -> 0
A67: 1.4 | B67: 现浇构件钢筋 | C67: (1)钢筋种类、规格:螺纹钢制安Ⅲ级(HRB400E)φ6mm_x000D_ (2)满足设计图纸、相关规范、招标文件及技术要求_x000D_ (3)建筑物超高增加费 | D67: t | E67: 0.006 | F67: 1127.2381 | G67: 6.7634284 | H67: 0.006 | I67: 1480 | J67: 8.88 | K67: =+Q67-Z67 -> 0 | L67: 1127.2381 | M67: =+L67*K67 -> 0 | N67: =+K67 -> 0 | O67: =+U67 -> 1380 | P67: =+O67*N67 -> 0 | R67: 1127.2381 | S67: =+R67*Q67 -> 0 | T67: =+Q67 -> 0 | U67: 1380 | V67: =+U67*T67 -> 0
A68: 1.5 | B68: 现浇构件钢筋 | C68: (1)钢筋种类、规格:螺纹钢制安Ⅲ级(HRB400E)φ8mm_x000D_ (2)满足设计图纸、相关规范、招标文件及技术要求_x000D_ (3)建筑物超高增加费 | D68: t | E68: 21.638 | F68: 1127.1053 | G68: 24388.304 | H68: 21.638 | I68: 1480 | J68: 32024.24 | K68: =+Q68-Z68 -> 0 | L68: 1127.1053 | M68: =+L68*K68 -> 0 | N68: =+K68 -> 0 | O68: =+U68 -> 1380 | P68: =+O68*N68 -> 0 | Q68: 17.54 | R68: 1127.1053 | S68: =+R68*Q68 -> 19769.427 | T68: =+Q68 -> 17.54 | U68: 1380 | V68: =+U68*T68 -> 24205.2 | Z68: 17.54
A69: 1.6 | B69: 现浇构件钢筋 | C69: (1)钢筋种类、规格:螺纹钢制安Ⅲ级(HRB400E)φ10mm_x000D_ (2)满足设计图纸、相关规范、招标文件及技术要求_x000D_ (3)建筑物超高增加费 | D69: t | E69: 12.745 | F69: 1127.1053 | G69: 14364.957 | H69: 12.745 | I69: 1480 | J69: 18862.6 | K69: =+Q69-Z69 -> 0 | L69: 1127.1053 | M69: =+L69*K69 -> 0 | N69: =+K69 -> 0 | O69: =+U69 -> 1380 | P69: =+O69*N69 -> 0 | Q69: 13.63 | R69: 1127.1053 | S69: =+R69*Q69 -> 15362.445 | T69: =+Q69 -> 13.63 | U69: 1380 | V69: =+U69*T69 -> 18809.4 | Z69: 13.63
A70: 1.7 | B70: 现浇构件钢筋 | C70: (1)钢筋种类、规格:螺纹钢制安Ⅲ级(HRB400E)φ12mm_x000D_ (2)满足设计图纸、相关规范、招标文件及技术要求_x000D_ (3)建筑物超高增加费 | D70: t | E70: 14.325 | F70: 1002.1359 | G70: 14355.596 | H70: 14.325 | I70: 1480 | J70: 21201 | K70: =+Q70-Z70 -> 0 | L70: 1002.1359 | M70: =+L70*K70 -> 0 | N70: =+K70 -> 0 | O70: =+U70 -> 1380 | P70: =+O70*N70 -> 0 | Q70: 6.29 | R70: 1002.1359 | S70: =+R70*Q70 -> 6303.4346 | T70: =+Q70 -> 6.29 | U70: 1380 | V70: =+U70*T70 -> 8680.2 | Z70: 6.29
A71: 1.8 | B71: 现浇构件钢筋 | C71: (1)钢筋种类、规格:螺纹钢制安Ⅲ级(HRB400E)φ14mm_x000D_ (2)满足设计图纸、相关规范、招标文件及技术要求_x000D_ (3)建筑物超高增加费 | D71: t | E71: 3.268 | F71: 1002.1359 | G71: 3274.98 | H71: 3.268 | I71: 1480 | J71: 4836.64 | K71: =+Q71-Z71 -> 0 | L71: 1002.1359 | M71: =+L71*K71 -> 0 | N71: =+K71 -> 0 | O71: =+U71 -> 1380 | P71: =+O71*N71 -> 0 | Q71: 3.05 | R71: 1002.1359 | S71: =+R71*Q71 -> 3056.5144 | T71: =+Q71 -> 3.05 | U71: 1380 | V71: =+U71*T71 -> 4209 | Z71: 3.05
A72: 1.9 | B72: 现浇构件钢筋 | C72: (1)钢筋种类、规格:螺纹钢制安Ⅲ级(HRB400E)φ16mm_x000D_ (2)满足设计图纸、相关规范、招标文件及技术要求_x000D_ (3)建筑物超高增加费 | D72: t | E72: 17.43 | F72: 1002.1454 | G72: 17467.394 | H72: 17.43 | I72: 1480 | J72: 25796.4 | K72: =+Q72-Z72 -> 0 | L72: 1002.1454 | M72: =+L72*K72 -> 0 | N72: =+K72 -> 0 | O72: =+U72 -> 1380 | P72: =+O72*N72 -> 0 | Q72: 10.78 | R72: 1002.1454 | S72: =+R72*Q72 -> 10803.127 | T72: =+Q72 -> 10.78 | U72: 1380 | V72: =+U72*T72 -> 14876.4 | Z72: 10.78
A73: 1.1 | B73: 现浇构件钢筋 | C73: (1)钢筋种类、规格:螺纹钢制安Ⅲ级(HRB400E)φ18mm_x000D_ (2)满足设计图纸、相关规范、招标文件及技术要求_x000D_ (3)建筑物超高增加费 | D73: t | E73: 9.786 | F73: 1002.1359 | G73: 9806.9016 | H73: 9.786 | I73: 1480 | J73: 14483.28 | K73: =+Q73-Z73 -> 0 | L73: 1002.1359 | M73: =+L73*K73 -> 0 | N73: =+K73 -> 0 | O73: =+U73 -> 1380 | P73: =+O73*N73 -> 0 | Q73: 6.76 | R73: 1002.1359 | S73: =+R73*Q73 -> 6774.4385 | T73: =+Q73 -> 6.76 | U73: 1380 | V73: =+U73*T73 -> 9328.8 | Z73: 6.76
A74: 1.11 | B74: 现浇构件钢筋 | C74: (1)钢筋种类、规格:螺纹钢制安Ⅲ级(HRB400E)φ20mm_x000D_ (2)满足设计图纸、相关规范、招标文件及技术要求_x000D_ (3)建筑物超高增加费 | D74: t | E74: 16.775 | F74: 1002.1359 | G74: 16810.829 | H74: 16.775 | I74: 1480 | J74: 24827 | K74: =+Q74-Z74 -> 0 | L74: 1002.1359 | M74: =+L74*K74 -> 0 | N74: =+K74 -> 0 | O74: =+U74 -> 1380 | P74: =+O74*N74 -> 0 | Q74: 13.27 | R74: 1002.1359 | S74: =+R74*Q74 -> 13298.343 | T74: =+Q74 -> 13.27 | U74: 1380 | V74: =+U74*T74 -> 18312.6 | Z74: 13.27
A75: 1.12 | B75: 现浇构件钢筋 | C75: (1)钢筋种类、规格:螺纹钢制安Ⅲ级(HRB400E)φ22mm_x000D_ (2)满足设计图纸、相关规范、招标文件及技术要求_x000D_ (3)建筑物超高增加费 | D75: t | E75: 12.006 | F75: 1002.1454 | G75: 12031.757 | H75: 12.006 | I75: 1480 | J75: 17768.88 | K75: =+Q75-Z75 -> 0 | L75: 1002.1454 | M75: =+L75*K75 -> 0 | N75: =+K75 -> 0 | O75: =+U75 -> 1380 | P75: =+O75*N75 -> 0 | Q75: 12.64 | R75: 1002.1454 | S75: =+R75*Q75 -> 12667.117 | T75: =+Q75 -> 12.64 | U75: 1380 | V75: =+U75*T75 -> 17443.2 | Z75: 12.64
A76: 1.13 | B76: 现浇构件钢筋 | C76: (1)钢筋种类、规格:螺纹钢制安Ⅲ级(HRB400E)φ25mm_x000D_ (2)满足设计图纸、相关规范、招标文件及技术要求_x000D_ (3)建筑物超高增加费 | D76: t | E76: 24.052 | F76: 1002.1454 | G76: 24103.6 | H76: 24.052 | I76: 1480 | J76: 35596.96 | K76: =+Q76-Z76 -> 0 | L76: 1002.1454 | M76: =+L76*K76 -> 0 | N76: =+K76 -> 0 | O76: =+U76 -> 1380 | P76: =+O76*N76 -> 0 | Q76: 25.05 | R76: 1002.1454 | S76: =+R76*Q76 -> 25103.741 | T76: =+Q76 -> 25.05 | U76: 1380 | V76: =+U76*T76 -> 34569 | Z76: 25.05
A77: 1.14 | B77: 现浇构件钢筋 | C77: (1)钢筋种类、规格:螺纹钢制安Ⅲ级(HRB400E)φ28~32mm_x000D_ (2)满足设计图纸、相关规范、招标文件及技术要求_x000D_ (3)建筑物超高增加费 | D77: t | E77: 16.812 | F77: 887.54265 | G77: 14921.367 | H77: 16.812 | I77: 1480 | J77: 24881.76 | K77: =+Q77-Z77 -> 0 | L77: 887.54265 | M77: =+L77*K77 -> 0 | N77: =+K77 -> 0 | O77: =+U77 -> 1380 | P77: =+O77*N77 -> 0 | Q77: 15.01 | R77: 887.54265 | S77: =+R77*Q77 -> 13322.015 | T77: =+Q77 -> 15.01 | U77: 1380 | V77: =+U77*T77 -> 20713.8 | Z77: 15.01
A78: 1.15 | B78: 现浇构件钢筋 | C78: (1)钢筋种类、规格:螺纹钢制安Ⅲ级(HRB400E)φ36~40mm_x000D_ (2)满足设计图纸、相关规范、招标文件及技术要求_x000D_ (3)建筑物超高增加费 | D78: t | E78: 0.2 | F78: 887.56162 | G78: 177.51232 | H78: 0.2 | I78: 1480 | J78: 296 | K78: =+Q78-Z78 -> 0 | L78: 887.56162 | M78: =+L78*K78 -> 0 | N78: =+K78 -> 0 | O78: =+U78 -> 1380 | P78: =+O78*N78 -> 0 | R78: 887.56162 | S78: =+R78*Q78 -> 0 | T78: =+Q78 -> 0 | U78: 1380 | V78: =+U78*T78 -> 0
A79: 1.16 | B79: 现浇构件钢筋 （箍筋） | C79: (1)钢筋种类、规格:圆钢制安 φ6mm_x000D_ (2)满足设计图纸、相关规范、招标文件及技术要求_x000D_ (3)建筑物超高增加费 | D79: t | E79: 0.541 | F79: 1874.56 | G79: 1014.137 | H79: 0.541 | I79: 1480 | J79: 800.68 | K79: =+Q79-Z79 -> 0 | L79: 1874.56 | M79: =+L79*K79 -> 0 | N79: =+K79 -> 0 | O79: =+U79 -> 1380 | P79: =+O79*N79 -> 0 | R79: 1874.56 | S79: =+R79*Q79 -> 0 | T79: =+Q79 -> 0 | U79: 1380 | V79: =+U79*T79 -> 0
A80: 1.17 | B80: 现浇构件钢筋 （箍筋） | C80: (1)钢筋种类、规格:圆钢制安 φ8~10mm及以上_x000D_ (2)满足设计图纸、相关规范、招标文件及技术要求_x000D_ (3)建筑物超高增加费 | D80: t | E80: 1.005 | F80: 1142.8877 | G80: 1148.6021 | H80: 1.005 | I80: 1480 | J80: 1487.4 | K80: =+Q80-Z80 -> 0 | L80: 1142.8877 | M80: =+L80*K80 -> 0 | N80: =+K80 -> 0 | O80: =+U80 -> 1380 | P80: =+O80*N80 -> 0 | R80: 1142.8877 | S80: =+R80*Q80 -> 0 | T80: =+Q80 -> 0 | U80: 1380 | V80: =+U80*T80 -> 0
A81: 1.18 | B81: 现浇构件钢筋 （箍筋） | C81: (1)钢筋种类、规格:螺纹钢制安Ⅲ级(HRB400E)φ6mm_x000D_ (2)满足设计图纸、相关规范、招标文件及技术要求_x000D_ (3)建筑物超高增加费 | D81: t | E81: 1.435 | F81: 1874.5411 | G81: 2689.9664 | H81: 1.435 | I81: 1480 | J81: 2123.8 | K81: =+Q81-Z81 -> 0 | L81: 1874.5411 | M81: =+L81*K81 -> 0 | N81: =+K81 -> 0 | O81: =+U81 -> 1380 | P81: =+O81*N81 -> 0 | Q81: 1.26 | R81: 1874.5411 | S81: =+R81*Q81 -> 2361.9217 | T81: =+Q81 -> 1.26 | U81: 1380 | V81: =+U81*T81 -> 1738.8 | Z81: 1.26
A82: 1.19 | B82: 现浇构件钢筋 （箍筋） | C82: (1)钢筋种类、规格:螺纹钢制安Ⅲ级(HRB400E)φ8mm_x000D_ (2)满足设计图纸、相关规范、招标文件及技术要求_x000D_ (3)建筑物超高增加费 | D82: t | E82: 9.272 | F82: 1874.5505 | G82: 17380.833 | H82: 9.272 | I82: 1480 | J82: 13722.56 | K82: =+Q82-Z82 -> 0 | L82: 1874.5505 | M82: =+L82*K82 -> 0 | N82: =+K82 -> 0 | O82: =+U82 -> 1380 | P82: =+O82*N82 -> 0 | Q82: 11.47 | R82: 1874.5505 | S82: =+R82*Q82 -> 21501.095 | T82: =+Q82 -> 11.47 | U82: 1380 | V82: =+U82*T82 -> 15828.6 | Z82: 11.47
A83: 1.2 | B83: 现浇构件钢筋 （箍筋） | C83: (1)钢筋种类、规格:螺纹钢制安Ⅲ级(HRB400E)φ10mm_x000D_ (2)满足设计图纸、相关规范、招标文件及技术要求_x000D_ (3)建筑物超高增加费 | D83: t | E83: 28.097 | F83: 1874.5505 | G83: 52669.247 | H83: 28.097 | I83: 1480 | J83: 41583.56 | K83: =+Q83-Z83 -> 0 | L83: 1874.5505 | M83: =+L83*K83 -> 0 | N83: =+K83 -> 0 | O83: =+U83 -> 1380 | P83: =+O83*N83 -> 0 | Q83: 23.58 | R83: 1874.5505 | S83: =+R83*Q83 -> 44201.902 | T83: =+Q83 -> 23.58 | U83: 1380 | V83: =+U83*T83 -> 32540.4 | Z83: 23.58
A84: 1.21 | B84: 现浇构件钢筋 （箍筋） | C84: (1)钢筋种类、规格:螺纹钢制安Ⅲ级(HRB400E)φ12mm_x000D_ (2)满足设计图纸、相关规范、招标文件及技术要求_x000D_ (3)建筑物超高增加费 | D84: t | E84: 17.469 | F84: 1142.8972 | G84: 19965.271 | H84: 17.469 | I84: 1480 | J84: 25854.12 | K84: =+Q84-Z84 -> 0 | L84: 1142.8972 | M84: =+L84*K84 -> 0 | N84: =+K84 -> 0 | O84: =+U84 -> 1380 | P84: =+O84*N84 -> 0 | Q84: 39.23 | R84: 1142.8972 | S84: =+R84*Q84 -> 44835.856 | T84: =+Q84 -> 39.23 | U84: 1380 | V84: =+U84*T84 -> 54137.4 | Z84: 39.23
A85: 1.22 | B85: 现浇构件钢筋 （箍筋） | C85: (1)钢筋种类、规格:螺纹钢制安Ⅲ级(HRB400E)φ14mm_x000D_ (2)满足设计图纸、相关规范、招标文件及技术要求_x000D_ (3)建筑物超高增加费 | D85: t | E85: 2.864 | F85: 1142.8972 | G85: 3273.2575 | H85: 2.864 | I85: 1480 | J85: 4238.72 | K85: =+Q85-Z85 -> 0 | L85: 1142.8972 | M85: =+L85*K85 -> 0 | N85: =+K85 -> 0 | O85: =+U85 -> 1380 | P85: =+O85*N85 -> 0 | R85: 1142.8972 | S85: =+R85*Q85 -> 0 | T85: =+Q85 -> 0 | U85: 1380 | V85: =+U85*T85 -> 0
A86: 1.23 | B86: 现浇构件钢筋 （箍筋） | C86: (1)钢筋种类、规格:螺纹钢制安Ⅲ级(HRB400E)φ16mm_x000D_ (2)满足设计图纸、相关规范、招标文件及技术要求_x000D_ (3)建筑物超高增加费 | D86: t | E86: 10.623 | F86: 1142.8972 | G86: 12140.997 | H86: 10.623 | I86: 1480 | J86: 15722.04 | K86: =+Q86-Z86 -> 0 | L86: 1142.8972 | M86: =+L86*K86 -> 0 | N86: =+K86 -> 0 | O86: =+U86 -> 1380 | P86: =+O86*N86 -> 0 | R86: 1142.8972 | S86: =+R86*Q86 -> 0 | T86: =+Q86 -> 0 | U86: 1380 | V86: =+U86*T86 -> 0
A87: 1.24 | B87: 现浇构件钢筋 （箍筋） | C87: (1)钢筋种类、规格:螺纹钢制安Ⅲ级(HRB400E)φ18mm_x000D_ (2)满足设计图纸、相关规范、招标文件及技术要求_x000D_ (3)建筑物超高增加费 | D87: t | E87: 28.237 | F87: 1142.8972 | G87: 32271.988 | H87: 28.237 | I87: 1480 | J87: 41790.76 | K87: =+Q87-Z87 -> 0 | L87: 1142.8972 | M87: =+L87*K87 -> 0 | N87: =+K87 -> 0 | O87: =+U87 -> 1380 | P87: =+O87*N87 -> 0 | R87: 1142.8972 | S87: =+R87*Q87 -> 0 | T87: =+Q87 -> 0 | U87: 1380 | V87: =+U87*T87 -> 0
A88: 1.25 | B88: 机械连接 | C88: (1)连接方式:电渣压力焊_x000D_ (2)满足设计图纸、相关规范、招标文件及技术要求_x000D_ (3)建筑物超高增加费 | D88: 个 | E88: 2157 | F88: 8.2231689 | G88: 17737.375 | H88: 2157 | J88: 0 | K88: =+Q88-Z88 -> 0 | L88: 8.2231689 | M88: =+L88*K88 -> 0 | N88: =+K88 -> 0 | O88: =+U88 -> 0 | P88: =+O88*N88 -> 0 | Q88: 2182 | R88: 8.2231689 | S88: =+R88*Q88 -> 17942.954 | T88: =+Q88 -> 2182 | U88: 0 | V88: =+U88*T88 -> 0 | Z88: 2182
A89: 1.26 | B89: 机械连接 | C89: (1)连接方式:套筒直螺纹接头Φ25mm以内_x000D_ (2)满足设计图纸、相关规范、招标文件及技术要求_x000D_ (3)建筑物超高增加费 | D89: 个 | E89: 404 | F89: 10.21494 | G89: 4126.8357 | H89: 404 | J89: 0 | K89: =+Q89-Z89 -> 0 | L89: 10.21494 | M89: =+L89*K89 -> 0 | N89: =+K89 -> 0 | O89: =+U89 -> 0 | P89: =+O89*N89 -> 0 | Q89: 468 | R89: 10.21494 | S89: =+R89*Q89 -> 4780.5919 | T89: =+Q89 -> 468 | U89: 0 | V89: =+U89*T89 -> 0 | Z89: 468
A90: 1.27 | B90: 机械连接 | C90: (1)连接方式:套筒直螺纹接头Φ25mm以外_x000D_ (2)满足设计图纸、相关规范、招标文件及技术要求_x000D_ (3)建筑物超高增加费 | D90: 个 | E90: 209 | F90: 12.159288 | G90: 2541.2911 | H90: 209 | J90: 0 | K90: =+Q90-Z90 -> 0 | L90: 12.159288 | M90: =+L90*K90 -> 0 | N90: =+K90 -> 0 | O90: =+U90 -> 0 | P90: =+O90*N90 -> 0 | Q90: 218 | R90: 12.159288 | S90: =+R90*Q90 -> 2650.7247 | T90: =+Q90 -> 218 | U90: 0 | V90: =+U90*T90 -> 0 | Z90: 218
A91: 2 | B91: 钢筋混凝土工程（地上） | F91: 0 | J91: 0 | M91: =SUM(M92:M105) -> 0 | P91: =SUM(P92:P105) -> 0 | S91: =SUM(S92:S105) -> 100567.07 | V91: =SUM(V92:V105) -> 66745.91
A92: 2.1 | B92: 砼墙、柱 C60 | C92: (1)混凝土强度等级:C60泵送商品混凝土_x000D_ (2)满足设计图纸、相关规范、招标文件及技术要求_x000D_ (3)建筑物超高增加费 | D92: m3 | E92: 465.16 | F92: 92.389721 | G92: 42976.003 | H92: 465.16 | I92: 59.5 | J92: 27677.02 | K92: =+Q92-Z92 -> 0 | L92: 92.389721 | M92: =+L92*K92 -> 0 | N92: =+K92 -> 0 | O92: =+U92 -> 59.5 | P92: =+O92*N92 -> 0 | Q92: 543.45 | R92: 92.389721 | S92: =+R92*Q92 -> 50209.194 | T92: =+Q92 -> 543.45 | U92: 59.5 | V92: =+U92*T92 -> 32335.275 | Z92: 543.45
A93: 2.2 | B93: 有梁板 C30 | C93: (1)混凝土强度等级:C30泵送商品混凝土_x000D_ (2)满足设计图纸、相关规范、招标文件及技术要求_x000D_ (3)建筑物超高增加费 | D93: m3 | E93: 164.31 | F93: 84.109644 | G93: 13820.056 | H93: 164.31 | I93: 59.5 | J93: 9776.445 | K93: =+Q93-Z93 -> 0 | L93: 84.109644 | M93: =+L93*K93 -> 0 | N93: =+K93 -> 0 | O93: =+U93 -> 59.5 | P93: =+O93*N93 -> 0 | Q93: 244.07 | R93: 84.109644 | S93: =+R93*Q93 -> 20528.641 | T93: =+Q93 -> 244.07 | U93: 59.5 | V93: =+U93*T93 -> 14522.165 | Z93: 244.07
A94: 2.3 | B94: 有梁板 C30P6_x000D_ | C94: (1)混凝土强度等级:C30泵送商品混凝土，抗渗P6_x000D_ (2)满足设计图纸、相关规范、招标文件及技术要求_x000D_ (3)建筑物超高增加费 | D94: m3 | E94: 295.38 | F94: 84.109644 | G94: 24844.307 | H94: 295.38 | I94: 59.5 | J94: 17575.11 | K94: =+Q94-Z94 -> 0 | L94: 84.109644 | M94: =+L94*K94 -> 0 | N94: =+K94 -> 0 | O94: =+U94 -> 59.5 | P94: =+O94*N94 -> 0 | Q94: 295.38 | R94: 84.109644 | S94: =+R94*Q94 -> 24844.307 | T94: =+Q94 -> 295.38 | U94: 59.5 | V94: =+U94*T94 -> 17575.11 | Z94: 295.38
A95: 2.4 | B95: 直形楼梯 C30 | C95: (1)混凝土强度等级:C30泵送商品混凝土_x000D_ (2)满足设计图纸、相关规范、招标文件及技术要求_x000D_ (3)建筑物超高增加费 | D95: m3 | E95: 38.88 | F95: 128.21315 | G95: 4984.9271 | H95: 38.88 | I95: 59.5 | J95: 2313.36 | K95: =+Q95-Z95 -> 0 | L95: 128.21315 | M95: =+L95*K95 -> 0 | N95: =+K95 -> 0 | O95: =+U95 -> 59.5 | P95: =+O95*N95 -> 0 | Q95: 38.88 | R95: 128.21315 | S95: =+R95*Q95 -> 4984.9271 | T95: =+Q95 -> 38.88 | U95: 59.5 | V95: =+U95*T95 -> 2313.36 | Z95: 38.88
A96: 2.5 | B96: 构造柱 C20 | C96: (1)混凝土强度等级:C20非泵送商品混凝土_x000D_ (2)满足设计图纸、相关规范、招标文件及技术要求_x000D_ (3)建筑物超高增加费 | D96: m3 | E96: 43.1 | F96: 231.9939 | G96: 9998.9371 | H96: 43.1 | I96: 59.5 | J96: 2564.45 | K96: =+Q96-Z96 -> 0 | L96: 231.9939 | M96: =+L96*K96 -> 0 | N96: =+K96 -> 0 | O96: =+U96 -> 59.5 | P96: =+O96*N96 -> 0 | R96: 231.9939 | S96: =+R96*Q96 -> 0 | T96: =+Q96 -> 0 | U96: 59.5 | V96: =+U96*T96 -> 0
A97: 2.6 | B97: 圈、过梁 C20 | C97: (1)混凝土强度等级:C20非泵送商品混凝土_x000D_ (2)满足设计图纸、相关规范、招标文件及技术要求_x000D_ (3)建筑物超高增加费 | D97: m3 | E97: 12.85 | F97: 228.71222 | G97: 2938.952 | H97: 12.85 | I97: 59.5 | J97: 764.575 | K97: =+Q97-Z97 -> 0 | L97: 228.71222 | M97: =+L97*K97 -> 0 | N97: =+K97 -> 0 | O97: =+U97 -> 59.5 | P97: =+O97*N97 -> 0 | R97: 228.71222 | S97: =+R97*Q97 -> 0 | T97: =+Q97 -> 0 | U97: 59.5 | V97: =+U97*T97 -> 0
A98: 2.7 | B98: 门槛、反坎 C25 | C98: (1)混凝土强度等级:C25非泵送商品混凝土_x000D_ (2)满足设计图纸、相关规范、招标文件及技术要求_x000D_ (3)建筑物超高增加费 | D98: m3 | E98: 1.2 | F98: 181.50725 | G98: 217.8087 | H98: 1.2 | I98: 59.5 | J98: 71.4 | K98: =+Q98-Z98 -> 0 | L98: 181.50725 | M98: =+L98*K98 -> 0 | N98: =+K98 -> 0 | O98: =+U98 -> 59.5 | P98: =+O98*N98 -> 0 | R98: 181.50725 | S98: =+R98*Q98 -> 0 | T98: =+Q98 -> 0 | U98: 59.5 | V98: =+U98*T98 -> 0
A99: 2.8 | B99: 门槛、反坎 C20 | C99: (1)混凝土强度等级:C20非泵送商品混凝土_x000D_ (2)满足设计图纸、相关规范、招标文件及技术要求_x000D_ (3)建筑物超高增加费 | D99: m3 | E99: 13.5 | F99: 181.50725 | G99: 2450.3478 | H99: 13.5 | I99: 59.5 | J99: 803.25 | K99: =+Q99-Z99 -> 0 | L99: 181.50725 | M99: =+L99*K99 -> 0 | N99: =+K99 -> 0 | O99: =+U99 -> 59.5 | P99: =+O99*N99 -> 0 | R99: 181.50725 | S99: =+R99*Q99 -> 0 | T99: =+Q99 -> 0 | U99: 59.5 | V99: =+U99*T99 -> 0
A100: 2.9 | B100: 雨篷、悬挑板、阳台板 C30 | C100: (1)混凝土强度等级:C30非泵送商品混凝土_x000D_ (2)满足设计图纸、相关规范、招标文件及技术要求_x000D_ (3)建筑物超高增加费 | D100: m3 | E100: 69.21 | F100: 172.25025 | G100: 11921.44 | H100: 69.21 | I100: 59.5 | J100: 4117.995 | K100: =+Q100-Z100 -> 0 | L100: 172.25025 | M100: =+L100*K100 -> 0 | N100: =+K100 -> 0 | O100: =+U100 -> 59.5 | P100: =+O100*N100 -> 0 | R100: 172.25025 | S100: =+R100*Q100 -> 0 | T100: =+Q100 -> 0 | U100: 59.5 | V100: =+U100*T100 -> 0
A101: 2.1 | B101: 天沟(檐沟)、挑檐板 C30 | C101: (1)混凝土强度等级:C30非泵送商品混凝土_x000D_ (2)满足设计图纸、相关规范、招标文件及技术要求_x000D_ (3)建筑物超高增加费 | D101: m3 | E101: 46.14 | F101: 207.39079 | G101: 9569.0108 | H101: 46.14 | I101: 59.5 | J101: 2745.33 | K101: =+Q101-Z101 -> 0 | L101: 207.39079 | M101: =+L101*K101 -> 0 | N101: =+K101 -> 0 | O101: =+U101 -> 59.5 | P101: =+O101*N101 -> 0 | R101: 207.39079 | S101: =+R101*Q101 -> 0 | T101: =+Q101 -> 0 | U101: 59.5 | V101: =+U101*T101 -> 0
A102: 2.11 | B102: 扶手、压顶 C30 | C102: (1)混凝土强度等级:C30非泵送商品混凝土_x000D_ (2)满足设计图纸、相关规范、招标文件及技术要求_x000D_ (3)建筑物超高增加费 | D102: m3 | E102: 18 | F102: 193.35354 | G102: 3480.3638 | H102: 18 | J102: 0 | K102: =+Q102-Z102 -> 0 | L102: 193.35354 | M102: =+L102*K102 -> 0 | N102: =+K102 -> 0 | O102: =+U102 -> 59.5 | P102: =+O102*N102 -> 0 | R102: 193.35354 | S102: =+R102*Q102 -> 0 | T102: =+Q102 -> 0 | U102: 59.5 | V102: =+U102*T102 -> 0
A103: 2.12 | B103: 栏板 C30 | C103: (1)混凝土强度等级:C30非泵送商品混凝土_x000D_ (2)满足设计图纸、相关规范、招标文件及技术要求_x000D_ (3)建筑物超高增加费 | D103: m3 | E103: 6.21 | F103: 206.31902 | G103: 1281.2411 | H103: 6.21 | J103: 0 | K103: =+Q103-Z103 -> 0 | L103: 206.31902 | M103: =+L103*K103 -> 0 | N103: =+K103 -> 0 | O103: =+U103 -> 59.5 | P103: =+O103*N103 -> 0 | R103: 206.31902 | S103: =+R103*Q103 -> 0 | T103: =+Q103 -> 0 | U103: 59.5 | V103: =+U103*T103 -> 0
A104: 2.13 | B104: 设备基础 C30 | C104: (1)混凝土强度等级:C30非泵送商品混凝土_x000D_ (2)满足设计图纸、相关规范、招标文件及技术要求_x000D_ (3)建筑物超高增加费 | D104: m3 | E104: 10.4 | F104: 92.28539 | G104: 959.76806 | H104: 10.4 | J104: 0 | K104: =+Q104-Z104 -> 0 | L104: 92.28539 | M104: =+L104*K104 -> 0 | N104: =+K104 -> 0 | O104: =+U104 -> 59.5 | P104: =+O104*N104 -> 0 | R104: 92.28539 | S104: =+R104*Q104 -> 0 | T104: =+Q104 -> 0 | U104: 59.5 | V104: =+U104*T104 -> 0
A105: 2.14 | B105: 混凝土泵送费扣减 | D105: 项 | E105: 1 | F105: -6123.0455 | G105: -6123.0455 | H105: 1 | J105: 0 | K105: =+Q105-Z105 -> 0 | L105: -6123.0455 | M105: =+L105*K105 -> 0 | N105: =+K105 -> 0 | P105: =+O105*N105 -> 0 | R105: -6123.0455 | S105: =+R105*Q105 -> 0 | V105: =+U105*T105 -> 0
A106: 三 | B106: 1#塔楼结构 | G106: 1541884.5 | J106: 1453947.2 | M106: =+M107+M135+M156 -> 176749.46 | P106: =+P107+P135+P156 -> 173500.82 | S106: =+S107+S135+S156 -> 679877.49 | V106: =+V107+V135+V156 -> 643023.32
A107: 1 | B107: 钢筋工程 | F107: 0 | M107: =SUM(M108:M134) -> 123669.1 | P107: =SUM(P108:P134) -> 138162.84 | S107: =SUM(S108:S134) -> 477656.16 | V107: =SUM(V108:V134) -> 509018.52
A108: 1.1 | B108: 现浇构件钢筋 | C108: (1)钢筋种类、规格:拉结筋制安(HPB300)φ6mm_x000D_ (2)满足设计图纸、相关规范、招标文件及技术要求_x000D_ (3)建筑物超高增加费 | D108: t | E108: 3.55 | F108: 1831.8223 | G108: 6502.9692 | H108: 3.55 | I108: 1480 | J108: 5254 | K108: =+Q108-Z108 -> 0 | L108: 1831.8223 | M108: =+L108*K108 -> 0 | N108: =+K108 -> 0 | O108: =+U108 -> 1380 | P108: =+O108*N108 -> 0 | R108: 1831.8223 | S108: =+R108*Q108 -> 0 | T108: =+Q108 -> 0 | U108: 1380 | V108: =+U108*T108 -> 0
A109: 1.2 | B109: 现浇构件钢筋 | C109: (1)钢筋种类、规格:圆钢制安 φ6mm_x000D_ (2)满足设计图纸、相关规范、招标文件及技术要求_x000D_ (3)建筑物超高增加费 | D109: t | E109: 0.1 | F109: 1360.6357 | G109: 136.06357 | H109: 0.1 | I109: 1480 | J109: 148 | K109: =+Q109-Z109 -> 0 | L109: 1360.6357 | M109: =+L109*K109 -> 0 | N109: =+K109 -> 0 | O109: =+U109 -> 1380 | P109: =+O109*N109 -> 0 | R109: 1360.6357 | S109: =+R109*Q109 -> 0 | T109: =+Q109 -> 0 | U109: 1380 | V109: =+U109*T109 -> 0
A110: 1.3 | B110: 现浇构件钢筋 | C110: (1)钢筋种类、规格:圆钢制安 φ8~10mm及以上_x000D_ (2)满足设计图纸、相关规范、招标文件及技术要求_x000D_ (3)建筑物超高增加费 | D110: t | E110: 0.5 | F110: 1052.338 | G110: 526.16899 | H110: 0.5 | I110: 1480 | J110: 740 | K110: =+Q110-Z110 -> 0 | L110: 1052.338 | M110: =+L110*K110 -> 0 | N110: =+K110 -> 0 | O110: =+U110 -> 1380 | P110: =+O110*N110 -> 0 | R110: 1052.338 | S110: =+R110*Q110 -> 0 | T110: =+Q110 -> 0 | U110: 1380 | V110: =+U110*T110 -> 0
A111: 1.4 | B111: 现浇构件钢筋 | C111: (1)钢筋种类、规格:螺纹钢制安Ⅲ级(HRB400E)φ6mm_x000D_ (2)满足设计图纸、相关规范、招标文件及技术要求_x000D_ (3)建筑物超高增加费 | D111: t | E111: 3.16 | F111: 1127.1053 | G111: 3561.6527 | H111: 3.16 | I111: 1480 | J111: 4676.8 | K111: =+Q111-Z111 -> 0 | L111: 1127.1053 | M111: =+L111*K111 -> 0 | N111: =+K111 -> 0 | O111: =+U111 -> 1380 | P111: =+O111*N111 -> 0 | R111: 1127.1053 | S111: =+R111*Q111 -> 0 | T111: =+Q111 -> 0 | U111: 1380 | V111: =+U111*T111 -> 0
...

Sheet 材料费
A1: 工程项目材料费计算表
A2: =[1]人工费!A2 -> 工程名称：
A3: 序号 | B3: 材料名称 | C3: 材料规格 | D3: 单位 | E3: 预测工程竣工数据统计 | K3: 本期数据统计 | Q3: 累计数据统计 | W3: 备注 | Z3: 上次累计数据统计
E4: 预算收入 | H4: 计划成本 | K4: 预算收入 | N4: 实际成本 | Q4: 预算收入 | T4: 实际成本 | Z4: 实际成本
E5: 工程量 | F5: 单价 | G5: 合价 | H5: 工程量 | I5: 单价 | J5: 合价 | K5: 工程量 | L5: 单价 | M5: 合价 | N5: 工程量 | O5: 单价 | P5: 合价 | Q5: 工程量 | R5: 单价 | S5: 合价 | T5: 工程量 | U5: 单价 | V5: 合价 | Z5: 工程量 | AA5: 单价 | AB5: 合价
A6: 一 | B6: 地下室结构 | E6: 0 | G6: =+G7+G33 -> 12707131 | H6: 0 | J6: =+J7+J33 -> 9739695.9 | M6: =+M7+M33 -> -203714.54 | P6: =+P7+P33 -> 2668225.5 | S6: =+S7+S33 -> 12342703 | V6: =+V7+V33 -> 15952817 | AB6: 13266956
A7: 1 | B7: 钢筋混凝土工程（地下） | E7: 0 | F7: 0 | G7: =SUM(G8:G32) -> 6709892.8 | H7: 0 | J7: =SUM(J8:J32) -> 4576549.5 | K7: =SUM(K8:K31) -> 0 | M7: =SUM(M8:M32) -> 0 | N7: =SUM(N12:N30) -> 11962 | P7: =SUM(P8:P32) -> 1186598.9 | Q7: =SUM(Q8:Q31) -> 11509.41 | S7: =SUM(S8:S32) -> 6595980.8 | T7: =SUM(T8:T31) -> 16225.5 | V7: =SUM(V8:V32) -> 6609727.1 | Z7: 15269.5 | AB7: 6227130.8
A8: 1.1 | B8: 垫层 C20 | C8: (1)混凝土强度等级:C20泵送商品混凝土_x000D_ (2)满足设计图纸、相关规范、招标文件及技术要求 | D8: m3 | E8: 530.03 | F8: 492.40373 | G8: =+F8*E8 -> 260988.75 | H8: 530.03 | I8: 332.50971 | J8: =+I8*H8 -> 176240.12 | K8: =+人工费!K8 -> 0 | L8: =+R8 -> 492.40373 | M8: =+L8*K8 -> 0 | N8: =+T8-Z8 -> -230.5 | O8: =+U8 -> 330.76633 | P8: =+N8*O8 -> -76241.639 | Q8: =+人工费!Q8 -> 530.03 | R8: 492.40373 | S8: =+R8*Q8 -> 260988.75 | T8: 257.5 | U8: 330.76633 | V8: =+U8*T8 -> 85172.33 | W8: 细砼C20 | Z8: 488 | AA8: 333.46078 | AB8: 162728.86
A9: 1.2 | B9: 基础（筏板、柱墩、桩承台、基础梁、集水坑） C35P10 | C9: (1)混凝土强度等级:C35泵送商品混凝土，抗渗P10 (2)补偿收缩混凝土，补偿收缩时≥0.02% (3)满足设计图纸、相关规范、招标文件及技术要求 | D9: m3 | E9: 3895.64 | F9: 575.56491 | G9: =+F9*E9 -> 2242193.7 | H9: 3895.64 | I9: 388.63689 | J9: =+I9*H9 -> 1513989.4 | K9: =+人工费!K9 -> 0 | L9: =+R9 -> 575.56491 | M9: =+L9*K9 -> 0 | N9: =+T9-Z9 -> -7067 | O9: =+U9 -> 330.17464 | P9: =+N9*O9 -> -2333344.2 | Q9: =+人工费!Q9 -> 3895.64 | R9: 575.56491 | S9: =+R9*Q9 -> 2242193.7 | T9: 491 | U9: 330.17464 | V9: =+U9*T9 -> 162115.75 | W9: 商砼C20 | Z9: 7558 | AA9: 397.97682 | AB9: 3007908.8
A10: 1.3 | B10: 砼墙、柱 C60 | C10: (1)混凝土强度等级:C60泵送商品混凝土 (2)满足设计图纸、相关规范、招标文件及技术要求 | D10: m3 | E10: 1201.57 | F10: 647.44888 | G10: =+F10*E10 -> 777955.15 | H10: 1201.57 | I10: 447.05485 | J10: =+I10*H10 -> 537167.7 | K10: =+人工费!K10 -> 0 | L10: =+R10 -> 647.44888 | M10: =+L10*K10 -> 0 | N10: =+T10-Z10 -> -2978.5 | O10: =+U10 -> 358.37068 | P10: =+N10*O10 -> -1067407.1 | Q10: =+人工费!Q10 -> 1201.57 | R10: 647.44888 | S10: =+R10*Q10 -> 777955.15 | T10: 36.5 | U10: 358.37068 | V10: =+U10*T10 -> 13080.53 | W10: 细砼C25 | Z10: 3015 | AA10: 449.36519 | AB10: 1354836
A11: 1.4 | B11: 砼墙、柱 C40 | C11: (1)混凝土强度等级:C40泵送商品混凝土 (2)满足设计图纸、相关规范、招标文件及技术要求 | D11: m3 | E11: 182.21 | F11: 564.5343 | G11: =+F11*E11 -> 102863.79 | H11: 182.21 | I11: 388.70631 | J11: =+I11*H11 -> 70826.177 | K11: =+人工费!K11 -> 0 | L11: =+R11 -> 564.5343 | M11: =+L11*K11 -> 0 | N11: =+T11-Z11 -> -762 | O11: =+U11 -> 359.565 | P11: =+N11*O11 -> -273988.53 | Q11: =+人工费!Q11 -> 182.21 | R11: 564.5343 | S11: =+R11*Q11 -> 102863.79 | T11: 6 | U11: 359.565 | V11: =+U11*T11 -> 2157.39 | W11: 商砼C25 | Z11: 768 | AA11: 401.71936 | AB11: 308520.47
A12: 1.5 | B12: 砼墙、柱 C35P10_x000D_ | C12: (1)混凝土强度等级:C35泵送商品混凝土，抗渗P10_x000D_ (2)补偿收缩混凝土，补偿收缩时≥0.02%_x000D_ (3)满足设计图纸、相关规范、招标文件及技术要求 | D12: m3 | E12: 481.52 | F12: 575.56491 | G12: =+F12*E12 -> 277146.02 | H12: 481.52 | I12: 388.63689 | J12: =+I12*H12 -> 187136.44 | K12: =+人工费!K12 -> 0 | L12: =+R12 -> 575.56491 | M12: =+L12*K12 -> 0 | N12: =+T12-Z12 -> -222 | O12: =+U12 -> 367.05226 | P12: =+N12*O12 -> -81485.601 | Q12: =+人工费!Q12 -> 481.52 | R12: 575.56491 | S12: =+R12*Q12 -> 277146.02 | T12: 1142.5 | U12: 367.05226 | V12: =+U12*T12 -> 419357.2 | W12: 商砼C30 | Z12: 1364.5 | AA12: 373.9623 | AB12: 510271.56
A13: 1.6 | B13: 砼墙、柱 C35P8_x000D_ | C13: (1)混凝土强度等级:C35泵送商品混凝土，抗渗P8_x000D_ (2)补偿收缩混凝土，补偿收缩时≥0.02%_x000D_ (3)满足设计图纸、相关规范、招标文件及技术要求 | D13: m3 | E13: 394.28 | F13: 573.95253 | G13: =+F13*E13 -> 226298 | H13: 394.28 | I13: 387.37476 | J13: =+I13*H13 -> 152734.12 | K13: =+人工费!K13 -> 0 | L13: =+R13 -> 573.95253 | M13: =+L13*K13 -> 0 | N13: =+T13-Z13 -> -1193 | O13: =+U13 -> 381.905 | P13: =+V13-AB13 -> -527724.68 | Q13: =+人工费!Q13 -> 394.28 | R13: 573.95253 | S13: =+R13*Q13 -> 226298 | T13: 3 | U13: 381.905 | V13: =+U13*T13 -> 1145.715 | W13: C30 +10%膨胀剂 | Z13: 1196 | AA13: 442.19932 | AB13: 528870.39
A14: 1.7 | B14: 砼墙、柱 C35P6_x000D_ | C14: (1)混凝土强度等级:C35泵送商品混凝土，抗渗P6_x000D_ (2)补偿收缩混凝土，补偿收缩时≥0.02%_x000D_ (3)满足设计图纸、相关规范、招标文件及技术要求 | D14: m3 | E14: 560.18 | F14: 572.33066 | G14: =+F14*E14 -> 320608.19 | H14: 560.18 | I14: 386.11262 | J14: =+I14*H14 -> 216292.57 | K14: =+人工费!K14 -> 0 | L14: =+R14 -> 572.33066 | M14: =+L14*K14 -> 0 | N14: =+T14-Z14 -> -595 | O14: =+U14 -> 0 | P14: =+V14-AB14 -> -256762.7 | Q14: =+人工费!Q14 -> 560.18 | R14: 572.33066 | S14: =+R14*Q14 -> 320608.19 | T14: 0 | U14: 0 | V14: =+U14*T14 -> 0 | W14: C30 P6 | Z14: 595 | AA14: 431.53395 | AB14: 256762.7
A15: 1.8 | B15: 砼墙、柱 C35_x000D_ | C15: (1)混凝土强度等级:C35泵送商品混凝土_x000D_ (2)满足设计图纸、相关规范、招标文件及技术要求 | D15: m3 | E15: 335.64 | F15: 545.58402 | G15: =+F15*E15 -> 183119.82 | H15: 335.64 | I15: 381.06408 | J15: =+I15*H15 -> 127900.35 | K15: =+人工费!K15 -> 0 | L15: =+R15 -> 545.58402 | M15: =+L15*K15 -> 0 | N15: =+T15-Z15 -> 413 | O15: =+U15 -> 393.29257 | P15: =+V15-AB15 -> 162429.83 | Q15: =+人工费!Q15 -> 335.64 | R15: 545.58402 | S15: =+R15*Q15 -> 183119.82 | T15: 413 | U15: 393.29257 | V15: =+U15*T15 -> 162429.83 | W15: C30 P8+8%膨胀剂 | AB15: 0
A16: 1.9 | B16: 矩形柱 C35 | C16: (1)混凝土强度等级:C35泵送商品混凝土_x000D_ (2)满足设计图纸、相关规范、招标文件及技术要求 | D16: m3 | E16: 39.15 | F16: 545.58402 | G16: =+F16*E16 -> 21359.614 | H16: 39.15 | I16: 381.06408 | J16: =+I16*H16 -> 14918.659 | K16: =+人工费!K16 -> 0 | L16: =+R16 -> 545.58402 | M16: =+L16*K16 -> 0 | N16: =+T16-Z16 -> 1956.5 | O16: =+U16 -> 375.54733 | P16: =+V16-AB16 -> 734758.36 | Q16: =+人工费!Q16 -> 39.15 | R16: 545.58402 | S16: =+R16*Q16 -> 21359.614 | T16: 1956.5 | U16: 375.54733 | V16: =+U16*T16 -> 734758.36 | W16: 商砼C35 | AB16: 0
A17: 1.1 | B17: 有梁板 (梁、板) C35P6 | C17: (1)混凝土强度等级:C35泵送商品混凝土,P6_x000D_ (2)补偿收缩混凝土，补偿收缩时≥0.02%_x000D_ (3)满足设计图纸、相关规范、招标文件及技术要求 | D17: m3 | E17: 1349.99 | F17: 572.33066 | G17: =+F17*E17 -> 772640.66 | H17: 1349.99 | I17: 386.11262 | J17: =+I17*H17 -> 521248.18 | K17: =+人工费!K17 -> 0 | L17: =+R17 -> 572.33066 | M17: =+L17*K17 -> 0 | N17: =+T17-Z17 -> 0 | O17: =+U17 -> 0 | P17: =+V17-AB17 -> 0 | Q17: =+人工费!Q17 -> 1349.99 | R17: 572.33066 | S17: =+R17*Q17 -> 772640.66 | T17: 0 | U17: 0 | V17: =+U17*T17 -> 0 | W17: C35 P6补偿收缩时≥0.02% | AB17: 0
A18: 1.11 | B18: 有梁板 (梁、板) C35 | C18: (1)混凝土强度等级:C35泵送商品混凝土_x000D_ (2)满足设计图纸、相关规范、招标文件及技术要求 | D18: m3 | E18: 1871.42 | F18: 545.58402 | G18: =+F18*E18 -> 1021016.8 | H18: 1871.42 | I18: 381.06408 | J18: =+I18*H18 -> 713130.94 | K18: =+人工费!K18 -> 0 | L18: =+R18 -> 545.58402 | M18: =+L18*K18 -> 0 | N18: =+T18-Z18 -> 771 | O18: =+U18 -> 408.21484 | P18: =+V18-AB18 -> 314733.64 | Q18: =+人工费!Q18 -> 1871.42 | R18: 545.58402 | S18: =+R18*Q18 -> 1021016.8 | T18: 771 | U18: 408.21484 | V18: =+U18*T18 -> 314733.64 | W18: C35 P8+8%膨胀剂 | AB18: 0
A19: 1.12 | B19: 有梁板 (梁、板)坡道 C35 | C19: (1)混凝土强度等级:C35泵送商品混凝土_x000D_ (2)满足设计图纸、相关规范、招标文件及技术要求 | D19: m3 | E19: 155.94 | F19: 545.58402 | G19: =+F19*E19 -> 85078.372 | H19: 155.94 | I19: 381.06408 | J19: =+I19*H19 -> 59423.132 | K19: =+人工费!K19 -> 0 | L19: =+R19 -> 545.58402 | M19: =+L19*K19 -> 0 | N19: =+T19-Z19 -> 315 | O19: =+U19 -> 380.72816 | P19: =+V19-AB19 -> 119929.37 | Q19: =+人工费!Q19 -> 155.94 | R19: 545.58402 | S19: =+R19*Q19 -> 85078.372 | T19: 315 | U19: 380.72816 | V19: =+U19*T19 -> 119929.37 | W19: C35 P10 | AB19: 0
A20: 1.13 | B20: 后浇带 基础 C40P10 | C20: (1)混凝土强度等级:C40泵送商品混凝土,P10_x000D_ (2)补偿收缩混凝土，补偿收缩时≥0.03%_x000D_ (3)满足设计图纸、相关规范、招标文件及技术要求 | D20: m3 | E20: 141.94 | F20: 593.72797 | G20: =+F20*E20 -> 84273.748 | H20: 141.94 | I20: 396.27913 | J20: =+I20*H20 -> 56247.859 | K20: =+人工费!K20 -> 0 | L20: =+R20 -> 593.72797 | M20: =+L20*K20 -> 0 | N20: =+T20-Z20 -> 4515.5 | O20: =+U20 -> 407.15036 | P20: =+V20-AB20 -> 1838487.5 | Q20: =+人工费!Q20 -> 141.94 | R20: 593.72797 | S20: =+R20*Q20 -> 84273.748 | T20: 4515.5 | U20: 407.15036 | V20: =+U20*T20 -> 1838487.5 | W20: C35 P10+8%膨胀剂 | AB20: 0
A21: 1.14 | B21: 后浇带 梁、楼板、墙 C40P8 | C21: (1)混凝土强度等级:C40泵送商品混凝土,P8_x000D_ (2)补偿收缩混凝土，补偿收缩时≥0.03%_x000D_ (3)满足设计图纸、相关规范、招标文件及技术要求 | D21: m3 | E21: 26.5 | F21: 592.11558 | G21: =+F21*E21 -> 15691.063 | H21: 26.5 | I21: 395.01699 | J21: =+I21*H21 -> 10467.95 | K21: =+人工费!K21 -> 0 | L21: =+R21 -> 592.11558 | M21: =+L21*K21 -> 0 | N21: =+T21-Z21 -> 358 | O21: =+U21 -> 385.72673 | P21: =+V21-AB21 -> 138090.17 | Q21: =+人工费!Q21 -> 26.5 | R21: 592.11558 | S21: =+R21*Q21 -> 15691.063 | T21: 358 | U21: 385.72673 | V21: =+U21*T21 -> 138090.17 | W21: 商砼C40 | AB21: 0
A22: 1.15 | B22: 后浇带 梁、楼板、墙 C40P6 | C22: (1)混凝土强度等级:C40泵送商品混凝土,P6_x000D_ (2)补偿收缩混凝土，补偿收缩时≥0.03%_x000D_ (3)满足设计图纸、相关规范、招标文件及技术要求 | D22: m3 | E22: 90.52 | F22: 590.5032 | G22: =+F22*E22 -> 53452.349 | H22: 90.52 | I22: 393.75485 | J22: =+I22*H22 -> 35642.689 | K22: =+人工费!K22 -> 0 | L22: =+R22 -> 590.5032 | M22: =+L22*K22 -> 0 | N22: =+T22-Z22 -> 149 | O22: =+U22 -> 412.42718 | P22: =+V22-AB22 -> 61451.65 | Q22: =+人工费!Q22 -> 90.52 | R22: 590.5032 | S22: =+R22*Q22 -> 53452.349 | T22: 149 | U22: 412.42718 | V22: =+U22*T22 -> 61451.65 | W22: C40+8%膨胀剂 | AB22: 0
A23: 1.16 | B23: 后浇带 梁、楼板、墙 C60P6 | C23: (1)混凝土强度等级:C60泵送商品混凝土,P6_x000D_ (2)补偿收缩混凝土，补偿收缩时≥0.03%_x000D_ (3)满足设计图纸、相关规范、招标文件及技术要求 | D23: m3 | E23: 86.71 | F23: 673.40829 | G23: =+F23*E23 -> 58391.233 | H23: 86.71 | I23: 452.1034 | J23: =+I23*H23 -> 39201.886 | K23: =+人工费!K23 -> 0 | L23: =+R23 -> 673.40829 | M23: =+L23*K23 -> 0 | N23: =+T23-Z23 -> 0 | O23: =+U23 -> 0 | P23: =+V23-AB23 -> 0 | Q23: =+人工费!Q23 -> 86.71 | R23: 673.40829 | S23: =+R23*Q23 -> 58391.233 | T23: 0 | U23: 0 | V23: =+U23*T23 -> 0 | W23: C40 P6补偿收缩时≥0.03% | AB23: 0
A24: 1.17 | B24: 后浇带 梁、楼板、墙 C40 | C24: (1)混凝土强度等级:C40泵送商品混凝土_x000D_ (2)满足设计图纸、相关规范、招标文件及技术要求 | D24: m3 | E24: 109.07 | F24: 563.74707 | G24: =+F24*E24 -> 61487.893 | H24: 109.07 | I24: 388.70631 | J24: =+I24*H24 -> 42396.197 | K24: =+人工费!K24 -> 0 | L24: =+R24 -> 563.74707 | M24: =+L24*K24 -> 0 | N24: =+T24-Z24 -> 81 | O24: =+U24 -> 418.25247 | P24: =+V24-AB24 -> 33878.45 | Q24: =+人工费!Q24 -> 109.07 | R24: 563.74707 | S24: =+R24*Q24 -> 61487.893 | T24: 81 | U24: 418.25247 | V24: =+U24*T24 -> 33878.45 | W24: C40 P8+8%膨胀剂 | AB24: 0
A25: 1.18 | B25: 直形楼梯 C35 | C25: (1)混凝土强度等级:C35泵送商品混凝土_x000D_ (2)满足设计图纸、相关规范、招标文件及技术要求 | D25: m3 | E25: 25.9 | F25: 545.58402 | G25: =+F25*E25 -> 14130.626 | H25: 25.9 | I25: 381.06408 | J25: =+I25*H25 -> 9869.5596 | K25: =+人工费!K25 -> 0 | L25: =+R25 -> 545.58402 | M25: =+L25*K25 -> 0 | N25: =+T25-Z25 -> 180 | O25: =+U25 -> 417.22333 | P25: =+V25-AB25 -> 75100.2 | Q25: =+人工费!Q25 -> 26.01 | R25: 545.58402 | S25: =+R25*Q25 -> 14190.64 | T25: 180 | U25: 417.22333 | V25: =+U25*T25 -> 75100.2 | W25: C40 P10+8%膨胀剂 | AB25: 0
A26: 1.19 | B26: 构造柱 C20 | C26: (1)混凝土强度等级:C20非泵送商品混凝土_x000D_ (2)满足设计图纸、相关规范、招标文件及技术要求 | D26: m3 | E26: 60.5 | F26: 475.57801 | G26: =+F26*E26 -> 28772.47 | H26: 60.5 | I26: 332.50971 | J26: =+I26*H26 -> 20116.837 | K26: =+人工费!K26 -> 0 | L26: =+R26 -> 475.57801 | M26: =+L26*K26 -> 0 | N26: =+T26-Z26 -> -128.5 | O26: =+U26 -> 431.53402 | P26: =+N26*O26 -> -55452.121 | Q26: =+人工费!Q26 -> 0 | R26: 475.57801 | S26: =+R26*Q26 -> 0 | T26: 117 | U26: 431.53402 | V26: =+U26*T26 -> 50489.48 | W26: 商砼C45 | Z26: 245.5 | AA26: 338.44872 | AB26: 83089.16
A27: 1.2 | B27: 圈、过梁 C20 | C27: (1)混凝土强度等级:C20非泵送商品混凝土_x000D_ (2)满足设计图纸、相关规范、招标文件及技术要求 | D27: m3 | E27: 16.98 | F27: 474.67697 | G27: =+F27*E27 -> 8060.015 | H27: 16.98 | I27: 332.50971 | J27: =+I27*H27 -> 5646.0149 | K27: =+人工费!K27 -> 0 | L27: =+R27 -> 474.67697 | M27: =+L27*K27 -> 0 | N27: =+T27-Z27 -> 1178 | O27: =+U27 -> 431.53395 | P27: =+V27-AB27 -> 508579.31 | Q27: =+人工费!Q27 -> 0 | R27: 474.67697 | S27: =+R27*Q27 -> 0 | T27: 1181 | U27: 431.53395 | V27: =+U27*T27 -> 509641.6 | W27: 商砼C50 | Z27: 3 | AA27: 354.09667 | AB27: 1062.29
A28: 1.21 | B28: 门槛、反坎 C25 | C28: (1)混凝土强度等级:C25非泵送商品混凝土_x000D_ (2)满足设计图纸、相关规范、招标文件及技术要求 | D28: m3 | E28: 10 | F28: 493.94973 | G28: =+F28*E28 -> 4939.4973 | H28: 10 | I28: 346.75291 | J28: =+I28*H28 -> 3467.5291 | K28: =+人工费!K28 -> 0 | L28: =+R28 -> 493.94973 | M28: =+L28*K28 -> 0 | N28: =+T28-Z28 -> 1168.5 | O28: =+U28 -> 442.21734 | P28: =+N28*O28 -> 516730.96 | Q28: =+人工费!Q28 -> 0 | R28: 493.94973 | S28: =+R28*Q28 -> 0 | T28: 1205 | U28: 442.21734 | V28: =+U28*T28 -> 532871.89 | W28: 商砼C55 | Z28: 36.5 | AA28: 358.37068 | AB28: 13080.53
A29: 1.22 | B29: 门槛、反坎 C20 | C29: (1)混凝土强度等级:C20非泵送商品混凝土_x000D_ (2)满足设计图纸、相关规范、招标文件及技术要求 | D29: m3 | E29: 108.25 | F29: 474.32604 | G29: =+F29*E29 -> 51345.794 | H29: 108.25 | I29: 332.50971 | J29: =+I29*H29 -> 35994.176 | K29: =+人工费!K29 -> 0 | L29: =+R29 -> 474.32604 | M29: =+L29*K29 -> 0 | N29: =+T29-Z29 -> 3015 | O29: =+U29 -> 449.36519 | P29: =+V29-AB29 -> 1354836 | Q29: =+人工费!Q29 -> 0 | R29: 474.32604 | S29: =+R29*Q29 -> 0 | T29: 3015 | U29: 449.36519 | V29: =+U29*T29 -> 1354836 | W29: C60 | AB29: 0
A30: 1.23 | B30: 设备基础 C35 | C30: (1)混凝土强度等级:C35非泵送商品混凝土_x000D_ (2)满足设计图纸、相关规范、招标文件及技术要求 | D30: m3 | E30: 31.09 | F30: 554.03482 | G30: =+F30*E30 -> 17224.942 | H30: 31.09 | I30: 381.06408 | J30: =+I30*H30 -> 11847.282 | K30: =+人工费!K30 -> 0 | L30: =+R30 -> 554.03482 | M30: =+L30*K30 -> 0 | N30: =+T30-Z30 -> 0 | O30: =+U30 -> 338.44872 | P30: =+V30-AB30 -> 0 | Q30: =+人工费!Q30 -> 31.09 | R30: 554.03482 | S30: =+R30*Q30 -> 17224.942 | T30: 0 | U30: 338.44872 | V30: =+U30*T30 -> 0 | W30: C60 P6 补偿收缩时≥0.03% | AB30: 0
A31: 1.24 | B31: C20素混凝土（坡道位置）_x000D_ | C31: (1)C20素混凝土_x000D_ (2)满足设计图纸、相关规范、招标文件及技术要求 | D31: m3 | E31: 44.04 | F31: 473.52933 | G31: =+F31*E31 -> 20854.232 | H31: 44.04 | I31: 332.50971 | J31: =+I31*H31 -> 14643.728 | K31: =+人工费!K31 -> 0 | L31: =+R31 -> 473.52933 | M31: =+L31*K31 -> 0 | P31: =+V31-AB31 -> 0 | Q31: =+人工费!Q31 -> 0 | R31: 473.52933 | S31: =+R31*Q31 -> 0 | T31: 32 | V31: =+U31*T31 -> 0 | W31: 润管砂浆 | AB31: 0
A32: 1.25 | B32: 混凝土泵送费扣减 | D32: 项 | E32: 1 | F32: 0 | G32: =+F32*E32 -> 0 | H32: 1 | J32: =+I32*H32 -> 0 | K32: =+人工费!K32 -> 0 | M32: =+L32*K32 -> 0 | P32: =+V32-AB32 -> 0 | Q32: =+人工费!Q32 -> 0 | R32: 0 | S32: =+R32*Q32 -> 0 | V32: =+U32*T32 -> 0 | AB32: 0
A33: 2 | B33: 钢筋工程 | E33: 0 | F33: 0 | G33: =SUM(G34:G61) -> 5997238.7 | H33: 0 | J33: =SUM(J34:J61) -> 5163146.4 | K33: =SUM(K34:K58) -> -50 | M33: =SUM(M34:M61) -> -203714.54 | N33: =SUM(N34:N58) -> 366.71841 | P33: =SUM(P34:P61) -> 1481626.6 | Q33: =SUM(Q34:Q58) -> 1412.575 | S33: =SUM(S34:S61) -> 5746722.2 | T33: =SUM(T34:T58) -> 2324.6994 | V33: =SUM(V34:V61) -> 9343089.8 | Z33: 1957.981 | AB33: 7039825
A34: 2.1 | B34: 现浇构件钢筋 | C34: (1)钢筋种类、规格:拉结筋制安(HPB300)φ6mm_x000D_ (2)满足设计图纸、相关规范、招标文件及技术要求 | D34: t | E34: 4.5 | F34: 4046.482 | G34: =+F34*E34 -> 18209.169 | H34: 4.5 | I34: 3690.4779 | J34: =+I34*H34 -> 16607.15 | K34: =+人工费!K34 -> 0 | L34: =+R34 -> 4046.482 | M34: =+L34*K34 -> 0 | P34: =+N34*O34 -> 0 | Q34: =+人工费!Q34 -> 0 | R34: 4046.482 | S34: =+R34*Q34 -> 0 | V34: 0 | AB34: 0
A35: 2.2 | B35: 现浇构件钢筋 | C35: (1)钢筋种类、规格:圆钢制安 φ6mm_x000D_ (2)满足设计图纸、相关规范、招标文件及技术要求 | D35: t | E35: 0.2 | F35: 4017.0133 | G35: =+F35*E35 -> 803.40265 | H35: 0.2 | I35: 4116.7226 | J35: =+I35*H35 -> 823.34452 | K35: =+人工费!K35 -> 0 | L35: =+R35 -> 4017.0133 | M35: =+L35*K35 -> 0 | P35: =+N35*O35 -> 0 | Q35: =+人工费!Q35 -> 0 | R35: 4017.0133 | S35: =+R35*Q35 -> 0 | V35: 0 | AB35: 0
A36: 2.3 | B36: 现浇构件钢筋 | C36: (1)钢筋种类、规格:圆钢制安 φ8~10mm以上_x000D_ (2)满足设计图纸、相关规范、招标文件及技术要求 | D36: t | E36: 0.2 | F36: 4046.1785 | G36: =+F36*E36 -> 809.23569 | H36: 0.2 | I36: 3646.2301 | J36: =+I36*H36 -> 729.24602 | K36: =+人工费!K36 -> 0 | L36: =+R36 -> 4046.1785 | M36: =+L36*K36 -> 0 | N36: =+T36-Z36 -> 0 | O36: =+U36 -> 0 | P36: =+N36*O36 -> 0 | Q36: =+人工费!Q36 -> 0 | R36: 4046.1785 | S36: =+R36*Q36 -> 0 | V36: 0 | AB36: 0
A37: 2.4 | B37: 现浇构件钢筋 | C37: (1)钢筋种类、规格:螺纹钢制安Ⅲ级(HRB400E)φ6mm (2)满足设计图纸、相关规范、招标文件及技术要求 | D37: t | E37: 0.022 | F37: 4202.6179 | G37: =+F37*E37 -> 92.457593 | H37: 0.022 | I37: 3839.4425 | J37: =+I37*H37 -> 84.467735 | K37: =+人工费!K37 -> 0 | L37: =+R37 -> 4202.6179 | M37: =+L37*K37 -> 0 | N37: =+T37-Z37 -> 5.583981 | O37: =+U37 -> 4334.1068 | P37: =+N37*O37 -> 24201.57 | Q37: =+人工费!Q37 -> 0 | R37: 4202.6179 | S37: =+R37*Q37 -> 0 | T37: 16.693981 | U37: 4334.1068 | V37: =+T37*U37 -> 72353.496 | Z37: 11.11 | AA37: 3957.5666 | AB37: 43968.565
A38: 2.5 | B38: 现浇构件钢筋 | C38: (1)钢筋种类、规格:螺纹钢制安Ⅲ级(HRB400E)φ8mm_x000D_ (2)满足设计图纸、相关规范、招标文件及技术要求 | D38: t | E38: 36.245 | F38: 4002.0465 | G38: =+F38*E38 -> 145054.18 | H38: 36.245 | I38: 3582.8053 | J38: =+I38*H38 -> 129858.78 | K38: =+人工费!K38 -> 0 | L38: =+R38 -> 4002.0465 | M38: =+L38*K38 -> 0 | N38: =+T38-Z38 -> 136.28158 | O38: =+U38 -> 4104.76 | P38: =+N38*O38 -> 559403.18 | Q38: =+人工费!Q38 -> 36.245 | R38: 4002.0465 | S38: =+R38*Q38 -> 145054.18 | T38: 327.65558 | U38: 4104.76 | V38: =+T38*U38 -> 1344947.5 | Z38: 191.374 | AA38: 3718.3741 | AB38: 711600.13
A39: 2.6 | B39: 现浇构件钢筋 | C39: (1)钢筋种类、规格:螺纹钢制安Ⅲ级(HRB400E)φ10mm_x000D_ (2)满足设计图纸、相关规范、招标文件及技术要求 | D39: t | E39: 177.258 | F39: 4059.5518 | G39: =+F39*E39 -> 719588.03 | H39: 177.258 | I39: 3580.1504 | J39: =+I39*H39 -> 634610.31 | K39: =+人工费!K39 -> 0 | L39: =+R39 -> 4059.5518 | M39: =+L39*K39 -> 0 | N39: =+T39-Z39 -> 52.207774 | O39: =+U39 -> 4101.5511 | P39: =+N39*O39 -> 214132.85 | Q39: =+人工费!Q39 -> 177.258 | R39: 4059.5518 | S39: =+R39*Q39 -> 719588.03 | T39: 335.44277 | U39: 4101.5511 | V39: =+T39*U39 -> 1375835.7 | Z39: 283.235 | AA39: 3690.0844 | AB39: 1045161
A40: 2.7 | B40: 现浇构件钢筋 | C40: (1)钢筋种类、规格:螺纹钢制安Ⅲ级(HRB400E)φ12mm_x000D_ (2)满足设计图纸、相关规范、招标文件及技术要求 | D40: t | E40: 313.589 | F40: 4074.2909 | G40: =+F40*E40 -> 1277652.8 | H40: 313.589 | I40: 3518.3274 | J40: =+I40*H40 -> 1103308.8 | K40: =+人工费!K40 -> -50 | L40: =+R40 -> 4074.2909 | M40: =+L40*K40 -> -203714.54 | N40: =+T40-Z40 -> 61.635709 | O40: =+U40 -> 3953.7448 | P40: =+N40*O40 -> 243691.86 | Q40: =+人工费!Q40 -> 263.589 | R40: 4074.2909 | S40: =+R40*Q40 -> 1073938.3 | T40: 435.25071 | U40: 3953.7448 | V40: =+T40*U40 -> 1720870.2 | Z40: 373.615 | AA40: 3544.7996 | AB40: 1324390.3
A41: 2.8 | B41: 现浇构件钢筋 | C41: (1)钢筋种类、规格:螺纹钢制安Ⅲ级(HRB400E)φ14mm_x000D_ (2)满足设计图纸、相关规范、招标文件及技术要求 | D41: t | E41: 72.128 | F41: 4040.0988 | G41: =+F41*E41 -> 291404.25 | H41: 72.128 | I41: 3518.3274 | J41: =+I41*H41 -> 253769.92 | K41: =+人工费!K41 -> 0 | L41: =+R41 -> 4040.0988 | M41: =+L41*K41 -> 0 | N41: =+T41-Z41 -> 13.950046 | O41: =+U41 -> 3909.7388 | P41: =+N41*O41 -> 54541.037 | Q41: =+人工费!Q41 -> 72.128 | R41: 4040.0988 | S41: =+R41*Q41 -> 291404.25 | T41: 137.67905 | U41: 3909.7388 | V41: =+T41*U41 -> 538289.11 | Z41: 123.729 | AA41: 3499.8996 | AB41: 433039.08
A42: 2.9 | B42: 现浇构件钢筋 | C42: (1)钢筋种类、规格:螺纹钢制安Ⅲ级(HRB400E)φ16mm_x000D_ (2)满足设计图纸、相关规范、招标文件及技术要求 | D42: t | E42: 320.691 | F42: 3988.3981 | G42: =+F42*E42 -> 1279043.4 | H42: 320.691 | I42: 3420.9823 | J42: =+I42*H42 -> 1097078.2 | K42: =+人工费!K42 -> 0 | L42: =+R42 -> 3988.3981 | M42: =+L42*K42 -> 0 | N42: =+T42-Z42 -> 12.146183 | O42: =+U42 -> 3919.7387 | P42: =+N42*O42 -> 47609.863 | Q42: =+人工费!Q42 -> 320.691 | R42: 3988.3981 | S42: =+R42*Q42 -> 1279043.4 | T42: 427.46718 | U42: 3919.7387 | V42: =+T42*U42 -> 1675559.6 | Z42: 415.321 | AA42: 3494.163 | AB42: 1451199.3
A43: 2.1 | B43: 现浇构件钢筋 | C43: (1)钢筋种类、规格:螺纹钢制安Ⅲ级(HRB400E)φ18mm_x000D_ (2)满足设计图纸、相关规范、招标文件及技术要求 | D43: t | E43: 65.535 | F43: 3945.0155 | G43: =+F43*E43 -> 258536.59 | H43: 65.535 | I43: 3359.0354 | J43: =+I43*H43 -> 220134.38 | K43: =+人工费!K43 -> 0 | L43: =+R43 -> 3945.0155 | M43: =+L43*K43 -> 0 | N43: =+T43-Z43 -> 9.278614 | O43: =+U43 -> 3912.4089 | P43: =+N43*O43 -> 36301.732 | Q43: =+人工费!Q43 -> 65.535 | R43: 3945.0155 | S43: =+R43*Q43 -> 258536.59 | T43: 159.80461 | U43: 3912.4089 | V43: =+T43*U43 -> 625220.99 | Z43: 150.526 | AA43: 3470.6561 | AB43: 522423.98
A44: 2.11 | B44: 现浇构件钢筋 | C44: (1)钢筋种类、规格:螺纹钢制安Ⅲ级(HRB400E)φ20mm_x000D_ (2)满足设计图纸、相关规范、招标文件及技术要求 | D44: t | E44: 84.293 | F44: 3960.8738 | G44: =+F44*E44 -> 333873.93 | H44: 84.293 | I44: 3376.7345 | J44: =+I44*H44 -> 284635.08 | K44: =+人工费!K44 -> 0 | L44: =+R44 -> 3960.8738 | M44: =+L44*K44 -> 0 | N44: =+T44-Z44 -> 6.576269 | O44: =+U44 -> 3915.0814 | P44: =+N44*O44 -> 25746.629 | Q44: =+人工费!Q44 -> 84.293 | R44: 3960.8738 | S44: =+R44*Q44 -> 333873.93 | T44: 120.91627 | U44: 3915.0814 | V44: =+T44*U44 -> 473397.04 | Z44: 114.34 | AA44: 3465.8912 | AB44: 396289.99
A45: 2.12 | B45: 现浇构件钢筋 | C45: (1)钢筋种类、规格:螺纹钢制安Ⅲ级(HRB400E)φ22mm_x000D_ (2)满足设计图纸、相关规范、招标文件及技术要求 | D45: t | E45: 59.776 | F45: 3952.5178 | G45: =+F45*E45 -> 236265.7 | H45: 59.776 | I45: 3376.7345 | J45: =+I45*H45 -> 201847.68 | K45: =+人工费!K45 -> 0 | L45: =+R45 -> 3952.5178 | M45: =+L45*K45 -> 0 | N45: =+T45-Z45 -> 13.822624 | O45: =+U45 -> 3928.3888 | P45: =+N45*O45 -> 54300.641 | Q45: =+人工费!Q45 -> 59.776 | R45: 3952.5178 | S45: =+R45*Q45 -> 236265.7 | T45: 110.14462 | U45: 3928.3888 | V45: =+T45*U45 -> 432690.91 | Z45: 96.322 | AA45: 3489.607 | AB45: 336125.93
A46: 2.13 | B46: 现浇构件钢筋 | C46: (1)钢筋种类、规格:螺纹钢制安Ⅲ级(HRB400E)φ25mm_x000D_ (2)满足设计图纸、相关规范、招标文件及技术要求 | D46: t | E46: 77.28 | F46: 3966.7163 | G46: =+F46*E46 -> 306547.84 | H46: 77.28 | I46: 3403.2832 | J46: =+I46*H46 -> 263005.72 | K46: =+人工费!K46 -> 0 | L46: =+R46 -> 3966.7163 | M46: =+L46*K46 -> 0 | N46: =+T46-Z46 -> 52.087468 | O46: =+U46 -> 3954.676 | P46: =+N46*O46 -> 205989.06 | Q46: =+人工费!Q46 -> 77.28 | R46: 3966.7163 | S46: =+R46*Q46 -> 306547.84 | T46: 209.80047 | U46: 3954.676 | V46: =+T46*U46 -> 829692.87 | Z46: 157.713 | AA46: 3524.1827 | AB46: 555809.43
A47: 2.14 | B47: 现浇构件钢筋 | C47: (1)钢筋种类、规格:螺纹钢制安Ⅲ级(HRB400E)φ28~32mm_x000D_ (2)满足设计图纸、相关规范、招标文件及技术要求 | D47: t | E47: 10.911 | F47: 4128.4481 | G47: =+F47*E47 -> 45045.497 | H47: 10.911 | I47: 3518.3274 | J47: =+I47*H47 -> 38388.471 | K47: =+人工费!K47 -> 0 | L47: =+R47 -> 4128.4481 | M47: =+L47*K47 -> 0 | N47: =+T47-Z47 -> 3.14816 | O47: =+U47 -> 4088.055 | P47: =+N47*O47 -> 12869.851 | Q47: =+人工费!Q47 -> 10.911 | R47: 4128.4481 | S47: =+R47*Q47 -> 45045.497 | T47: =35.89416+7.95 -> 43.84416 | U47: 4088.055 | V47: =+T47*U47 -> 179237.34 | Z47: 40.696 | AA47: 3628.3808 | AB47: 147660.58
A48: 2.15 | B48: 现浇构件钢筋 | C48: (1)钢筋种类、规格:螺纹钢制安Ⅲ级(HRB400E)φ36~40mm_x000D_ (2)满足设计图纸、相关规范、招标文件及技术要求 | D48: t | E48: 0.2 | F48: 4278.3431 | G48: =+F48*E48 -> 855.66862 | H48: 0.2 | I48: 3677.6195 | J48: =+I48*H48 -> 735.52389 | K48: =+人工费!K48 -> 0 | L48: =+R48 -> 4278.3431 | M48: =+L48*K48 -> 0 | N48: =+T48-Z48 -> 0 | O48: =+U48 -> 3953.7448 | P48: =+O48*N48 -> 0 | Q48: =+人工费!Q48 -> 0 | R48: 4278.3431 | S48: =+R48*Q48 -> 0 | U48: =+U40 -> 3953.7448 | V48: =+T48*U48 -> 0 | W48: 措施筋 | AB48: 0
A49: 2.16 | B49: 现浇构件钢筋 （箍筋） | C49: (1)钢筋种类、规格:圆钢制安 φ6mm_x000D_ (2)满足设计图纸、相关规范、招标文件及技术要求 | D49: t | E49: 2.469 | F49: 4075.9223 | G49: =+F49*E49 -> 10063.452 | H49: 2.469 | I49: 4116.7226 | J49: =+I49*H49 -> 10164.188 | K49: =+人工费!K49 -> 0 | L49: =+R49 -> 4075.9223 | M49: =+L49*K49 -> 0 | P49: =+O49*N49 -> 0 | Q49: =+人工费!Q49 -> 0 | R49: 4075.9223 | S49: =+R49*Q49 -> 0 | V49: 0 | AB49: 0
A50: 2.17 | B50: 现浇构件钢筋 （箍筋） | C50: (1)钢筋种类、规格:圆钢制安 φ8~10mm_x000D_ (2)满足设计图纸、相关规范、招标文件及技术要求 | D50: t | E50: 1.676 | F50: 4075.8938 | G50: =+F50*E50 -> 6831.198 | H50: 1.676 | I50: 3646.2301 | J50: =+I50*H50 -> 6111.0816 | K50: =+人工费!K50 -> 0 | L50: =+R50 -> 4075.8938 | M50: =+L50*K50 -> 0 | P50: =+O50*N50 -> 0 | Q50: =+人工费!Q50 -> 0 | R50: 4075.8938 | S50: =+R50*Q50 -> 0 | V50: 0 | AB50: 0
A51: 2.18 | B51: 现浇构件钢筋 （箍筋） | C51: (1)钢筋种类、规格:螺纹钢制安Ⅲ级(HRB400E)φ6mm_x000D_ (2)满足设计图纸、相关规范、招标文件及技术要求 | D51: t | E51: 5.325 | F51: 4215.6972 | G51: =+F51*E51 -> 22448.587 | H51: 5.325 | I51: 3839.4425 | J51: =+I51*H51 -> 20445.031 | K51: =+人工费!K51 -> 0 | L51: =+R51 -> 4215.6972 | M51: =+L51*K51 -> 0 | P51: =+O51*N51 -> 0 | Q51: =+人工费!Q51 -> 5.325 | R51: 4215.6972 | S51: =+R51*Q51 -> 22448.587 | V51: 0 | AB51: 0
A52: 2.19 | B52: 现浇构件钢筋 （箍筋） | C52: (1)钢筋种类、规格:螺纹钢制安Ⅲ级(HRB400E)φ8mm_x000D_ (2)满足设计图纸、相关规范、招标文件及技术要求 | D52: t | E52: 30.246 | F52: 4015.1163 | G52: =+F52*E52 -> 121441.21 | H52: 30.246 | I52: 3582.8053 | J52: =+I52*H52 -> 108365.53 | K52: =+人工费!K52 -> 0 | L52: =+R52 -> 4015.1163 | M52: =+L52*K52 -> 0 | P52: =+O52*N52 -> 0 | Q52: =+人工费!Q52 -> 30.246 | R52: 4015.1163 | S52: =+R52*Q52 -> 121441.21 | V52: 0 | AB52: 0
A53: 2.2 | B53: 现浇构件钢筋 （箍筋） | C53: (1)钢筋种类、规格:螺纹钢制安Ⅲ级(HRB400E)φ10mm_x000D_ (2)满足设计图纸、相关规范、招标文件及技术要求 | D53: t | E53: 74.192 | F53: 4072.6216 | G53: =+F53*E53 -> 302155.94 | H53: 74.192 | I53: 3580.1504 | J53: =+I53*H53 -> 265618.52 | K53: =+人工费!K53 -> 0 | L53: =+R53 -> 4072.6216 | M53: =+L53*K53 -> 0 | P53: =+O53*N53 -> 0 | Q53: =+人工费!Q53 -> 42.624 | R53: 4072.6216 | S53: =+R53*Q53 -> 173591.42 | V53: 0 | AB53: 0
A54: 2.21 | B54: 现浇构件钢筋 （箍筋） | C54: (1)钢筋种类、规格:螺纹钢制安Ⅲ级(HRB400E)φ12mm_x000D_ (2)满足设计图纸、相关规范、招标文件及技术要求 | D54: t | E54: 23.106 | F54: 4016.7097 | G54: =+F54*E54 -> 92810.095 | H54: 23.106 | I54: 3518.3274 | J54: =+I54*H54 -> 81294.474 | K54: =+人工费!K54 -> 0 | L54: =+R54 -> 4016.7097 | M54: =+L54*K54 -> 0 | P54: =+O54*N54 -> 0 | Q54: =+人工费!Q54 -> 63.069 | R54: 4016.7097 | S54: =+R54*Q54 -> 253329.87 | V54: 0 | AB54: 0
A55: 2.22 | B55: 现浇构件钢筋 （箍筋） | C55: (1)钢筋种类、规格:螺纹钢制安Ⅲ级(HRB400E)φ14mm_x000D_ (2)满足设计图纸、相关规范、招标文件及技术要求 | D55: t | E55: 18.609 | F55: 3982.5082 | G55: =+F55*E55 -> 74110.495 | H55: 18.609 | I55: 3518.3274 | J55: =+I55*H55 -> 65472.555 | K55: =+人工费!K55 -> 0 | L55: =+R55 -> 3982.5082 | M55: =+L55*K55 -> 0 | P55: =+O55*N55 -> 0 | Q55: =+人工费!Q55 -> 17.654 | R55: 3982.5082 | S55: =+R55*Q55 -> 70307.2 | V55: 0 | AB55: 0
A56: 2.23 | B56: 现浇构件钢筋 （箍筋） | C56: (1)钢筋种类、规格:螺纹钢制安Ⅲ级(HRB400E)φ16mm_x000D_ (2)满足设计图纸、相关规范、招标文件及技术要求 | D56: t | E56: 62.289 | F56: 3930.817 | G56: =+F56*E56 -> 244846.66 | H56: 62.289 | I56: 3420.9823 | J56: =+I56*H56 -> 213089.57 | K56: =+人工费!K56 -> 0 | L56: =+R56 -> 3930.817 | M56: =+L56*K56 -> 0 | P56: =+O56*N56 -> 0 | Q56: =+人工费!Q56 -> 56.475 | R56: 3930.817 | S56: =+R56*Q56 -> 221992.89 | V56: 0 | AB56: 0
A57: 2.24 | B57: 现浇构件钢筋 （箍筋） | C57: (1)钢筋种类、规格:螺纹钢制安Ⅲ级(HRB400E)φ18mm_x000D_ (2)满足设计图纸、相关规范、招标文件及技术要求 | D57: t | E57: 32.457 | F57: 3887.4248 | G57: =+F57*E57 -> 126174.15 | H57: 32.457 | I57: 3359.0354 | J57: =+I57*H57 -> 109024.21 | K57: =+人工费!K57 -> 0 | L57: =+R57 -> 3887.4248 | M57: =+L57*K57 -> 0 | P57: =+O57*N57 -> 0 | Q57: =+人工费!Q57 -> 29.476 | R57: 3887.4248 | S57: =+R57*Q57 -> 114585.73 | V57: 0 | AB57: 0
A58: 2.25 | B58: 现浇构件钢筋 （箍筋） | C58: (1)钢筋种类、规格:螺纹钢制安Ⅲ级(HRB400E)φ20mm_x000D_ (2)满足设计图纸、相关规范、招标文件及技术要求 | D58: t | E58: 0.94 | F58: 3903.2831 | G58: =+F58*E58 -> 3669.0861 | H58: 0.94 | I58: 3376.7345 | J58: =+I58*H58 -> 3174.1304 | K58: =+人工费!K58 -> 0 | L58: =+R58 -> 3903.2831 | M58: =+L58*K58 -> 0 | P58: =+O58*N58 -> 0 | Q58: =+人工费!Q58 -> 0 | R58: 3903.2831 | S58: =+R58*Q58 -> 0 | V58: 0 | AB58: 0
A59: 2.26 | B59: 机械连接 | C59: (1)连接方式:电渣压力焊_x000D_ (2)满足设计图纸、相关规范、招标文件及技术要求 | D59: 个 | E59: 10771 | F59: 2.1530096 | G59: =+F59*E59 -> 23190.067 | H59: 10771 | I59: 2 | J59: =+I59*H59 -> 21542 | K59: =+人工费!K59 -> 0 | L59: =+R59 -> 2.1530096 | M59: =+L59*K59 -> 0 | P59: =+V59-AB59 -> 2838.3186 | Q59: =+人工费!Q59 -> 10771 | R59: 2.1530096 | S59: =+R59*Q59 -> 23190.067 | V59: 74994.956 | W59: 深圳市固力士建材有限公司 | AB59: 72156.637
A60: 2.27 | B60: 机械连接 | C60: (1)连接方式:套筒直螺纹接头Φ25mm以内_x000D_ (2)满足设计图纸、相关规范、招标文件及技术要求 | D60: 个 | E60: 6466 | F60: 8.3844075 | G60: =+F60*E60 -> 54213.579 | H60: 6466 | I60: 2 | J60: =+I60*H60 -> 12932 | K60: =+人工费!K60 -> 0 | L60: =+R60 -> 8.3844075 | M60: =+L60*K60 -> 0 | P60: =+O60*N60 -> 0 | Q60: =+人工费!Q60 -> 6466 | R60: 8.3844075 | S60: =+R60*Q60 -> 54213.579 | V60: 0 | AB60: 0
A61: 2.28 | B61: 机械连接 | C61: (1)连接方式:套筒直螺纹接头Φ25mm以外_x000D_ (2)满足设计图纸、相关规范、招标文件及技术要求 | D61: 个 | E61: 148 | F61: 10.148548 | G61: =+F61*E61 -> 1501.985 | H61: 148 | I61: 2 | J61: =+I61*H61 -> 296 | K61: =+人工费!K61 -> 0 | L61: =+R61 -> 10.148548 | M61: =+L61*K61 -> 0 | P61: =+O61*N61 -> 0 | Q61: =+人工费!Q61 -> 229 | R61: 10.148548 | S61: =+R61*Q61 -> 2324.0174 | V61: 0 | AB61: 0
A62: 二 | B62: 裙楼结构 | E62: 0 | F62: 0 | G62: =+G63+G91 -> 1691235.1 | H62: 0 | J62: =+J63+J91 -> 1348878.4 | M62: =+M63+M91 -> 0 | P62: =+P63+P91 -> 0 | S62: =+S63+S91 -> 1468222.2 | V62: =+V63+V91 -> 0 | AB62: 0
A63: 1 | B63: 钢筋工程 | E63: 0 | F63: 0 | G63: =SUM(G64:G90) -> 1017186.8 | H63: 0 | J63: =SUM(J64:J90) -> 881248.68 | M63: =SUM(M64:M90) -> 0 | P63: =SUM(P64:P90) -> 0 | S63: =SUM(S64:S90) -> 812802.54 | V63: =SUM(V64:V90) -> 0 | AB63: 0
A64: 1.1 | B64: 现浇构件钢筋 | C64: (1)钢筋种类、规格:拉结筋制安(HPB300)φ6mm_x000D_ (2)满足设计图纸、相关规范、招标文件及技术要求_x000D_ (3)建筑物超高增加费 | D64: t | E64: 1.743 | F64: 4046.482 | G64: =+F64*E64 -> 7053.0181 | H64: 1.743 | I64: 3690.4779 | J64: =+I64*H64 -> 6432.5029 | K64: =+人工费!K64 -> 0 | L64: =+R64 -> 4046.482 | M64: =+L64*K64 -> 0 | P64: =+O64*N64 -> 0 | Q64: =+人工费!Q64 -> 0 | R64: 4046.482 | S64: =+R64*Q64 -> 0 | V64: =+U64*T64 -> 0 | AB64: 0
A65: 1.2 | B65: 现浇构件钢筋 | C65: (1)钢筋种类、规格:圆钢制安 φ6mm_x000D_ (2)满足设计图纸、相关规范、招标文件及技术要求_x000D_ (3)建筑物超高增加费 | D65: t | E65: 0.2 | F65: 4017.0133 | G65: =+F65*E65 -> 803.40265 | H65: 0.2 | I65: 4116.7226 | J65: =+I65*H65 -> 823.34452 | K65: =+人工费!K65 -> 0 | L65: =+R65 -> 4017.0133 | M65: =+L65*K65 -> 0 | P65: =+O65*N65 -> 0 | Q65: =+人工费!Q65 -> 0 | R65: 4017.0133 | S65: =+R65*Q65 -> 0 | V65: =+U65*T65 -> 0 | AB65: 0
A66: 1.3 | B66: 现浇构件钢筋 | C66: (1)钢筋种类、规格:圆钢制安 φ8~10mm及以上_x000D_ (2)满足设计图纸、相关规范、招标文件及技术要求_x000D_ (3)建筑物超高增加费 | D66: t | E66: 1.1 | F66: 4046.1785 | G66: =+F66*E66 -> 4450.7963 | H66: 1.1 | I66: 3646.2301 | J66: =+I66*H66 -> 4010.8531 | K66: =+人工费!K66 -> 0 | L66: =+R66 -> 4046.1785 | M66: =+L66*K66 -> 0 | P66: =+O66*N66 -> 0 | Q66: =+人工费!Q66 -> 0 | R66: 4046.1785 | S66: =+R66*Q66 -> 0 | V66: =+U66*T66 -> 0 | AB66: 0
A67: 1.4 | B67: 现浇构件钢筋 | C67: (1)钢筋种类、规格:螺纹钢制安Ⅲ级(HRB400E)φ6mm_x000D_ (2)满足设计图纸、相关规范、招标文件及技术要求_x000D_ (3)建筑物超高增加费 | D67: t | E67: 0.006 | F67: 4202.6179 | G67: =+F67*E67 -> 25.215707 | H67: 0.006 | I67: 3839.4425 | J67: =+I67*H67 -> 23.036655 | K67: =+人工费!K67 -> 0 | L67: =+R67 -> 4202.6179 | M67: =+L67*K67 -> 0 | P67: =+O67*N67 -> 0 | Q67: =+人工费!Q67 -> 0 | R67: 4202.6179 | S67: =+R67*Q67 -> 0 | V67: =+U67*T67 -> 0 | AB67: 0
A68: 1.5 | B68: 现浇构件钢筋 | C68: (1)钢筋种类、规格:螺纹钢制安Ⅲ级(HRB400E)φ8mm_x000D_ (2)满足设计图纸、相关规范、招标文件及技术要求_x000D_ (3)建筑物超高增加费 | D68: t | E68: 21.638 | F68: 4002.0465 | G68: =+F68*E68 -> 86596.283 | H68: 21.638 | I68: 3582.8053 | J68: =+I68*H68 -> 77524.741 | K68: =+人工费!K68 -> 0 | L68: =+R68 -> 4002.0465 | M68: =+L68*K68 -> 0 | P68: =+O68*N68 -> 0 | Q68: =+人工费!Q68 -> 17.54 | R68: 4002.0465 | S68: =+R68*Q68 -> 70195.896 | V68: =+U68*T68 -> 0 | AB68: 0
A69: 1.6 | B69: 现浇构件钢筋 | C69: (1)钢筋种类、规格:螺纹钢制安Ⅲ级(HRB400E)φ10mm_x000D_ (2)满足设计图纸、相关规范、招标文件及技术要求_x000D_ (3)建筑物超高增加费 | D69: t | E69: 12.745 | F69: 4059.5518 | G69: =+F69*E69 -> 51738.988 | H69: 12.745 | I69: 3580.1504 | J69: =+I69*H69 -> 45629.017 | K69: =+人工费!K69 -> 0 | L69: =+R69 -> 4059.5518 | M69: =+L69*K69 -> 0 | P69: =+O69*N69 -> 0 | Q69: =+人工费!Q69 -> 13.63 | R69: 4059.5518 | S69: =+R69*Q69 -> 55331.691 | V69: =+U69*T69 -> 0 | AB69: 0
A70: 1.7 | B70: 现浇构件钢筋 | C70: (1)钢筋种类、规格:螺纹钢制安Ⅲ级(HRB400E)φ12mm_x000D_ (2)满足设计图纸、相关规范、招标文件及技术要求_x000D_ (3)建筑物超高增加费 | D70: t | E70: 14.325 | F70: 4074.2909 | G70: =+F70*E70 -> 58364.217 | H70: 14.325 | I70: 3518.3274 | J70: =+I70*H70 -> 50400.04 | K70: =+人工费!K70 -> 0 | L70: =+R70 -> 4074.2909 | M70: =+L70*K70 -> 0 | P70: =+O70*N70 -> 0 | Q70: =+人工费!Q70 -> 6.29 | R70: 4074.2909 | S70: =+R70*Q70 -> 25627.29 | V70: =+U70*T70 -> 0 | AB70: 0
A71: 1.8 | B71: 现浇构件钢筋 | C71: (1)钢筋种类、规格:螺纹钢制安Ⅲ级(HRB400E)φ14mm_x000D_ (2)满足设计图纸、相关规范、招标文件及技术要求_x000D_ (3)建筑物超高增加费 | D71: t | E71: 3.268 | F71: 4040.0988 | G71: =+F71*E71 -> 13203.043 | H71: 3.268 | I71: 3518.3274 | J71: =+I71*H71 -> 11497.894 | K71: =+人工费!K71 -> 0 | L71: =+R71 -> 4040.0988 | M71: =+L71*K71 -> 0 | P71: =+O71*N71 -> 0 | Q71: =+人工费!Q71 -> 3.05 | R71: 4040.0988 | S71: =+R71*Q71 -> 12322.301 | V71: =+U71*T71 -> 0 | AB71: 0
A72: 1.9 | B72: 现浇构件钢筋 | C72: (1)钢筋种类、规格:螺纹钢制安Ⅲ级(HRB400E)φ16mm_x000D_ (2)满足设计图纸、相关规范、招标文件及技术要求_x000D_ (3)建筑物超高增加费 | D72: t | E72: 17.43 | F72: 3988.3981 | G72: =+F72*E72 -> 69517.78 | H72: 17.43 | I72: 3420.9823 | J72: =+I72*H72 -> 59627.722 | K72: =+人工费!K72 -> 0 | L72: =+R72 -> 3988.3981 | M72: =+L72*K72 -> 0 | P72: =+O72*N72 -> 0 | Q72: =+人工费!Q72 -> 10.78 | R72: 3988.3981 | S72: =+R72*Q72 -> 42994.932 | V72: =+U72*T72 -> 0 | AB72: 0
A73: 1.1 | B73: 现浇构件钢筋 | C73: (1)钢筋种类、规格:螺纹钢制安Ⅲ级(HRB400E)φ18mm_x000D_ (2)满足设计图纸、相关规范、招标文件及技术要求_x000D_ (3)建筑物超高增加费 | D73: t | E73: 9.786 | F73: 3945.0155 | G73: =+F73*E73 -> 38605.921 | H73: 9.786 | I73: 3359.0354 | J73: =+I73*H73 -> 32871.52 | K73: =+人工费!K73 -> 0 | L73: =+R73 -> 3945.0155 | M73: =+L73*K73 -> 0 | P73: =+O73*N73 -> 0 | Q73: =+人工费!Q73 -> 6.76 | R73: 3945.0155 | S73: =+R73*Q73 -> 26668.305 | V73: =+U73*T73 -> 0 | AB73: 0
A74: 1.11 | B74: 现浇构件钢筋 | C74: (1)钢筋种类、规格:螺纹钢制安Ⅲ级(HRB400E)φ20mm_x000D_ (2)满足设计图纸、相关规范、招标文件及技术要求_x000D_ (3)建筑物超高增加费 | D74: t | E74: 16.775 | F74: 3960.8738 | G74: =+F74*E74 -> 66443.657 | H74: 16.775 | I74: 3376.7345 | J74: =+I74*H74 -> 56644.721 | K74: =+人工费!K74 -> 0 | L74: =+R74 -> 3960.8738 | M74: =+L74*K74 -> 0 | P74: =+O74*N74 -> 0 | Q74: =+人工费!Q74 -> 13.27 | R74: 3960.8738 | S74: =+R74*Q74 -> 52560.795 | V74: =+U74*T74 -> 0 | AB74: 0
A75: 1.12 | B75: 现浇构件钢筋 | C75: (1)钢筋种类、规格:螺纹钢制安Ⅲ级(HRB400E)φ22mm_x000D_ (2)满足设计图纸、相关规范、招标文件及技术要求_x000D_ (3)建筑物超高增加费 | D75: t | E75: 12.006 | F75: 3952.5178 | G75: =+F75*E75 -> 47453.929 | H75: 12.006 | I75: 3376.7345 | J75: =+I75*H75 -> 40541.075 | K75: =+人工费!K75 -> 0 | L75: =+R75 -> 3952.5178 | M75: =+L75*K75 -> 0 | P75: =+O75*N75 -> 0 | Q75: =+人工费!Q75 -> 12.64 | R75: 3952.5178 | S75: =+R75*Q75 -> 49959.825 | V75: =+U75*T75 -> 0 | AB75: 0
... A90: 1.27 | B90: 机械连接 | C90: (1)连接方式:套筒直螺纹接头Φ25mm以外_x000D_ (2)满足设计图纸、相关规范、招标文件及技术要求_x000D_ (3)建筑物超高增加费 | D90: 个 | E90: 209 | F90: 10.148548 | G90: =+F90*E90 -> 2121.0464 | H90: 209 | I90: 2 | J90: =+I90*H90 -> 418 | K90: =+人工费!K90 -> 0 | L90: =+R90 -> 10.148548 | M90: =+L90*K90 -> 0 | P90: =+O90*N90 -> 0 | Q90: =+人工费!Q90 -> 218 | R90: 10.148548 | S90: =+R90*Q90 -> 2212.3834 | V90: =+U90*T90 -> 0 | AB90: 0
A91: 2 | B91: 钢筋混凝土工程（地上） | E91: 0 | F91: 0 | G91: =SUM(G92:G105) -> 674048.25 | H91: 0 | J91: =SUM(J92:J105) -> 467629.68 | K91: =SUM(K92:K104) -> 0 | M91: =SUM(M92:M105) -> 0 | P91: =SUM(P92:P105) -> 0 | Q91: =SUM(Q92:Q104) -> 1121.78 | S91: =SUM(S92:S105) -> 655419.62 | V91: =SUM(V92:V105) -> 0 | AB91: 0
A92: 2.1 | B92: 砼墙、柱 C60 | C92: (1)混凝土强度等级:C60泵送商品混凝土_x000D_ (2)满足设计图纸、相关规范、招标文件及技术要求_x000D_ (3)建筑物超高增加费 | D92: m3 | E92: 465.16 | F92: 647.44888 | G92: =+F92*E92 -> 301167.32 | H92: 465.16 | I92: 447.05485 | J92: =+I92*H92 -> 207952.04 | K92: =+人工费!K92 -> 0 | L92: =+R92 -> 647.44888 | M92: =+L92*K92 -> 0 | P92: =+O92*N92 -> 0 | Q92: =+人工费!Q92 -> 543.45 | R92: 647.44888 | S92: =+R92*Q92 -> 351856.09 | V92: =+U92*T92 -> 0 | AB92: 0
A93: 2.2 | B93: 有梁板 C30 | C93: (1)混凝土强度等级:C30泵送商品混凝土_x000D_ (2)满足设计图纸、相关规范、招标文件及技术要求_x000D_ (3)建筑物超高增加费 | D93: m3 | E93: 164.31 | F93: 521.57843 | G93: =+F93*E93 -> 85700.553 | H93: 164.31 | I93: 361.86068 | J93: =+I93*H93 -> 59457.328 | K93: =+人工费!K93 -> 0 | L93: =+R93 -> 521.57843 | M93: =+L93*K93 -> 0 | P93: =+O93*N93 -> 0 | Q93: =+人工费!Q93 -> 244.07 | R93: 521.57843 | S93: =+R93*Q93 -> 127301.65 | V93: =+U93*T93 -> 0 | AB93: 0
A94: 2.3 | B94: 有梁板 C30P6_x000D_ | C94: (1)混凝土强度等级:C30泵送商品混凝土，抗渗P6_x000D_ (2)满足设计图纸、相关规范、招标文件及技术要求_x000D_ (3)建筑物超高增加费 | D94: m3 | E94: 295.38 | F94: 528.0754 | G94: =+F94*E94 -> 155982.91 | H94: 295.38 | I94: 366.90922 | J94: =+I94*H94 -> 108377.65 | K94: =+人工费!K94 -> 0 | L94: =+R94 -> 528.0754 | M94: =+L94*K94 -> 0 | P94: =+O94*N94 -> 0 | Q94: =+人工费!Q94 -> 295.38 | R94: 528.0754 | S94: =+R94*Q94 -> 155982.91 | V94: =+U94*T94 -> 0 | AB94: 0
A95: 2.4 | B95: 直形楼梯 C30 | C95: (1)混凝土强度等级:C30泵送商品混凝土_x000D_ (2)满足设计图纸、相关规范、招标文件及技术要求_x000D_ (3)建筑物超高增加费 | D95: m3 | E95: 38.88 | F95: 521.57843 | G95: =+F95*E95 -> 20278.97 | H95: 38.88 | I95: 361.86068 | J95: =+I95*H95 -> 14069.143 | K95: =+人工费!K95 -> 0 | L95: =+R95 -> 521.57843 | M95: =+L95*K95 -> 0 | P95: =+O95*N95 -> 0 | Q95: =+人工费!Q95 -> 38.88 | R95: 521.57843 | S95: =+R95*Q95 -> 20278.97 | V95: =+U95*T95 -> 0 | AB95: 0
A96: 2.5 | B96: 构造柱 C20 | C96: (1)混凝土强度等级:C20非泵送商品混凝土_x000D_ (2)满足设计图纸、相关规范、招标文件及技术要求_x000D_ (3)建筑物超高增加费 | D96: m3 | E96: 43.1 | F96: 475.57801 | G96: =+F96*E96 -> 20497.412 | H96: 43.1 | I96: 332.50971 | J96: =+I96*H96 -> 14331.168 | K96: =+人工费!K96 -> 0 | L96: =+R96 -> 475.57801 | M96: =+L96*K96 -> 0 | P96: =+O96*N96 -> 0 | Q96: =+人工费!Q96 -> 0 | R96: 475.57801 | S96: =+R96*Q96 -> 0 | V96: =+U96*T96 -> 0 | AB96: 0
A97: 2.6 | B97: 圈、过梁 C20 | C97: (1)混凝土强度等级:C20非泵送商品混凝土_x000D_ (2)满足设计图纸、相关规范、招标文件及技术要求_x000D_ (3)建筑物超高增加费 | D97: m3 | E97: 12.85 | F97: 474.67697 | G97: =+F97*E97 -> 6099.5991 | H97: 12.85 | I97: 332.50971 | J97: =+I97*H97 -> 4272.7498 | K97: =+人工费!K97 -> 0 | L97: =+R97 -> 474.67697 | M97: =+L97*K97 -> 0 | P97: =+O97*N97 -> 0 | Q97: =+人工费!Q97 -> 0 | R97: 474.67697 | S97: =+R97*Q97 -> 0 | V97: =+U97*T97 -> 0 | AB97: 0
A98: 2.7 | B98: 门槛、反坎 C25 | C98: (1)混凝土强度等级:C25非泵送商品混凝土_x000D_ (2)满足设计图纸、相关规范、招标文件及技术要求_x000D_ (3)建筑物超高增加费 | D98: m3 | E98: 1.2 | F98: 493.94973 | G98: =+F98*E98 -> 592.73967 | H98: 1.2 | I98: 346.75291 | J98: =+I98*H98 -> 416.1035 | K98: =+人工费!K98 -> 0 | L98: =+R98 -> 493.94973 | M98: =+L98*K98 -> 0 | P98: =+O98*N98 -> 0 | Q98: =+人工费!Q98 -> 0 | R98: 493.94973 | S98: =+R98*Q98 -> 0 | V98: =+U98*T98 -> 0 | AB98: 0
A99: 2.8 | B99: 门槛、反坎 C20 | C99: (1)混凝土强度等级:C20非泵送商品混凝土_x000D_ (2)满足设计图纸、相关规范、招标文件及技术要求_x000D_ (3)建筑物超高增加费 | D99: m3 | E99: 13.5 | F99: 474.32604 | G99: =+F99*E99 -> 6403.4015 | H99: 13.5 | I99: 332.50971 | J99: =+I99*H99 -> 4488.8811 | K99: =+人工费!K99 -> 0 | L99: =+R99 -> 474.32604 | M99: =+L99*K99 -> 0 | P99: =+O99*N99 -> 0 | Q99: =+人工费!Q99 -> 0 | R99: 474.32604 | S99: =+R99*Q99 -> 0 | V99: =+U99*T99 -> 0 | AB99: 0
A100: 2.9 | B100: 雨篷、悬挑板、阳台板 C30 | C100: (1)混凝土强度等级:C30非泵送商品混凝土_x000D_ (2)满足设计图纸、相关规范、招标文件及技术要求_x000D_ (3)建筑物超高增加费 | D100: m3 | E100: 69.21 | F100: 515.03404 | G100: =+F100*E100 -> 35645.506 | H100: 69.21 | I100: 361.86068 | J100: =+I100*H100 -> 25044.378 | K100: =+人工费!K100 -> 0 | L100: =+R100 -> 515.03404 | M100: =+L100*K100 -> 0 | P100: =+O100*N100 -> 0 | Q100: =+人工费!Q100 -> 0 | R100: 515.03404 | S100: =+R100*Q100 -> 0 | V100: =+U100*T100 -> 0 | AB100: 0
A101: 2.1 | B101: 天沟(檐沟)、挑檐板 C30 | C101: (1)混凝土强度等级:C30非泵送商品混凝土_x000D_ (2)满足设计图纸、相关规范、招标文件及技术要求_x000D_ (3)建筑物超高增加费 | D101: m3 | E101: 46.14 | F101: 514.16146 | G101: =+F101*E101 -> 23723.41 | H101: 46.14 | I101: 361.86068 | J101: =+I101*H101 -> 16696.252 | K101: =+人工费!K101 -> 0 | L101: =+R101 -> 514.16146 | M101: =+L101*K101 -> 0 | P101: =+O101*N101 -> 0 | Q101: =+人工费!Q101 -> 0 | R101: 514.16146 | S101: =+R101*Q101 -> 0 | V101: =+U101*T101 -> 0 | AB101: 0
A102: 2.11 | B102: 扶手、压顶 C30 | C102: (1)混凝土强度等级:C30非泵送商品混凝土_x000D_ (2)满足设计图纸、相关规范、招标文件及技术要求_x000D_ (3)建筑物超高增加费 | D102: m3 | E102: 18 | F102: 516.45674 | G102: =+F102*E102 -> 9296.2213 | H102: 18 | I102: 361.86068 | J102: =+I102*H102 -> 6513.4922 | K102: =+人工费!K102 -> 0 | L102: =+R102 -> 516.45674 | M102: =+L102*K102 -> 0 | P102: =+O102*N102 -> 0 | Q102: =+人工费!Q102 -> 0 | R102: 516.45674 | S102: =+R102*Q102 -> 0 | V102: =+U102*T102 -> 0 | AB102: 0
A103: 2.12 | B103: 栏板 C30 | C103: (1)混凝土强度等级:C30非泵送商品混凝土_x000D_ (2)满足设计图纸、相关规范、招标文件及技术要求_x000D_ (3)建筑物超高增加费 | D103: m3 | E103: 6.21 | F103: 513.07073 | G103: =+F103*E103 -> 3186.1692 | H103: 6.21 | I103: 361.86068 | J103: =+I103*H103 -> 2247.1548 | K103: =+人工费!K103 -> 0 | L103: =+R103 -> 513.07073 | M103: =+L103*K103 -> 0 | P103: =+O103*N103 -> 0 | Q103: =+人工费!Q103 -> 0 | R103: 513.07073 | S103: =+R103*Q103 -> 0 | V103: =+U103*T103 -> 0 | AB103: 0
A104: 2.13 | B104: 设备基础 C30 | C104: (1)混凝土强度等级:C30非泵送商品混凝土_x000D_ (2)满足设计图纸、相关规范、招标文件及技术要求_x000D_ (3)建筑物超高增加费 | D104: m3 | E104: 10.4 | F104: 526.3492 | G104: =+F104*E104 -> 5474.0317 | H104: 10.4 | I104: 361.86068 | J104: =+I104*H104 -> 3763.3511 | K104: =+人工费!K104 -> 0 | L104: =+R104 -> 526.3492 | M104: =+L104*K104 -> 0 | P104: =+O104*N104 -> 0 | Q104: =+人工费!Q104 -> 0 | R104: 526.3492 | S104: =+R104*Q104 -> 0 | V104: =+U104*T104 -> 0 | AB104: 0
A105: 2.14 | B105: 混凝土泵送费扣减 | D105: 项 | E105: 1 | F105: 0 | G105: =+F105*E105 -> 0 | H105: 1 | J105: =+I105*H105 -> 0 | M105: =+L105*K105 -> 0 | P105: =+O105*N105 -> 0 | Q105: =+人工费!Q105 -> 0 | R105: 0 | S105: =+R105*Q105 -> 0 | V105: =+U105*T105 -> 0 | AB105: 0
A106: 三 | B106: 1#塔楼结构 | E106: 0 | F106: 0 | G106: =+G107+G135+G156 -> 5914166.5 | H106: 0 | J106: =+J107+J135+J156 -> 4680406.6 | M106: =+M107+M135+M156 -> 738851.92 | P106: =+P107+P135+P156 -> 0 | S106: =+S107+S135+S156 -> 2815215.9 | V106: =+V107+V135+V156 -> 0 | AB106: 0
A107: 1 | B107: 钢筋工程 | E107: 0 | F107: 0 | G107: =SUM(G108:G134) -> 3144090.3 | H107: 0 | J107: =SUM(J108:J134) -> 2760443.5 | M107: =SUM(M108:M134) -> 402838.35 | P107: =SUM(P108:P134) -> 0 | S107: =SUM(S108:S134) -> 1488560.6 | V107: =SUM(V108:V134) -> 0 | AB107: 0
A108: 1.1 | B108: 现浇构件钢筋 | C108: (1)钢筋种类、规格:拉结筋制安(HPB300)φ6mm_x000D_ (2)满足设计图纸、相关规范、招标文件及技术要求_x000D_ (3)建筑物超高增加费 | D108: t | E108: 3.55 | F108: 4046.482 | G108: =+F108*E108 -> 14365.011 | H108: 3.55 | I108: 3690.4779 | J108: =+I108*H108 -> 13101.196 | K108: =+人工费!K108 -> 0 | L108: =+R108 -> 4046.482 | M108: =+L108*K108 -> 0 | P108: =+O108*N108 -> 0 | Q108: =+人工费!Q108 -> 0 | R108: 4046.482 | S108: =+R108*Q108 -> 0 | V108: =+U108*T108 -> 0 | AB108: 0
A109: 1.2 | B109: 现浇构件钢筋 | C109: (1)钢筋种类、规格:圆钢制安 φ6mm_x000D_ (2)满足设计图纸、相关规范、招标文件及技术要求_x000D_ (3)建筑物超高增加费 | D109: t | E109: 0.1 | F109: 4017.0133 | G109: =+F109*E109 -> 401.70133 | H109: 0.1 | I109: 4116.7226 | J109: =+I109*H109 -> 411.67226 | K109: =+人工费!K109 -> 0 | L109: =+R109 -> 4017.0133 | M109: =+L109*K109 -> 0 | P109: =+O109*N109 -> 0 | Q109: =+人工费!Q109 -> 0 | R109: 4017.0133 | S109: =+R109*Q109 -> 0 | V109: =+U109*T109 -> 0 | AB109: 0
A110: 1.3 | B110: 现浇构件钢筋 | C110: (1)钢筋种类、规格:圆钢制安 φ8~10mm及以上_x000D_ (2)满足设计图纸、相关规范、招标文件及技术要求_x000D_ (3)建筑物超高增加费 | D110: t | E110: 0.5 | F110: 4046.1785 | G110: =+F110*E110 -> 2023.0892 | H110: 0.5 | I110: 3646.2301 | J110: =+I110*H110 -> 1823.115 | K110: =+人工费!K110 -> 0 | L110: =+R110 -> 4046.1785 | M110: =+L110*K110 -> 0 | P110: =+O110*N110 -> 0 | Q110: =+人工费!Q110 -> 0 | R110: 4046.1785 | S110: =+R110*Q110 -> 0 | V110: =+U110*T110 -> 0 | AB110: 0
A111: 1.4 | B111: 现浇构件钢筋 | C111: (1)钢筋种类、规格:螺纹钢制安Ⅲ级(HRB400E)φ6mm_x000D_ (2)满足设计图纸、相关规范、招标文件及技术要求_x000D_ (3)建筑物超高增加费 | D111: t | E111: 3.16 | F111: 4202.6179 | G111: =+F111*E111 -> 13280.272 | H111: 3.16 | I111: 3839.4425 | J111: =+I111*H111 -> 12132.638 | K111: =+人工费!K111 -> 0 | L111: =+R111 -> 4202.6179 | M111: =+L111*K111 -> 0 | P111: =+O111*N111 -> 0 | Q111: =+人工费!Q111 -> 0 | R111: 4202.6179 | S111: =+R111*Q111 -> 0 | V111: =+U111*T111 -> 0 | AB111: 0
A112: 1.5 | B112: 现浇构件钢筋 | C112: (1)钢筋种类、规格:螺纹钢制安Ⅲ级(HRB400E)φ8mm_x000D_ (2)满足设计图纸、相关规范、招标文件及技术要求_x000D_ (3)建筑物超高增加费 | D112: t | E112: 174.55 | F112: 4002.0465 | G112: =+F112*E112 -> 698557.22 | H112: 174.55 | I112: 3582.8053 | J112: =+I112*H112 -> 625378.67 | K112: =+人工费!K112 -> 24.496 | L112: =+R112 -> 4002.0465 | M112: =+L112*K112 -> 98034.132 | P112: =+O112*N112 -> 0 | Q112: =+人工费!Q112 -> 82.642 | R112: 4002.0465 | S112: =+R112*Q112 -> 330737.13 | V112: =+U112*T112 -> 0 | AB112: 0
A113: 1.6 | B113: 现浇构件钢筋 | C113: (1)钢筋种类、规格:螺纹钢制安Ⅲ级(HRB400E)φ10mm_x000D_ (2)满足设计图纸、相关规范、招标文件及技术要求_x000D_ (3)建筑物超高增加费 | D113: t | E113: 90.32 | F113: 4059.5518 | G113: =+F113*E113 -> 366658.72 | H113: 90.32 | I113: 3580.1504 | J113: =+I113*H113 -> 323359.19 | K113: =+人工费!K113 -> 10.371 | L113: =+R113 -> 4059.5518 | M113: =+L113*K113 -> 42101.612 | P113: =+O113*N113 -> 0 | Q113: =+人工费!Q113 -> 35.399 | R113: 4059.5518 | S113: =+R113*Q113 -> 143704.07 | V113: =+U113*T113 -> 0 | AB113: 0
A114: 1.7 | B114: 现浇构件钢筋 | C114: (1)钢筋种类、规格:螺纹钢制安Ⅲ级(HRB400E)φ12mm_x000D_ (2)满足设计图纸、相关规范、招标文件及技术要求_x000D_ (3)建筑物超高增加费 | D114: t | E114: 94.88 | F114: 4074.2909 | G114: =+F114*E114 -> 386568.72 | H114: 94.88 | I114: 3518.3274 | J114: =+I114*H114 -> 333818.91 | K114: =+人工费!K114 -> 14.274 | L114: =+R114 -> 4074.2909 | M114: =+L114*K114 -> 58156.428 | P114: =+O114*N114 -> 0 | Q114: =+人工费!Q114 -> 40.931 | R114: 4074.2909 | S114: =+R114*Q114 -> 166764.8 | V114: =+U114*T114 -> 0 | AB114: 0
...

Sheet 机械费
A1: 工程项目机械费计算表
A2: 工程名称： XXX项目
A3: 序号 | B3: 机械名称及型号 | C3: 单位 | D3: 预测工程竣工数据统计 | J3: 本期数据统计 | Q3: 累计数据统计 | X3: 备注 | AA3: 上次累计数据统计
D4: 预算收入 | G4: 计划成本 | J4: 预算收入 | M4: 实际成本 | Q4: 预算收入 | T4: 实际成本 | AA4: 预算收入 | AD4: 实际成本
D5: 工程量 | E5: 单价 | F5: 合价 | G5: 工程量 | H5: 单价 | I5: 合计 | J5: 工程量 | K5: 单价 | L5: 合价 | M5: 工程量 | N5: 天数 | O5: 单价 | P5: 合价 | Q5: 工程量 | R5: 单价 | S5: 合价 | T5: 工程量 | U5: 天数 | V5: 单价 | W5: 合价 | AA5: 工程量 | AB5: 单价 | AC5: 合价 | AD5: 工程量 | AE5: 天数 | AF5: 单价 | AG5: 合价
A6: 一 | B6: 塔吊 | F6: 1807634.2 | I6: 2311838.8 | L6: =SUM(L7:L14) -> 106842.51 | P6: =SUM(P7:P14) -> 141000 | S6: =SUM(S7:S14) -> 1009698.5 | W6: =SUM(W7:W14) -> 1273187.6 | AC6: 902855.95 | AG6: 1351787.6
A7: 1 | B7: 塔吊7020 | C7: 元 | F7: 1495795.2 | I7: 1048800 | J7: =+Q7-AA7 -> 2 | K7: =+R7 -> 53421.257 | L7: =K7*J7 -> 106842.51 | M7: =+T7 -> 1 | N7: =+U7-AE7 -> 2 | O7: =+V7 -> 34500 | P7: =+O7*N7*M7 -> 69000 | Q7: =+U7 -> 14.2 | R7: =F7/2/14 -> 53421.257 | S7: =+R7*Q7 -> 758581.85 | T7: 1 | U7: =2.23+1.17+2+2+2+2.8+2 -> 14.2 | V7: 34500 | W7: =+V7*U7*T7 -> 489900 | AA7: 12.2 | AB7: 53421.257 | AC7: 651739.34 | AD7: 1 | AE7: 12.2 | AF7: 34500 | AG7: 420900
A8: 2 | B8: 塔吊司机 | C8: 元 | F8: 0 | I8: 504000 | L8: =K8*J8 -> 0 | M8: =+T8 -> 1 | N8: =+U8-AE8 -> 2 | O8: =+V8 -> 18000 | P8: =+O8*N8*M8 -> 36000 | S8: =+R8*Q8 -> 0 | T8: 1 | U8: =+U7 -> 14.2 | V8: 18000 | W8: =+V8*U8*T8 -> 255600 | AC8: 0 | AD8: 1 | AE8: 12.2 | AF8: 18000 | AG8: 219600
A9: 3 | B9: 塔吊指挥 | C9: 元 | F9: 0 | I9: 504000 | L9: =K9*J9 -> 0 | M9: =+T9 -> 1 | N9: =+U9-AE9 -> 2 | O9: =+V9 -> 18000 | P9: =+O9*N9*M9 -> 36000 | S9: =+R9*Q9 -> 0 | T9: 1 | U9: =+U7 -> 14.2 | V9: 18000 | W9: =+V9*U9*T9 -> 255600 | AC9: 0 | AD9: 2 | AE9: 12.2 | AF9: 18000 | AG9: 439200
A10: 4 | B10: 塔吊7020进出场及安拆费 | C10: 元 | F10: 121444.82 | I10: 124000 | J10: =+Q10-AA10 -> 0 | K10: =+R10 -> 121444.82 | L10: =K10*J10 -> 0 | M10: =+T10-AD10 -> 0 | N10: / | O10: 62000 | P10: =+O10*M10 -> 0 | Q10: 0.5 | R10: 121444.82 | S10: =+R10*Q10 -> 60722.411 | T10: 1 | U10: / | V10: 62000 | W10: =+V10*T10 -> 62000 | AA10: 0.5 | AB10: 121444.82 | AC10: 60722.411 | AD10: 1 | AE10: / | AF10: 62000 | AG10: 62000
A11: 5 | B11: 塔吊基础混凝土 | C11: 元 | F11: 190394.21 | I11: 81856.768 | J11: =+Q11-AA11 -> 0 | K11: =+R11 -> 190394.21 | L11: =K11*J11 -> 0 | M11: =+T11-AD11 -> 0 | N11: / | O11: 438.05017 | P11: =+O11*M11 -> 0 | Q11: 1 | R11: 190394.21 | S11: =+R11*Q11 -> 190394.21 | T11: 269.5 | U11: / | V11: =+W11/T11 -> 438.05017 | W11: 118054.52 | AA11: 1 | AB11: 190394.21 | AC11: 190394.21 | AD11: 269.5 | AE11: / | AF11: 438.05017 | AG11: 118054.52
A12: 6 | B12: 塔吊基础钢筋 | C12: 元 | I12: 18384 | L12: =K12*J12 -> 0 | M12: =+T12-AD12 -> 0 | N12: / | O12: 3498.7871 | P12: =+O12*M12 -> 0 | S12: =+R12*Q12 -> 0 | T12: 16.489 | U12: / | V12: =+W12/T12 -> 3498.7871 | W12: 57691.5 | AC12: 0 | AD12: 16.489 | AE12: / | AF12: 3498.7871 | AG12: 57691.5
A13: 7 | B13: 塔吊基础混凝土人工 | C13: 元 | I13: 11648 | L13: =K13*J13 -> 0 | M13: =+T13-AD13 -> 0 | N13: / | O13: 48.5 | P13: =+O13*M13 -> 0 | S13: =+R13*Q13 -> 0 | T13: 269.5 | U13: / | V13: 48.5 | W13: =+V13*T13 -> 13070.75 | AC13: 0 | AD13: 269.5 | AE13: / | AF13: 48.5 | AG13: 13070.75
A14: 8 | B14: 塔吊基础钢筋人工 | C14: 元 | I14: 19150 | L14: =K14*J14 -> 0 | M14: =+T14-AD14 -> 0 | N14: / | O14: 1290 | P14: =+O14*M14 -> 0 | S14: =+R14*Q14 -> 0 | T14: 16.489 | U14: / | V14: 1290 | W14: =+V14*T14 -> 21270.81 | AC14: 0 | AD14: 16.489 | AE14: / | AF14: 1290 | AG14: 21270.81
A15: 二 | B15: 施工电梯 | F15: 964650.21 | I15: 1599500.9 | L15: =SUM(L16:L22) -> 0 | P15: =SUM(P16:P22) -> 201672.83 | S15: =SUM(S16:S22) -> 183497.32 | W15: =SUM(W16:W22) -> 201672.83 | AC15: 0 | AG15: 0
A16: 1 | B16: SC200/200、100-150米租赁费 | C16: 元 | F16: 908510.47 | I16: 317500 | L16: =+K16*J16 -> 0 | M16: =+T16 -> 1 | N16: =+U16-AE16 -> 4.2 | O16: =+V16 -> 18000 | P16: =+O16*M16*N16 -> 75600 | Q16: =+U16 -> 4.2 | R16: =F16/12.275/2 -> 37006.537 | S16: =+R16*Q16 -> 155427.45 | T16: 1 | U16: =2.33+1.87 -> 4.2 | V16: 18000 | W16: =+V16*T16*U16 -> 75600 | AC16: 0 | AG16: 0
A17: 2 | B17: 电梯司机 | C17: 元 | I17: 432000 | L17: =+K17*J17 -> 0 | M17: =+T17 -> 1 | N17: =+U17-AE17 -> 4.2 | O17: =+V17 -> 18000 | P17: =+O17*M17*N17 -> 75600 | S17: =+R17*Q17 -> 0 | T17: 1 | U17: =+U16 -> 4.2 | V17: 18000 | W17: =+V17*T17*U17 -> 75600 | AC17: 0 | AG17: 0
A18: 3 | B18: SC200/200、100-150米进出场安拆费用 | C18: 元 | F18: 56139.735 | I18: 838200 | L18: =+K18*J18 -> 0 | M18: =+T18-AD18 -> 1 | N18: / | O18: =+V18 -> 38000 | P18: =+O18*M18 -> 38000 | Q18: 0.5 | R18: =+F18 -> 56139.735 | S18: =+R18*Q18 -> 28069.868 | T18: =0.5+0.5 -> 1 | U18: / | V18: 38000 | W18: =+V18*T18 -> 38000 | AC18: 0 | AG18: 0
A19: 4 | B19: 电梯基础混凝土 | C19: 元 | I19: 8879.9976 | L19: =+K19*J19 -> 0 | M19: =+T19-AD19 -> 32.5 | N19: / | O19: =+V19 -> 335.27938 | P19: =+O19*M19 -> 10896.58 | S19: =+R19*Q19 -> 0 | T19: 32.5 | U19: / | V19: =+W19/T19 -> 335.27938 | W19: 10896.58 | AC19: 0 | AG19: 0
A20: 5 | B20: 电梯基础钢筋 | C20: 元 | I20: 1282.3009 | L20: =+K20*J20 -> 0 | M20: =+T20-AD20 -> 0 | N20: / | O20: =+V20 -> 0 | P20: =+O20*M20 -> 0 | S20: =+R20*Q20 -> 0 | U20: / | W20: =+V20*T20 -> 0 | AC20: 0 | AG20: 0
A21: 6 | B21: 电梯基础混凝土人工 | C21: 元 | I21: 1263.6 | L21: =+K21*J21 -> 0 | M21: =+T21-AD21 -> 32.5 | N21: / | O21: =+V21 -> 48.5 | P21: =+O21*M21 -> 1576.25 | S21: =+R21*Q21 -> 0 | T21: =+T19 -> 32.5 | U21: / | V21: 48.5 | W21: =+V21*T21 -> 1576.25 | AC21: 0 | AG21: 0
A22: 7 | B22: 电梯基础钢筋人工 | C22: 元 | I22: 375 | L22: =+K22*J22 -> 0 | M22: =+T22-AD22 -> 0 | N22: / | O22: =+V22 -> 1290 | P22: =+O22*M22 -> 0 | S22: =+R22*Q22 -> 0 | T22: =+T20 -> 0 | U22: / | V22: 1290 | W22: =+V22*T22 -> 0 | AC22: 0 | AG22: 0
A23: 三 | B23: 泵送费 | C23: 元 | F23: 136065.24 | I23: 451279.3 | J23: =材料费!K286/23296.47 -> 0.044863054 | K23: =+R23 -> 136065.24 | L23: =+S23-AC23 -> 6104.3022 | P23: =+W23-AG23 -> -55376.782 | Q23: =材料费!Q286/23296.47 -> 0.7274476 | R23: 136065.24 | S23: =R23*Q23 -> 98980.33 | W23: =481352.03/1.13 -> 425975.25 | AA23: 0.68258454 | AB23: 136065.24 | AC23: 92876.028 | AG23: 481352.03
A24: 四 | B24: 小型机械费用 | C24: 元 | I24: 135383.79 | L24: =+S24-AC24 -> 0 | P24: =+W24-AG24 -> 0 | S24: =+R24*Q24 -> 0 | W24: =107050+3450 -> 110500 | AC24: 0 | AG24: 110500
A25: 五 | B25: 施工水电费 | C25: 元 | I25: 812302.74 | L25: =+S25-AC25 -> 0 | P25: =+W25-AG25 -> 30483.34 | S25: =+R25*Q25 -> 0 | W25: 211286.91 | AC25: 0 | AG25: 180803.57
B26: 合计 | F26: =+F25+F24+F23+F15+F6 -> 2908349.7 | I26: =+I25+I24+I23+I15+I6 -> 5310305.5 | L26: =+L25+L24+L23+L15+L6 -> 112946.82 | P26: =+P25+P24+P23+P15+P6 -> 317779.39 | S26: =+S25+S24+S23+S15+S6 -> 1292176.1 | W26: =+W25+W24+W23+W15+W6 -> 2222622.6 | AC26: 995731.98 | AG26: 2124443.2

Sheet 专业分包费
A1: 工程项目专业分包费计算表
A2: 工程名称： XXX项目
A3: 序号 | B3: 分部分项名称 | C3: 项目特征 | D3: 单位 | E3: 预测工程竣工数据统计 | K3: 本期数据统计 | Q3: 累计数据统计 | W3: 备注 | Y3: 上次累计数据统计
E4: 预算收入 | H4: 计划成本 | K4: 预算收入 | N4: 实际成本 | Q4: 预算收入 | T4: 实际成本 | Y4: 预算收入 | AB4: 实际成本
E5: 工程量 | F5: 单价 | G5: 合价 | H5: 工程量 | I5: 单价 | J5: 合计 | K5: 工程量 | L5: 单价 | M5: 合价 | N5: 工程量 | O5: 单价 | P5: 合价 | Q5: 工程量 | R5: 单价 | S5: 合价 | T5: 工程量 | U5: 单价 | V5: 合价 | X5: =+X294+X295+X296+X312+X313+X468 -> 1093058.7 | Y5: 工程量 | Z5: 单价 | AA5: 合价 | AB5: 工程量 | AC5: 单价 | AD5: 合价
A6: 一 | B6: 土石方工程 | G6: =SUM(G7:G15) -> 748244.66 | J6: =SUM(J7:J15) -> 414077.95 | M6: =SUM(M7:M15) -> -37489.213 | P6: =SUM(P7:P15) -> -312278.28 | S6: =SUM(S7:S15) -> 2121654.5 | V6: =SUM(V7:V15) -> 1652037.3 | AA6: 2121654.5 | AD6: 1964315.6
A7: 1 | B7: 挖一般土方 | D7: m3 | E7: 2029.36 | F7: 3.3954953 | G7: 6890.6824 | H7: 2029.36 | J7: 20293.6 | K7: =+Q7-Y7 -> 0 | L7: =+R7 -> 3.3954953 | M7: =+L7*K7 -> 0 | N7: =+T7-AB7 -> 0 | O7: =+U7 -> 7 | P7: =+O7*N7 -> 0 | Q7: 12899.8 | R7: 3.3954953 | S7: =+R7*Q7 -> 43801.211 | T7: =+Q7 -> 12899.8 | U7: 7 | V7: =+U7*T7 -> 90298.6 | W7: =_xlfn.DISPIMG("ID_B109C0F5CA4242FF90574D65B8EAB85B",1) -> #NAME? | Y7: 12899.8 | Z7: 3.3954953 | AA7: 43801.211 | AB7: 12899.8 | AC7: 7 | AD7: 90298.6
A8: 2 | B8: 挖基坑土方 | D8: m3 | E8: 449.33 | F8: 8.6784308 | G8: 3899.4793 | H8: 449.33 | J8: 6739.95 | K8: =+Q8-Y8 -> 0 | L8: =+R8 -> 8.6784308 | M8: =+L8*K8 -> 0 | N8: =+T8-AB8 -> -1452.8658 | O8: =+U8 -> 12 | P8: =+O8*N8 -> -17434.389 | Q8: 2197.28 | R8: 8.6784308 | S8: =+R8*Q8 -> 19068.942 | T8: 744.41425 | U8: 12 | V8: =+U8*T8 -> 8932.971 | Y8: 2197.28 | Z8: 8.6784308 | AA8: 19068.942 | AB8: 2197.28 | AC8: 12 | AD8: 26367.36
A9: 3 | B9: 石方破除 | D9: m3 | E9: 299.55 | F9: 104.56798 | G9: 31323.338 | H9: 299.55 | J9: 11982 | K9: =+Q9-Y9 -> 0 | L9: =+R9 -> 104.56798 | M9: =+L9*K9 -> 0 | N9: =+T9-AB9 -> 0 | O9: =+U9 -> 35 | P9: =+O9*N9 -> 0 | Q9: 16.13 | R9: 104.56798 | S9: =+R9*Q9 -> 1686.6815 | T9: 0 | U9: 35 | V9: =+U9*T9 -> 0 | Y9: 16.13 | Z9: 104.56798 | AA9: 1686.6815 | AB9: 0 | AC9: 35 | AD9: 0
A10: 4 | B10: 余方弃置 | D10: m3 | E10: 2778.24 | F10: 137.52705 | G10: 382083.14 | H10: 2778.24 | J10: 375062.4 | K10: =+Q10-Y10 -> 0 | L10: =+R10 -> 137.52705 | M10: =+L10*K10 -> 0 | N10: =+T10-AB10 -> -2070.3658 | O10: =+U10 -> 120 | P10: =+O10*N10 -> -248443.89 | Q10: 15397.08 | R10: 137.52705 | S10: =+R10*Q10 -> 2117514.9 | T10: 13326.714 | U10: 120 | V10: =+U10*T10 -> 1599205.7 | Y10: 15397.08 | Z10: 137.52705 | AA10: 2117514.9 | AB10: 15397.08 | AC10: 120 | AD10: 1847649.6
A11: 5 | B11: 场内取土回填 | D11: m3 | E11: 2478.69 | F11: 19.585748 | G11: 48546.998 | H11: 2478.69 | J11: 0 | K11: =+Q11-Y11 -> 0 | L11: =+R11 -> 19.585748 | M11: =+L11*K11 -> 0 | N11: =+T11-AB11 -> 0 | O11: 0 | P11: =+O11*N11 -> 0 | Q11: 1264.78 | R11: 19.585748 | S11: =+R11*Q11 -> 24771.663 | T11: 0 | U11: 0 | V11: =+U11*T11 -> 0 | Y11: 1264.78 | Z11: 19.585748 | AA11: 24771.663 | AB11: 0 | AC11: 0 | AD11: 0
A12: 6 | B12: 场外取土回填 | D12: m3 | E12: 5907.12 | F12: 55.428142 | G12: 327420.68 | H12: 5907.12 | J12: 0 | K12: =+Q12-Y12 -> 0 | L12: =+R12 -> 55.428142 | M12: =+L12*K12 -> 0 | N12: =+T12-AB12 -> 2320 | O12: -20 | P12: =+O12*N12 -> -46400 | Q12: 0 | R12: 55.428142 | S12: =+R12*Q12 -> 0 | T12: 2320 | U12: -20 | V12: =+U12*T12 -> -46400 | Y12: 0 | Z12: 55.428142 | AA12: 0 | AB12: 0 | AC12: -20 | AD12: 0
A13: 7 | B13: 场外取土回填(群楼、塔楼屋面) | D13: m3 | E13: 150 | F13: 58.339921 | G13: 8750.9882 | H13: 150 | J13: 0 | K13: =+Q13-Y13 -> 0 | L13: =+R13 -> 58.339921 | M13: =+L13*K13 -> 0 | N13: =+T13-AB13 -> 0 | O13: 0 | P13: =+O13*N13 -> 0 | Q13: 0 | R13: 58.339921 | S13: =+R13*Q13 -> 0 | T13: 0 | U13: 0 | V13: =+U13*T13 -> 0 | Y13: 0 | Z13: 58.339921 | AA13: 0 | AB13: 0 | AC13: 0 | AD13: 0
A14: 8 | B14: 管理费 | D14: 项 | E14: 1 | F14: -29515.941 | G14: -29515.941 | H14: 1 | J14: 0 | K14: 1 | L14: =+R14 -> -6334.5 | M14: =+L14*K14 -> -6334.5 | N14: =+T14-AB14 -> 0 | O14: 0 | P14: =+O14*N14 -> 0 | Q14: 1 | R14: -6334.5 | S14: =+R14*Q14 -> -6334.5 | Y14: 1 | Z14: -6334.5 | AA14: -6334.5 | AB14: 0 | AC14: 0 | AD14: 0
A15: 9 | B15: 利润 | D15: 项 | E15: 1 | F15: -31154.713 | G15: -31154.713 | H15: 1 | J15: 0 | K15: 1 | L15: =F15 -> -31154.713 | M15: =+L15*K15 -> -31154.713 | N15: =+T15-AB15 -> 0 | O15: 0 | P15: =+O15*N15 -> 0 | Q15: 1 | R15: -78854.41 | S15: =+R15*Q15 -> -78854.41 | Y15: 1 | Z15: -78854.41 | AA15: -78854.41 | AB15: 0 | AC15: 0 | AD15: 0
A16: 二 | B16: 幕墙工程 | G16: 2682918.9 | J16: 5551864.2 | M16: =SUM(M17:M31) -> -234160.23 | P16: =SUM(P17:P31) -> 0 | S16: =SUM(S17:S31) -> -234160.23 | V16: =SUM(V17:V31) -> 0 | AA16: 0 | AD16: 0
A17: 1 | B17: 铝合金格栅幕墙 | C17: (1)立面铝合金格栅_x000D_ (2)铝合金表面做法:可见部分表面氟碳喷涂，不可见部分采用阳极氧化处理_x000D_ (3)综合单价包括面层、骨架、铝合金挂件、M6铝种钉和不锈钢弹簧垫圈@300mm、结构胶、胶带、阳极氧化角铝等费用综合考虑等所有费用_x000D_ (4)工程量计算规则:按设计图示尺寸以正立面投影面积计算_x000D_ (5)图纸位置;塔楼屋面，裙楼图F4014，F3012，F2001~05-EL(裙房),F3001~03-PE(裙房)_x000D_ (6)满足设计图纸、相关规范、招标文件及技术要求_x000D_ (7)建筑物超高增加费 | D17: m2 | E17: 668.56 | F17: 542.78605 | G17: 362885.04 | H17: 668.56 | J17: 735416 | L17: 542.78605 | M17: =+L17*K17 -> 0 | P17: =+O17*N17 -> 0 | R17: 542.78605 | S17: =+R17*Q17 -> 0 | V17: =+U17*T17 -> 0 | Z17: 542.78605 | AA17: 0 | AD17: 0
A18: 2 | B18: 铝单板幕墙 | C18: (1)2.5mm厚铝单板(氟碳三涂，颜色综合考虑)_x000D_ (2)综合单价包括面层、骨架、连接件等所有费用_x000D_ (3)工程量计算规则:按设计图示尺寸以可见光铝板展开面积计算_x000D_ (4)满足设计图纸、相关规范、招标文件及技术要求_x000D_ (5)建筑物超高增加费 | D18: m2 | E18: 3205.63 | F18: 450.26355 | G18: 1443378.3 | H18: 3205.63 | J18: 3109461.1 | L18: 450.26355 | M18: =+L18*K18 -> 0 | P18: =+O18*N18 -> 0 | R18: 450.26355 | S18: =+R18*Q18 -> 0 | V18: =+U18*T18 -> 0 | Z18: 450.26355 | AA18: 0 | AD18: 0
A19: 3 | B19: 穿孔铝板幕墙一 | C19: (1)4mm厚穿孔铝板(粉末喷涂，颜色综合考虑)_x000D_ (2)综合单价包括面层、骨架、连接件等所有费用_x000D_ (3)工程量计算规则:按设计图示尺寸以可见光铝板展开面积计算_x000D_ (4)满足设计图纸、相关规范、招标文件及技术要求_x000D_ (5)建筑物超高增加费 | D19: m2 | E19: 177.54 | F19: 447.39919 | G19: 79431.253 | H19: 177.54 | J19: 213048 | L19: 447.39919 | M19: =+L19*K19 -> 0 | P19: =+O19*N19 -> 0 | R19: 447.39919 | S19: =+R19*Q19 -> 0 | V19: =+U19*T19 -> 0 | Z19: 447.39919 | AA19: 0 | AD19: 0
A20: 4 | B20: 穿孔铝板幕墙二 | C20: (1)2mm厚穿孔铝板，穿孔率10%(粉末喷涂，颜色综合考虑)_x000D_ (2)综合单价包括面层、骨架、连接件等所有费用_x000D_ (3)满足设计图纸、相关规范、招标文件及技术要求_x000D_ (4)建筑物超高增加费 | D20: m2 | E20: 773.15 | F20: 253.23946 | G20: 195792.09 | H20: 773.15 | J20: 564399.5 | L20: 253.23946 | M20: =+L20*K20 -> 0 | P20: =+O20*N20 -> 0 | R20: 253.23946 | S20: =+R20*Q20 -> 0 | V20: =+U20*T20 -> 0 | Z20: 253.23946 | AA20: 0 | AD20: 0
A21: 5 | B21: 铝合金格栅雨棚 | C21: (1)铝合金型材格栅雨棚_x000D_ (2)铝合金表面做法:可见部分表面氟碳喷涂，不可见部分采用阳极氧化处理_x000D_ (3)综合单价包括面层、骨架、铝合金挂件、M6铝种钉和不锈钢弹簧垫圈@300mm、结构胶、胶带、阳极氧化角铝等费用综合考虑_x000D_ (4)详雨棚图纸F3006,及个节点大样_x000D_ (5)满足设计图纸、相关规范、招标文件及技术要求_x000D_ (6)建筑物超高增加费 | D21: m2 | E21: 86 | F21: 537.6359 | G21: 46236.688 | H21: 86 | J21: 48749.1 | L21: 537.6359 | M21: =+L21*K21 -> 0 | P21: =+O21*N21 -> 0 | R21: 537.6359 | S21: =+R21*Q21 -> 0 | V21: =+U21*T21 -> 0 | Z21: 537.6359 | AA21: 0 | AD21: 0
A22: 6 | B22: 不锈钢水槽 | C22: (1)2mm厚316不锈钢板_x000D_ (2)工程量计算规则:按设计图示尺寸以展开面积计算_x000D_ (3)详雨棚图纸F3006,及个节点大样_x000D_ (4)满足设计图纸、相关规范、招标文件及技术要求_x000D_ (5)建筑物超高增加费 | D22: m2 | E22: 62.87 | F22: 479.12526 | G22: 30122.605 | H22: 62.87 | J22: 31759.409 | L22: 479.12526 | M22: =+L22*K22 -> 0 | P22: =+O22*N22 -> 0 | R22: 479.12526 | S22: =+R22*Q22 -> 0 | V22: =+U22*T22 -> 0 | Z22: 479.12526 | AA22: 0 | AD22: 0
A23: 7 | B23: 铝合金格栅吊顶 | C23: (1)架空层吊顶,铝合金格栅 A15、A16_x000D_ (2)铝合金表面做法:可见部分表面氟碳喷涂，不可见部分采用阳极氧化处理_x000D_ (3)图纸:F1019~1023-PL(吊顶)，大样图F4029_x000D_ (4)钢骨架:100x50x5mm方管, 氟碳喷涂(深色)转接件间距@3000mm；120x60x4mm方管@1200mm, 氟碳喷涂(深色)_x000D_ (5)满足设计图纸、相关规范、招标文件及技术要求_x000D_ (6)建筑物超高增加费 | D23: m2 | E23: 850 | F23: 347.61146 | G23: 295469.74 | H23: 850 | J23: 306000 | L23: 347.61146 | M23: =+L23*K23 -> 0 | P23: =+O23*N23 -> 0 | R23: 347.61146 | S23: =+R23*Q23 -> 0 | V23: =+U23*T23 -> 0 | Z23: 347.61146 | AA23: 0 | AD23: 0
A24: 8 | B24: 石材幕墙 | C24: (1)30mm厚大理石，6面防护处理_x000D_ (2)综合单价包括面层、热镀锌钢骨架、铝合金挂件、石材背栓件、连接件、螺栓、防火隔离带封堵、保温棉、嵌缝塞缝防水、防雷接地、石材加工防护费(石材磨边、倒角、切割、拼接、背筋、六面防水防污防腐、养护等)等除所有费用_x000D_ (3)满足设计图纸、相关规范、招标文件及技术要求_x000D_ (4)建筑物超高增加费 | D24: m2 | E24: 47.68 | F24: 520.29801 | G24: 24807.809 | H24: 47.68 | J24: 61030.4 | L24: 520.29801 | M24: =+L24*K24 -> 0 | P24: =+O24*N24 -> 0 | R24: 520.29801 | S24: =+R24*Q24 -> 0 | V24: =+U24*T24 -> 0 | Z24: 520.29801 | AA24: 0 | AD24: 0
A25: 9 | B25: 铝合金装饰线一 | C25: (1)铝合金装饰线条 A4_x000D_ (2)铝合金表面做法:可见部分表面氟碳喷涂，不可见部分采用阳极氧化处理_x000D_ (3)图纸:大样图F4006_x000D_ (4)M8后扩底锚栓两颗一组@650mm_x000D_ (5)75x50x4mm热镀锌角钢L=110mm@650mm_x000D_ (6)泡沫棒&密封胶_x000D_ (7)满足设计图纸、相关规范、招标文件及技术要求_x000D_ (8)建筑物超高增加费 | D25: m | E25: 120.4 | F25: 76.152045 | G25: 9168.7062 | H25: 120.4 | J25: 9666.916 | L25: 76.152045 | M25: =+L25*K25 -> 0 | P25: =+O25*N25 -> 0 | R25: 76.152045 | S25: =+R25*Q25 -> 0 | V25: =+U25*T25 -> 0 | Z25: 76.152045 | AA25: 0 | AD25: 0
A26: 10 | B26: 铝合金装饰线二 | C26: (1)铝合金装饰线条 A6_x000D_ (2)铝合金表面做法:可见部分表面氟碳喷涂，不可见部分采用阳极氧化处理_x000D_ (3)图纸:大样图F3005_x000D_ (4)满足设计图纸、相关规范、招标文件及技术要求_x000D_ (5)建筑物超高增加费 | D26: m | E26: 54 | F26: 25.902508 | G26: 1398.7354 | H26: 54 | J26: 1474.74 | L26: 25.902508 | M26: =+L26*K26 -> 0 | P26: =+O26*N26 -> 0 | R26: 25.902508 | S26: =+R26*Q26 -> 0 | V26: =+U26*T26 -> 0 | Z26: 25.902508 | AA26: 0 | AD26: 0
A27: 11 | B27: 裙楼首层玻璃幕墙 | C27: (1)玻璃幕墙(含地弹门)_x000D_ (2)断热铝合金+较低透光Low-E中空玻璃6+12A+6，含弧形玻璃_x000D_ (3)铝合金表面做法:可见部分表面氟碳喷涂，不可见部分采用阳极氧化处理_x000D_ (4)含全部五金配件_x000D_ (5)综合单价包括面层、骨架、结构胶、密封胶等费用综合考虑等所有费用_x000D_ (6)工程量计算规则:按设计图示框外围尺寸计算_x000D_ (7)满足设计图纸、相关规范、招标文件及技术要求_x000D_ (8)建筑物超高增加费 | D27: m2 | E27: 321.71 | F27: 929.5785 | G27: 299054.7 | H27: 321.71 | J27: 337152.08 | L27: 929.5785 | M27: =+L27*K27 -> 0 | P27: =+O27*N27 -> 0 | R27: 929.5785 | S27: =+R27*Q27 -> 0 | V27: =+U27*T27 -> 0 | Z27: 929.5785 | AA27: 0 | AD27: 0
A28: 12 | B28: 预埋件 | C28: (1)结构镀锌钢预埋件_x000D_ (2)预埋在主体结构，综合考虑_x000D_ (3)满足设计图纸、相关规范、招标文件及技术要求_x000D_ (4)建筑物超高增加费 | D28: t | E28: 9.723 | F28: 8810.6939 | G28: 85666.377 | H28: 9.723 | J28: 87507 | L28: 8810.6939 | M28: =+L28*K28 -> 0 | P28: =+O28*N28 -> 0 | R28: 8810.6939 | S28: =+R28*Q28 -> 0 | V28: =+U28*T28 -> 0 | Z28: 8810.6939 | AA28: 0 | AD28: 0
A29: 13 | B29: 后置埋件 | C29: (1)后置埋件_x000D_ (2)12mm厚热镀锌钢板300*250mm，M12后扩底不锈钢锚栓_x000D_ (3)因投标单位自身原因(如预埋件埋偏等)增加后置埋件不给予计算工程量_x000D_ (4)满足设计图纸、相关规范、招标文件及技术要求_x000D_ (5)建筑物超高增加费 | D29: 套 | E29: 308 | F29: 141.77616 | G29: 43667.056 | H29: 308 | J29: 46200 | L29: 141.77616 | M29: =+L29*K29 -> 0 | P29: =+O29*N29 -> 0 | R29: 141.77616 | S29: =+R29*Q29 -> 0 | V29: =+U29*T29 -> 0 | Z29: 141.77616 | AA29: 0 | AD29: 0
A30: 14 | B30: 管理费 | D30: 项 | E30: 1 | F30: -95274.299 | G30: -95274.299 | H30: 1 | J30: 0 | K30: 1 | L30: -95274.299 | M30: =+L30*K30 -> -95274.299 | P30: =+O30*N30 -> 0 | Q30: 1 | R30: -95274.299 | S30: =+R30*Q30 -> -95274.299 | V30: =+U30*T30 -> 0 | Z30: -95274.299 | AA30: 0 | AD30: 0
A31: 15 | B31: 利润 | D31: 项 | E31: 1 | F31: -138885.93 | G31: -138885.93 | H31: 1 | J31: 0 | K31: 1 | L31: -138885.93 | M31: =+L31*K31 -> -138885.93 | P31: =+O31*N31 -> 0 | Q31: 1 | R31: -138885.93 | S31: =+R31*Q31 -> -138885.93 | V31: =+U31*T31 -> 0 | Z31: -138885.93 | AA31: 0 | AD31: 0
A32: 三 | B32: 门窗工程 | G32: 6371514.5 | J32: 7029195.8 | M32: =+M33+M60+M96+M131 -> -13057.7 | P32: =+P33+P60+P96+P131 -> 0 | S32: =+S33+S60+S96+S131 -> -13057.7 | V32: =+V33+V60+V96+V131 -> 0 | AA32: 0 | AD32: 0
A33: 1 | B33: 地下室 | F33: 0 | M33: =+M34+M39+M44+M47+M50+M58+M59 -> -13057.7 | P33: =+P34+P39+P44+P47+P50+P58+P59 -> 0 | R33: 0 | S33: =+S34+S39+S44+S47+S50+S58+S59 -> -13057.7 | V33: =+V34+V39+V44+V47+V50+V58+V59 -> 0 | Z33: 0 | AA33: 0 | AD33: 0
A34: 1.1 | B34: 甲级防火门 | F34: 0 | M34: =SUM(M35:M38) -> 0 | P34: =SUM(P35:P38) -> 0 | R34: 0 | S34: =SUM(S35:S38) -> 0 | V34: =SUM(V35:V38) -> 0 | Z34: 0 | AA34: 0 | AD34: 0
A35: 1.1.1 | B35: 钢质防火门 | C35: (1)甲级钢质防火门，FM甲0619_x000D_ (2)尺寸：600x1900_x000D_ (3)含控制箱、闭门器、顺序器等全部不锈钢五金配件安装_x000D_ (4)前室、合用前室以及楼梯间的防火门须带视口_x000D_ (5)满足设计图纸、相关规范、招标文件及技术要求 | D35: 樘 | E35: 1 | F35: 543.9906 | G35: 543.9906 | H35: 1 | J35: 535.8 | L35: 543.9906 | M35: =+L35*K35 -> 0 | P35: =+O35*N35 -> 0 | R35: 543.9906 | S35: =+R35*Q35 -> 0 | V35: =+U35*T35 -> 0 | Z35: 543.9906 | AA35: 0 | AD35: 0
A36: 1.1.2 | B36: 钢质防火门 | C36: (1)甲级钢质防火门，FM甲0821_x000D_ (2)尺寸：800x2100_x000D_ (3)含控制箱、闭门器、顺序器等全部不锈钢五金配件安装_x000D_ (4)前室、合用前室以及楼梯间的防火门须带视口_x000D_ (5)满足设计图纸、相关规范、招标文件及技术要求 | D36: 樘 | E36: 1 | F36: 801.67835 | G36: 801.67835 | H36: 1 | J36: 789.6 | L36: 801.67835 | M36: =+L36*K36 -> 0 | P36: =+O36*N36 -> 0 | R36: 801.67835 | S36: =+R36*Q36 -> 0 | V36: =+U36*T36 -> 0 | Z36: 801.67835 | AA36: 0 | AD36: 0
A37: 1.1.3 | B37: 钢质防火门 | C37: (1)甲级钢质防火门，FM甲10a21_x000D_ (2)尺寸：1100x2100_x000D_ (3)含控制箱、闭门器、顺序器等全部不锈钢五金配件安装_x000D_ (4)前室、合用前室以及楼梯间的防火门须带视口_x000D_ (5)满足设计图纸、相关规范、招标文件及技术要求 | D37: 樘 | E37: 10 | F37: 1102.303 | G37: 11023.03 | H37: 10 | J37: 9870 | L37: 1102.303 | M37: =+L37*K37 -> 0 | P37: =+O37*N37 -> 0 | R37: 1102.303 | S37: =+R37*Q37 -> 0 | V37: =+U37*T37 -> 0 | Z37: 1102.303 | AA37: 0 | AD37: 0
A38: 1.1.4 | B38: 钢质防火门 | C38: (1)甲级钢质防火门，FM甲1521_x000D_ (2)尺寸：1500x2100_x000D_ (3)含控制箱、闭门器、顺序器等全部不锈钢五金配件安装_x000D_ (4)前室、合用前室以及楼梯间的防火门须带视口_x000D_ (5)满足设计图纸、相关规范、招标文件及技术要求 | D38: 樘 | E38: 36 | F38: 1503.1422 | G38: 54113.118 | H38: 36 | J38: 53298 | L38: 1503.1422 | M38: =+L38*K38 -> 0 | P38: =+O38*N38 -> 0 | R38: 1503.1422 | S38: =+R38*Q38 -> 0 | V38: =+U38*T38 -> 0 | Z38: 1503.1422 | AA38: 0 | AD38: 0
A39: 1.2 | B39: 乙级防火门 | F39: 0 | J39: 0 | M39: =SUM(M40:M43) -> 0 | P39: =SUM(P40:P43) -> 0 | S39: =SUM(S40:S43) -> 0 | V39: =SUM(V40:V43) -> 0 | AA39: 0 | AD39: 0
A40: 1.2.1 | B40: 钢质防火门 | C40: (1)乙级钢质防火门，FM乙10a21_x000D_ (2)尺寸：1100x2100_x000D_ (3)含控制箱、闭门器、顺序器等全部不锈钢五金配件安装_x000D_ (4)前室、合用前室以及楼梯间的防火门须带视口_x000D_ (5)满足设计图纸、相关规范、招标文件及技术要求 | D40: 樘 | E40: 21 | F40: 1064.4404 | G40: 22353.248 | H40: 21 | J40: 21763.35 | L40: 1064.4404 | M40: =+L40*K40 -> 0 | P40: =+O40*N40 -> 0 | R40: 1064.4404 | S40: =+R40*Q40 -> 0 | V40: =+U40*T40 -> 0 | Z40: 1064.4404 | AA40: 0 | AD40: 0
A41: 1.2.2 | B41: 钢质防火门 | C41: (1)乙级钢质防火门，FM乙1220_x000D_ (2)尺寸：1200x2000_x000D_ (3)含控制箱、闭门器、顺序器等全部不锈钢五金配件安装_x000D_ (4)前室、合用前室以及楼梯间的防火门须带视口_x000D_ (5)满足设计图纸、相关规范、招标文件及技术要求 | D41: 樘 | E41: 1 | F41: 1105.9071 | G41: 1105.9071 | H41: 1 | J41: 1128 | L41: 1105.9071 | M41: =+L41*K41 -> 0 | P41: =+O41*N41 -> 0 | R41: 1105.9071 | S41: =+R41*Q41 -> 0 | V41: =+U41*T41 -> 0 | Z41: 1105.9071 | AA41: 0 | AD41: 0
A42: 1.2.3 | B42: 钢质防火门 | C42: (1)乙级钢质防火门，FM乙1221_x000D_ (2)尺寸：1200x2100_x000D_ (3)含控制箱、闭门器、顺序器等全部不锈钢五金配件安装_x000D_ (4)前室、合用前室以及楼梯间的防火门须带视口_x000D_ (5)满足设计图纸、相关规范、招标文件及技术要求 | D42: 樘 | E42: 2 | F42: 1161.2025 | G42: 2322.405 | H42: 2 | J42: 2368.8 | L42: 1161.2025 | M42: =+L42*K42 -> 0 | P42: =+O42*N42 -> 0 | R42: 1161.2025 | S42: =+R42*Q42 -> 0 | V42: =+U42*T42 -> 0 | Z42: 1161.2025 | AA42: 0 | AD42: 0
A43: 1.2.4 | B43: 钢质防火门 | C43: (1)乙级钢质防火门，FM乙1521(无障碍、常开)_x000D_ (2)尺寸：1500x2100_x000D_ (3)含控制箱、闭门器、顺序器等全部不锈钢五金配件安装_x000D_ (4)前室、合用前室以及楼梯间的防火门须带视口_x000D_ (5)满足设计图纸、相关规范、招标文件及技术要求 | D43: 樘 | E43: 6 | F43: 1451.5079 | G43: 8709.0472 | H43: 6 | J43: 8883 | L43: 1451.5079 | M43: =+L43*K43 -> 0 | P43: =+O43*N43 -> 0 | R43: 1451.5079 | S43: =+R43*Q43 -> 0 | V43: =+U43*T43 -> 0 | Z43: 1451.5079 | AA43: 0 | AD43: 0
A44: 1.3 | B44: 丙级防火门 | F44: 0 | J44: 0 | M44: =SUM(M45:M46) -> 0 | P44: =SUM(P45:P46) -> 0 | S44: =SUM(S45:S46) -> 0 | V44: =SUM(V45:V46) -> 0 | AA44: 0 | AD44: 0
A45: 1.3.1 | B45: 钢质防火门 | C45: (1)丙级钢质防火门，FM丙0619_x000D_ (2)尺寸：600x1900_x000D_ (3)含控制箱、闭门器、顺序器等全部不锈钢五金配件安装_x000D_ (4)满足设计图纸、相关规范、招标文件及技术要求 | D45: 樘 | E45: 9 | F45: 506.62118 | G45: 4559.5906 | H45: 9 | J45: 4822.2 | L45: 506.62118 | M45: =+L45*K45 -> 0 | P45: =+O45*N45 -> 0 | R45: 506.62118 | S45: =+R45*Q45 -> 0 | V45: =+U45*T45 -> 0 | Z45: 506.62118 | AA45: 0 | AD45: 0
A46: 1.3.2 | B46: 钢质防火门 | C46: (1)丙级钢质防火门，FM丙1219_x000D_ (2)尺寸：1200x1900_x000D_ (3)含控制箱、闭门器、顺序器等全部不锈钢五金配件安装_x000D_ (4)满足设计图纸、相关规范、招标文件及技术要求 | D46: 樘 | E46: 3 | F46: 1013.2424 | G46: 3039.7271 | H46: 3 | J46: 3214.8 | L46: 1013.2424 | M46: =+L46*K46 -> 0 | P46: =+O46*N46 -> 0 | R46: 1013.2424 | S46: =+R46*Q46 -> 0 | V46: =+U46*T46 -> 0 | Z46: 1013.2424 | AA46: 0 | AD46: 0
A47: 1.4 | B47: 甲级防火窗 | F47: 0 | J47: 0 | M47: =SUM(M48:M49) -> 0 | P47: =SUM(P48:P49) -> 0 | S47: =SUM(S48:S49) -> 0 | V47: =SUM(V48:V49) -> 0 | AA47: 0 | AD47: 0
A48: 1.4.1 | B48: 金属防火窗 | C48: (1)甲级防火窗，FC甲1015_x000D_ (2)尺寸：1000x1500_x000D_ (3)防火玻璃，含全部不锈钢五金配件安装_x000D_ (4)满足设计图纸、相关规范、招标文件及技术要求 | D48: 樘 | E48: 1 | F48: 665.04286 | G48: 665.04286 | H48: 1 | J48: 1290 | L48: 665.04286 | M48: =+L48*K48 -> 0 | P48: =+O48*N48 -> 0 | R48: 665.04286 | S48: =+R48*Q48 -> 0 | V48: =+U48*T48 -> 0 | Z48: 665.04286 | AA48: 0 | AD48: 0
A49: 1.4.2 | B49: 金属防火窗 | C49: (1)甲级防火窗，FC甲1515_x000D_ (2)尺寸：1500x1500_x000D_ (3)防火玻璃，含全部不锈钢五金配件安装_x000D_ (4)满足设计图纸、相关规范、招标文件及技术要求 | D49: 樘 | E49: 1 | F49: 997.5548 | G49: 997.5548 | H49: 1 | J49: 1935 | L49: 997.5548 | M49: =+L49*K49 -> 0 | P49: =+O49*N49 -> 0 | R49: 997.5548 | S49: =+R49*Q49 -> 0 | V49: =+U49*T49 -> 0 | Z49: 997.5548 | AA49: 0 | AD49: 0
A50: 1.5 | B50: 特级防火卷帘 | F50: 0 | J50: 0 | M50: =SUM(M51:M57) -> 0 | P50: =SUM(P51:P57) -> 0 | S50: =SUM(S51:S57) -> 0 | V50: =SUM(V51:V57) -> 0 | AA50: 0 | AD50: 0
A51: 1.5.1 | B51: 防火卷帘(闸)门 | C51: (1)特级防火卷帘 TFJM4525(侧装)_x000D_ (2)尺寸:4500*2500mm_x000D_ (3)含所有五金、卷帘箱、按钮盒及控制箱等所有配件_x000D_ (4)包括门洞封堵及收边收口_x000D_ (5)满足设计图纸、相关规范、招标文件及技术要求 | D51: 樘 | E51: 2 | F51: 8245.638 | G51: 16491.276 | H51: 2 | J51: 7425 | L51: 8245.638 | M51: =+L51*K51 -> 0 | P51: =+O51*N51 -> 0 | R51: 8245.638 | S51: =+R51*Q51 -> 0 | V51: =+U51*T51 -> 0 | Z51: 8245.638 | AA51: 0 | AD51: 0
A52: 1.5.2 | B52: 防火卷帘(闸)门 | C52: (1)特级防火卷帘 TFJM5025(侧装)_x000D_ (2)尺寸:5000*2500mm_x000D_ (3)含所有五金、卷帘箱、按钮盒及控制箱等所有配件_x000D_ (4)包括门洞封堵及收边收口_x000D_ (5)满足设计图纸、相关规范、招标文件及技术要求 | D52: 樘 | E52: 7 | F52: 9001.3633 | G52: 63009.543 | H52: 7 | J52: 28875 | L52: 9001.3633 | M52: =+L52*K52 -> 0 | P52: =+O52*N52 -> 0 | R52: 9001.3633 | S52: =+R52*Q52 -> 0 | V52: =+U52*T52 -> 0 | Z52: 9001.3633 | AA52: 0 | AD52: 0
A53: 1.5.3 | B53: 入户大堂门联窗 | F53: 0 | J53: 0 | L53: 0 | M53: =+L53*K53 -> 0 | P53: =+O53*N53 -> 0 | R53: 0 | S53: =+R53*Q53 -> 0 | V53: =+U53*T53 -> 0 | Z53: 0 | AA53: 0 | AD53: 0
A54: 1.5.4 | B54: 入户大堂门联窗 | C54: (1)门联窗MLC4627，6+9A+6中空钢化玻璃_x000D_ (2)尺寸:4600*2700mm_x000D_ (3)含全部五金配件_x000D_ (4)采用55系列铝合金型材窗,90系列铝合金型材门_x000D_ (5)铝合金表面做法：可见部分氟碳喷涂，不可见部分采用阳极氧化处理_x000D_ (6)工程量计算规则:设计图示洞口尺寸面积计算_x000D_ (7)满足设计图纸、相关规范、招标文件及技术要求 | D54: 樘 | E54: 1 | F54: 4260.1706 | G54: 4260.1706 | H54: 1 | J54: 4491.66 | L54: 4260.1706 | M54: =+L54*K54 -> 0 | P54: =+O54*N54 -> 0 | R54: 4260.1706 | S54: =+R54*Q54 -> 0 | V54: =+U54*T54 -> 0 | Z54: 4260.1706 | AA54: 0 | AD54: 0
A55: 1.5.5 | B55: 入户大堂门联窗 | C55: (1)门联窗MLC4727，6+9A+6中空钢化玻璃_x000D_ (2)尺寸:4700*2700mm_x000D_ (3)含全部五金配件_x000D_ (4)采用55系列铝合金型材窗,90系列铝合金型材门_x000D_ (5)铝合金表面做法：可见部分氟碳喷涂，不可见部分采用阳极氧化处理_x000D_ (6)工程量计算规则:设计图示洞口尺寸面积计算_x000D_ (7)满足设计图纸、相关规范、招标文件及技术要求 | D55: 樘 | E55: 1 | F55: 4352.7784 | G55: 4352.7784 | H55: 1 | J55: 4589.3 | L55: 4352.7784 | M55: =+L55*K55 -> 0 | P55: =+O55*N55 -> 0 | R55: 4352.7784 | S55: =+R55*Q55 -> 0 | V55: =+U55*T55 -> 0 | Z55: 4352.7784 | AA55: 0 | AD55: 0
A56: 1.5.6 | B56: 百叶窗 | F56: 0 | J56: 0 | L56: 0 | M56: =+L56*K56 -> 0 | P56: =+O56*N56 -> 0 | R56: 0 | S56: =+R56*Q56 -> 0 | V56: =+U56*T56 -> 0 | Z56: 0 | AA56: 0 | AD56: 0
A57: 1.5.7 | B57: 铝合金防雨百叶 | C57: (1)铝合金防雨百叶_x000D_ (2)铝合金表面做法：可见部分氟碳喷涂，不可见部分采用阳极氧化处理_x000D_ (3)工程量计算规则:设计图示洞口尺寸面积计算_x000D_ (4)满足设计图纸、相关规范、招标文件及技术要求 | D57: m2 | E57: 11.93 | F57: 266.85938 | G57: 3183.6324 | H57: 11.93 | J57: 3356.6248 | L57: 266.85938 | M57: =+L57*K57 -> 0 | P57: =+O57*N57 -> 0 | R57: 266.85938 | S57: =+R57*Q57 -> 0 | V57: =+U57*T57 -> 0 | Z57: 266.85938 | AA57: 0 | AD57: 0
A58: 1.6 | B58: 管理费 | D58: 项 | E58: 1 | F58: -3460.9203 | G58: -3460.9203 | H58: 1 | J58: 0 | K58: 1 | L58: -3460.9203 | M58: =+L58*K58 -> -3460.9203 | P58: =+O58*N58 -> 0 | Q58: 1 | R58: -3460.9203 | S58: =+R58*Q58 -> -3460.9203 | V58: =+U58*T58 -> 0 | Z58: -3460.9203 | AA58: 0 | AD58: 0
A59: 1.7 | B59: 利润 | D59: 项 | E59: 1 | F59: -9596.7795 | G59: -9596.7795 | H59: 1 | J59: 0 | K59: 1 | L59: -9596.7795 | M59: =+L59*K59 -> -9596.7795 | P59: =+O59*N59 -> 0 | Q59: 1 | R59: -9596.7795 | S59: =+R59*Q59 -> -9596.7795 | V59: =+U59*T59 -> 0 | Z59: -9596.7795 | AA59: 0 | AD59: 0
A60: 2 | B60: 裙楼（一层） | F60: 0 | J60: 0 | L60: 0 | M60: =+L60*K60 -> 0 | P60: =+O60*N60 -> 0 | R60: 0 | S60: =+R60*Q60 -> 0 | V60: =+U60*T60 -> 0 | Z60: 0 | AA60: 0 | AD60: 0
A61: 2.1 | B61: 甲级防火门 | F61: 0 | J61: 0 | L61: 0 | M61: =+L61*K61 -> 0 | P61: =+O61*N61 -> 0 | R61: 0 | S61: =+R61*Q61 -> 0 | V61: =+U61*T61 -> 0 | Z61: 0 | AA61: 0 | AD61: 0
A62: 2.1.1 | B62: 钢质防火门 | C62: (1)甲级钢质防火门，FM甲1221_x000D_ (2)尺寸:1200x2100_x000D_ (3)含控制箱、闭门器、顺序器等全部不锈钢五金配件安装_x000D_ (4)前室、合用前室以及楼梯间的防火门须带视口_x000D_ (5)满足设计图纸、相关规范、招标文件及技术要求_x000D_ (6)建筑物超高增加费 | D62: 樘 | E62: 1 | F62: 1215.2174 | G62: 1215.2174 | H62: 1 | J62: 1184.4 | L62: 1215.2174 | M62: =+L62*K62 -> 0 | P62: =+O62*N62 -> 0 | R62: 1215.2174 | S62: =+R62*Q62 -> 0 | V62: =+U62*T62 -> 0 | Z62: 1215.2174 | AA62: 0 | AD62: 0
A63: 2.1.2 | B63: 钢质防火门 | C63: (1)甲级钢质防火门，FM甲0615_x000D_ (2)尺寸:600x1500_x000D_ (3)含控制箱、闭门器、顺序器等全部不锈钢五金配件安装_x000D_ (4)前室、合用前室以及楼梯间的防火门须带视口_x000D_ (5)满足设计图纸、相关规范、招标文件及技术要求_x000D_ (6)建筑物超高增加费 | D63: 樘 | E63: 1 | F63: 434.0069 | G63: 434.0069 | H63: 1 | J63: 423 | L63: 434.0069 | M63: =+L63*K63 -> 0 | P63: =+O63*N63 -> 0 | R63: 434.0069 | S63: =+R63*Q63 -> 0 | V63: =+U63*T63 -> 0 | Z63: 434.0069 | AA63: 0 | AD63: 0
A64: 2.2 | B64: 乙级防火门 | F64: 0 | G64: 0 | J64: 0 | L64: 0 | M64: =+L64*K64 -> 0 | P64: =+O64*N64 -> 0 | R64: 0 | S64: =+R64*Q64 -> 0 | V64: =+U64*T64 -> 0 | Z64: 0 | AA64: 0 | AD64: 0
A65: 2.2.1 | B65: 钢质防火门 | C65: (1)乙级钢质防火门，FM乙1121_x000D_ (2)尺寸:1100x2100_x000D_ (3)含控制箱、闭门器、顺序器等全部不锈钢五金配件安装_x000D_ (4)前室、合用前室以及楼梯间的防火门须带视口_x000D_ (5)满足设计图纸、相关规范、招标文件及技术要求_x000D_ (6)建筑物超高增加费 | D65: 樘 | E65: 8 | F65: 1076.097 | G65: 8608.7757 | H65: 8 | J65: 8685.6 | L65: 1076.097 | M65: =+L65*K65 -> 0 | P65: =+O65*N65 -> 0 | R65: 1076.097 | S65: =+R65*Q65 -> 0 | V65: =+U65*T65 -> 0 | Z65: 1076.097 | AA65: 0 | AD65: 0
A66: 2.2.2 | B66: 钢质防火门 | C66: (1)乙级钢质防火门，FM乙12a21_x000D_ (2)尺寸:1250x2100_x000D_ (3)含控制箱、闭门器、顺序器等全部不锈钢五金配件安装_x000D_ (4)前室、合用前室以及楼梯间的防火门须带视口_x000D_ (5)满足设计图纸、相关规范、招标文件及技术要求_x000D_ (6)建筑物超高增加费 | D66: 樘 | E66: 1 | F66: 1225.1763 | G66: 1225.1763 | H66: 1 | J66: 1233.75 | L66: 1225.1763 | M66: =+L66*K66 -> 0 | P66: =+O66*N66 -> 0 | R66: 1225.1763 | S66: =+R66*Q66 -> 0 | V66: =+U66*T66 -> 0 | Z66: 1225.1763 | AA66: 0 | AD66: 0
A67: 2.2.3 | B67: 钢质防火门 | C67: (1)乙级钢质防火门，FM乙0619_x000D_ (2)尺寸:600x1900_x000D_ (3)含控制箱、闭门器、顺序器等全部不锈钢五金配件安装_x000D_ (4)前室、合用前室以及楼梯间的防火门须带视口_x000D_ (5)满足设计图纸、相关规范、招标文件及技术要求_x000D_ (6)建筑物超高增加费 | D67: 樘 | E67: 3 | F67: 531.06306 | G67: 1593.1892 | H67: 3 | J67: 1607.4 | L67: 531.06306 | M67: =+L67*K67 -> 0 | P67: =+O67*N67 -> 0 | R67: 531.06306 | S67: =+R67*Q67 -> 0 | V67: =+U67*T67 -> 0 | Z67: 531.06306 | AA67: 0 | AD67: 0
A68: 2.2.4 | B68: 钢质防火门 | C68: (1)乙级钢质防火门，FM乙10a21_x000D_ (2)尺寸:1000x2100_x000D_ (3)含控制箱、闭门器、顺序器等全部不锈钢五金配件安装_x000D_ (4)前室、合用前室以及楼梯间的防火门须带视口_x000D_ (5)满足设计图纸、相关规范、招标文件及技术要求_x000D_ (6)建筑物超高增加费 | D68: 樘 | E68: 3 | F68: 978.25359 | G68: 2934.7608 | H68: 3 | J68: 2961 | L68: 978.25359 | M68: =+L68*K68 -> 0 | P68: =+O68*N68 -> 0 | R68: 978.25359 | S68: =+R68*Q68 -> 0 | V68: =+U68*T68 -> 0 | Z68: 978.25359 | AA68: 0 | AD68: 0
A69: 2.2.5 | B69: 钢质防火门 | C69: (1)乙级钢质防火门，FM乙1219_x000D_ (2)尺寸:1200x1900_x000D_ (3)含控制箱、闭门器、顺序器等全部不锈钢五金配件安装_x000D_ (4)前室、合用前室以及楼梯间的防火门须带视口_x000D_ (5)满足设计图纸、相关规范、招标文件及技术要求_x000D_ (6)建筑物超高增加费 | D69: 樘 | E69: 1 | F69: 1062.1261 | G69: 1062.1261 | H69: 1 | J69: 1071.6 | L69: 1062.1261 | M69: =+L69*K69 -> 0 | P69: =+O69*N69 -> 0 | R69: 1062.1261 | S69: =+R69*Q69 -> 0 | V69: =+U69*T69 -> 0 | Z69: 1062.1261 | AA69: 0 | AD69: 0
A70: 2.2.6 | B70: 钢质防火门 | C70: (1)乙级钢质防火门，FM乙1322_x000D_ (2)尺寸:1300x2200_x000D_ (3)含控制箱、闭门器、顺序器等全部不锈钢五金配件安装_x000D_ (4)前室、合用前室以及楼梯间的防火门须带视口_x000D_ (5)满足设计图纸、相关规范、招标文件及技术要求_x000D_ (6)建筑物超高增加费 | D70: 樘 | E70: 4 | F70: 1844.7309 | G70: 7378.9235 | H70: 4 | J70: 5376.8 | L70: 1844.7309 | M70: =+L70*K70 -> 0 | P70: =+O70*N70 -> 0 | R70: 1844.7309 | S70: =+R70*Q70 -> 0 | V70: =+U70*T70 -> 0 | Z70: 1844.7309 | AA70: 0 | AD70: 0
A71: 2.3 | B71: 丙级防火门 | F71: 0 | G71: 0 | J71: 0 | L71: 0 | M71: =+L71*K71 -> 0 | P71: =+O71*N71 -> 0 | R71: 0 | S71: =+R71*Q71 -> 0 | V71: =+U71*T71 -> 0 | Z71: 0 | AA71: 0 | AD71: 0
A72: 2.3.1 | B72: 钢质防火门 | C72: (1)丙级钢质防火门，FM丙0619_x000D_ (2)尺寸：600x1900_x000D_ (3)含控制箱、闭门器、顺序器等全部不锈钢五金配件安装_x000D_ (4)满足设计图纸、相关规范、招标文件及技术要求_x000D_ (5)建筑物超高增加费 | D72: 樘 | E72: 2 | F72: 512.37835 | G72: 1024.7567 | H72: 2 | J72: 1071.6 | L72: 512.37835 | M72: =+L72*K72 -> 0 | P72: =+O72*N72 -> 0 | R72: 512.37835 | S72: =+R72*Q72 -> 0 | V72: =+U72*T72 -> 0 | Z72: 512.37835 | AA72: 0 | AD72: 0
A73: 2.4 | B73: 普通木门带套 | F73: 0 | G73: 0 | J73: 0 | L73: 0 | M73: =+L73*K73 -> 0 | P73: =+O73*N73 -> 0 | R73: 0 | S73: =+R73*Q73 -> 0 | V73: =+U73*T73 -> 0 | Z73: 0 | AA73: 0 | AD73: 0
A74: 2.4.1 | B74: 普通木门带套 | C74: (1)普通木门 M0921_x000D_ (2)尺寸：900x2100_x000D_ (3)门框、扇材质:成品单开普通门（含全部五金配件及安装）_x000D_ (4)满足设计图纸、相关规范、招标文件及其技术要求_x000D_ (5)建筑物超高增加费 | D74: 樘 | E74: 1 | F74: 1191.5059 | G74: 1191.5059 | H74: 1 | J74: 1120 | L74: 1191.5059 | M74: =+L74*K74 -> 0 | P74: =+O74*N74 -> 0 | R74: 1191.5059 | S74: =+R74*Q74 -> 0 | V74: =+U74*T74 -> 0 | Z74: 1191.5059 | AA74: 0 | AD74: 0
A75: 2.4.2 | B75: 普通木门带套 | C75: (1)普通木门 LM0930，上部为窗，具体详大样_x000D_ (2)尺寸：900x3100_x000D_ (3)门框、扇材质:成品单开普通门（含全部五金配件及安装）_x000D_ (4)满足设计图纸、相关规范、招标文件及其技术要求_x000D_ (5)建筑物超高增加费 | D75: 樘 | E75: 1 | F75: 1697.2545 | G75: 1697.2545 | H75: 1 | J75: 1620 | L75: 1697.2545 | M75: =+L75*K75 -> 0 | P75: =+O75*N75 -> 0 | R75: 1697.2545 | S75: =+R75*Q75 -> 0 | V75: =+U75*T75 -> 0 | Z75: 1697.2545 | AA75: 0 | AD75: 0
A76: 2.4.3 | B76: 普通木门带套 | C76: (1)普通木门 LM1130 无障碍门，上部为窗，具体详大样_x000D_ (2)尺寸：1100x3100_x000D_ (3)门框、扇材质:成品单开普通门（含全部五金配件及安装）_x000D_ (4)满足设计图纸、相关规范、招标文件及其技术要求_x000D_ (5)建筑物超高增加费 | D76: 樘 | E76: 1 | F76: 2045.6626 | G76: 2045.6626 | H76: 1 | J76: 2000 | L76: 2045.6626 | M76: =+L76*K76 -> 0 | P76: =+O76*N76 -> 0 | R76: 2045.6626 | S76: =+R76*Q76 -> 0 | V76: =+U76*T76 -> 0 | Z76: 2045.6626 | AA76: 0 | AD76: 0
A77: 2.4.4 | B77: 普通木门带套 | C77: (1)普通木门 M0821_x000D_ (2)尺寸：800x2100_x000D_ (3)门框、扇材质:成品单开普通门（含全部五金配件及安装）_x000D_ (4)满足设计图纸、相关规范、招标文件及其技术要求_x000D_ (5)建筑物超高增加费 | D77: 樘 | E77: 1 | F77: 1073.5266 | G77: 1073.5266 | H77: 1 | J77: 1100 | L77: 1073.5266 | M77: =+L77*K77 -> 0 | P77: =+O77*N77 -> 0 | R77: 1073.5266 | S77: =+R77*Q77 -> 0 | V77: =+U77*T77 -> 0 | Z77: 1073.5266 | AA77: 0 | AD77: 0
A78: 2.4.5 | B78: 普通木门带套 | C78: (1)普通木门 M1221 无障碍门_x000D_ (2)尺寸：1200x2100_x000D_ (3)门框、扇材质:成品双开普通门（含全部五金配件及安装）_x000D_ (4)满足设计图纸、相关规范、招标文件及其技术要求_x000D_ (5)建筑物超高增加费 | D78: 樘 | E78: 1 | F78: 1647.5076 | G78: 1647.5076 | H78: 1 | J78: 1500 | L78: 1647.5076 | M78: =+L78*K78 -> 0 | P78: =+O78*N78 -> 0 | R78: 1647.5076 | S78: =+R78*Q78 -> 0 | V78: =+U78*T78 -> 0 | Z78: 1647.5076 | AA78: 0 | AD78: 0
A79: 2.4.6 | B79: 普通木门带套 | C79: (1)普通木门 LM1521_x000D_ (2)尺寸：1500x2100_x000D_ (3)门框、扇材质:成品双开普通门（含全部五金配件及安装）_x000D_ (4)满足设计图纸、相关规范、招标文件及其技术要求_x000D_ (5)建筑物超高增加费 | D79: 樘 | E79: 2 | F79: 2001.5212 | G79: 4003.0424 | H79: 2 | J79: 3700 | L79: 2001.5212 | M79: =+L79*K79 -> 0 | P79: =+O79*N79 -> 0 | R79: 2001.5212 | S79: =+R79*Q79 -> 0 | V79: =+U79*T79 -> 0 | Z79: 2001.5212 | AA79: 0 | AD79: 0
A80: 2.4.7 | B80: 普通木门带套 | C80: (1)普通木门 M10a21_x000D_ (2)尺寸：1050x2100_x000D_ (3)门框、扇材质:成品单开普通门（含全部五金配件及安装）_x000D_ (4)满足设计图纸、相关规范、招标文件及其技术要求_x000D_ (5)建筑物超高增加费 | D80: 樘 | E80: 1 | F80: 1368.5459 | G80: 1368.5459 | H80: 1 | J80: 2210 | L80: 1368.5459 | M80: =+L80*K80 -> 0 | P80: =+O80*N80 -> 0 | R80: 1368.5459 | S80: =+R80*Q80 -> 0 | V80: =+U80*T80 -> 0 | Z80: 1368.5459 | AA80: 0 | AD80: 0
A81: 2.5 | B81: 卷帘门 | F81: 0 | G81: 0 | J81: 0 | L81: 0 | M81: =+L81*K81 -> 0 | P81: =+O81*N81 -> 0 | R81: 0 | S81: =+R81*Q81 -> 0 | V81: =+U81*T81 -> 0 | Z81: 0 | AA81: 0 | AD81: 0
A82: 2.5.1 | B82: 金属卷帘(闸)门 | C82: (1)卷帘门 JLM2255_x000D_ (2)尺寸:2200*5500mm_x000D_ (3)含所有五金、卷帘箱、按钮盒及控制箱等所有配件_x000D_ (4)包括门洞封堵及收边收口_x000D_ (5)满足设计图纸、相关规范、招标文件及技术要求_x000D_ (6)建筑物超高增加费 | D82: 樘 | E82: 1 | F82: 5609.2919 | G82: 5609.2919 | H82: 1 | J82: 10000 | L82: 5609.2919 | M82: =+L82*K82 -> 0 | P82: =+O82*N82 -> 0 | R82: 5609.2919 | S82: =+R82*Q82 -> 0 | V82: =+U82*T82 -> 0 | Z82: 5609.2919 | AA82: 0 | AD82: 0
A83: 2.5.2 | B83: 金属卷帘(闸)门 | C83: (1)卷帘门 JLM4455_x000D_ (2)尺寸:4500*5500mm_x000D_ (3)含所有五金、卷帘箱、按钮盒及控制箱等所有配件_x000D_ (4)包括门洞封堵及收边收口_x000D_ (5)满足设计图纸、相关规范、招标文件及技术要求_x000D_ (6)建筑物超高增加费 | D83: 樘 | E83: 1 | F83: 9948.9531 | G83: 9948.9531 | H83: 1 | J83: 12000 | L83: 9948.9531 | M83: =+L83*K83 -> 0 | P83: =+O83*N83 -> 0 | R83: 9948.9531 | S83: =+R83*Q83 -> 0 | V83: =+U83*T83 -> 0 | Z83: 9948.9531 | AA83: 0 | AD83: 0
A84: 2.5.3 | B84: 金属卷帘(闸)门 | C84: (1)卷帘门 JLM4055_x000D_ (2)尺寸:4000*5500mm_x000D_ (3)含所有五金、卷帘箱、按钮盒及控制箱等所有配件_x000D_ (4)包括门洞封堵及收边收口_x000D_ (5)满足设计图纸、相关规范、招标文件及技术要求_x000D_ (6)建筑物超高增加费 | D84: 樘 | E84: 1 | F84: 9005.546 | G84: 9005.546 | H84: 1 | J84: 13500 | L84: 9005.546 | M84: =+L84*K84 -> 0 | P84: =+O84*N84 -> 0 | R84: 9005.546 | S84: =+R84*Q84 -> 0 | V84: =+U84*T84 -> 0 | Z84: 9005.546 | AA84: 0 | AD84: 0
A85: 2.6 | B85: 断热铝合金窗 | F85: 0 | G85: 0 | J85: 0 | L85: 0 | M85: =+L85*K85 -> 0 | P85: =+O85*N85 -> 0 | R85: 0 | S85: =+R85*Q85 -> 0 | V85: =+U85*T85 -> 0 | Z85: 0 | AA85: 0 | AD85: 0
A86: 2.6.1 | B86: 断热铝合金窗 | C86: (1)铝合金窗，断热铝合金窗+较低透光Low-E中空玻璃(6+12A+6)_x000D_ (2)含全部五金配件安装_x000D_ (3)55系列铝合金型材窗_x000D_ (4)铝合金表面做法：可见部分氟碳喷涂，不可见部分采用阳极氧化处理_x000D_ (5)含完成门窗所有工序的费用(如防水密封胶、胶条、收边收口等)_x000D_ (6)工程量计算规则:设计图示洞口尺寸面积计算_x000D_ (7)满足设计图纸、相关规范、招标文件及技术要求_x000D_ (8)建筑物超高增加费 | D86: m2 | E86: 31.35 | F86: 771.669 | G86: 24191.823 | H86: 31.35 | J86: 25506.36 | L86: 771.669 | M86: =+L86*K86 -> 0 | P86: =+O86*N86 -> 0 | R86: 771.669 | S86: =+R86*Q86 -> 0 | V86: =+U86*T86 -> 0 | Z86: 771.669 | AA86: 0 | AD86: 0
A87: 2.6.2 | B87: 断热铝合金固定窗 | C87: (1)铝合金固定窗，断热铝合金窗+较低透光Low-E中空玻璃(6+12A+6)_x000D_ (2)55系列铝合金型材窗_x000D_ (3)铝合金表面做法:可见部分氟碳喷涂，不可见部分采用阳极氧化处理_x000D_ (4)含完成门窗所有工序的费用(如防水密封胶、胶条、收边收口等)_x000D_ (5)工程量计算规则:设计图示洞口尺寸面积计算_x000D_ (6)满足设计图纸、相关规范、招标文件及技术要求_x000D_ (7)建筑物超高增加费 | D87: m2 | E87: 1.5 | F87: 705.31457 | G87: 1057.9719 | H87: 1.5 | J87: 1115.46 | L87: 705.31457 | M87: =+L87*K87 -> 0 | P87: =+O87*N87 -> 0 | R87: 705.31457 | S87: =+R87*Q87 -> 0 | V87: =+U87*T87 -> 0 | Z87: 705.31457 | AA87: 0 | AD87: 0
A88: 2.7 | B88: 门联窗 | F88: 0 | G88: 0 | J88: 0 | L88: 0 | M88: =+L88*K88 -> 0 | P88: =+O88*N88 -> 0 | R88: 0 | S88: =+R88*Q88 -> 0 | V88: =+U88*T88 -> 0 | Z88: 0 | AA88: 0 | AD88: 0
A89: 2.7.1 | B89: 门联窗 | C89: (1)门联窗LMC6439，6+12A+6中空钢化玻璃_x000D_ (2)尺寸:6400*3900mm_x000D_ (3)含全部五金配件_x000D_ (4)采用55系列铝合金型材窗,90系列铝合金型材门_x000D_ (5)铝合金表面做法:可见部分氟碳喷涂，不可见部分采用阳极氧化处理_x000D_ (6)工程量计算规则:设计图示洞口尺寸面积计算_x000D_ (7)满足设计图纸、相关规范、招标文件及技术要求_x000D_ (8)建筑物超高增加费 | D89: 樘 | E89: 1 | F89: 9534.3233 | G89: 9534.3233 | H89: 1 | J89: 10052.4 | L89: 9534.3233 | M89: =+L89*K89 -> 0 | P89: =+O89*N89 -> 0 | R89: 9534.3233 | S89: =+R89*Q89 -> 0 | V89: =+U89*T89 -> 0 | Z89: 9534.3233 | AA89: 0 | AD89: 0
A90: 2.7.2 | B90: 门联窗 | C90: (1)门联窗LMC5239，6+12A+6中空钢化玻璃_x000D_ (2)尺寸:5200*3900mm_x000D_ (3)含全部五金配件_x000D_ (4)采用55系列铝合金型材窗,90系列铝合金型材门_x000D_ (5)铝合金表面做法:可见部分氟碳喷涂，不可见部分采用阳极氧化处理_x000D_ (6)工程量计算规则:设计图示洞口尺寸面积计算_x000D_ (7)满足设计图纸、相关规范、招标文件及技术要求_x000D_ (8)建筑物超高增加费 | D90: 樘 | E90: 1 | F90: 7746.6234 | G90: 7746.6234 | H90: 1 | J90: 8167.56 | L90: 7746.6234 | M90: =+L90*K90 -> 0 | P90: =+O90*N90 -> 0 | R90: 7746.6234 | S90: =+R90*Q90 -> 0 | V90: =+U90*T90 -> 0 | Z90: 7746.6234 | AA90: 0 | AD90: 0
A91: 2.8 | B91: 百叶窗 | F91: 0 | G91: 0 | J91: 0 | L91: 0 | M91: =+L91*K91 -> 0 | P91: =+O91*N91 -> 0 | R91: 0 | S91: =+R91*Q91 -> 0 | V91: =+U91*T91 -> 0 | Z91: 0 | AA91: 0 | AD91: 0
A92: 2.8.1 | B92: 铝合金普通百叶 | C92: (1)铝合金普通百叶_x000D_ (2)后设防虫网_x000D_ (3)铝合金表面做法：可见部分氟碳喷涂，不可见部分采用阳极氧化处理_x000D_ (4)工程量计算规则:设计图示洞口尺寸面积计算_x000D_ (5)满足设计图纸、相关规范、招标文件及技术要求_x000D_ (6)建筑物超高增加费 | D92: m2 | E92: 18.63 | F92: 285.81914 | G92: 5324.8106 | H92: 18.63 | J92: 5614.1505 | L92: 285.81914 | M92: =+L92*K92 -> 0 | P92: =+O92*N92 -> 0 | R92: 285.81914 | S92: =+R92*Q92 -> 0 | V92: =+U92*T92 -> 0 | Z92: 285.81914 | AA92: 0 | AD92: 0
A93: 2.8.2 | B93: 铝合金防雨百叶 | C93: (1)铝合金防雨百叶_x000D_ (2)后设防虫网_x000D_ (3)铝合金表面做法：可见部分氟碳喷涂，不可见部分采用阳极氧化处理_x000D_ (4)工程量计算规则:设计图示洞口尺寸面积计算_x000D_ (5)满足设计图纸、相关规范、招标文件及技术要求_x000D_ (6)建筑物超高增加费 | D93: m2 | E93: 31.82 | F93: 285.81914 | G93: 9094.765 | H93: 31.82 | J93: 9588.957 | L93: 285.81914 | M93: =+L93*K93 -> 0 | P93: =+O93*N93 -> 0 | R93: 285.81914 | S93: =+R93*Q93 -> 0 | V93: =+U93*T93 -> 0 | Z93: 285.81914 | AA93: 0 | AD93: 0
A94: 2.9 | B94: 管理费 | D94: 项 | E94: 1 | F94: -1969.9943 | G94: -1969.9943 | H94: 1 | J94: 0 | K94: 1 | L94: -1969.9943 | M94: =+L94*K94 -> -1969.9943 | P94: =+O94*N94 -> 0 | Q94: 1 | R94: -1969.9943 | S94: =+R94*Q94 -> -1969.9943 | V94: =+U94*T94 -> 0 | Z94: -1969.9943 | AA94: 0 | AD94: 0
A95: 2.1 | B95: 利润 | D95: 项 | E95: 1 | F95: -5715.0834 | G95: -5715.0834 | H95: 1 | J95: 0 | K95: 1 | L95: -5715.0834 | M95: =+L95*K95 -> -5715.0834 | P95: =+O95*N95 -> 0 | Q95: 1 | R95: -5715.0834 | S95: =+R95*Q95 -> -5715.0834 | V95: =+U95*T95 -> 0 | Z95: -5715.0834 | AA95: 0 | AD95: 0
A96: 3 | B96: 1#塔楼 | F96: 0 | G96: 0 | J96: 0 | L96: 0 | M96: =+L96*K96 -> 0 | P96: =+O96*N96 -> 0 | R96: 0 | S96: =+R96*Q96 -> 0 | V96: =+U96*T96 -> 0 | Z96: 0 | AA96: 0 | AD96: 0
A97: 3.1 | B97: 甲级防火门 | F97: 0 | G97: 0 | J97: 0 | L97: 0 | M97: =+L97*K97 -> 0 | P97: =+O97*N97 -> 0 | R97: 0 | S97: =+R97*Q97 -> 0 | V97: =+U97*T97 -> 0 | Z97: 0 | AA97: 0 | AD97: 0
A98: 3.1.1 | B98: 钢质防火门 | C98: (1)甲级钢质防火门，FM甲10a22_x000D_ (2)尺寸：1050x2200_x000D_ (3)含控制箱、闭门器、顺序器等全部不锈钢五金配件安装_x000D_ (4)楼梯间门、防火门均带视口_x000D_ (5)满足设计图纸、相关规范、招标文件及技术要求_x000D_ (6)建筑物超高增加费 | D98: 樘 | E98: 3 | F98: 1113.9501 | G98: 3341.8503 | H98: 3 | J98: 3257.1 | L98: 1113.9501 | M98: =+L98*K98 -> 0 | P98: =+O98*N98 -> 0 | R98: 1113.9501 | S98: =+R98*Q98 -> 0 | V98: =+U98*T98 -> 0 | Z98: 1113.9501 | AA98: 0 | AD98: 0
A99: 3.1.2 | B99: 钢质防火门 | C99: (1)甲级钢质防火门，FM甲1218_x000D_ (2)尺寸：1200x1800_x000D_ (3)含控制箱、闭门器、顺序器等全部不锈钢五金配件安装_x000D_ (4)楼梯间门、防火门均带视口_x000D_ (5)满足设计图纸、相关规范、招标文件及技术要求_x000D_ (6)建筑物超高增加费 | D99: 樘 | E99: 1 | F99: 1041.6204 | G99: 1041.6204 | H99: 1 | J99: 1015.2 | L99: 1041.6204 | M99: =+L99*K99 -> 0 | P99: =+O99*N99 -> 0 | R99: 1041.6204 | S99: =+R99*Q99 -> 0 | V99: =+U99*T99 -> 0 | Z99: 1041.6204 | AA99: 0 | AD99: 0
A100: 3.1.3 | B100: 钢质防火门 | C100: (1)甲级钢质防火门，FM甲1221_x000D_ (2)尺寸：1200x2100_x000D_ (3)含控制箱、闭门器、顺序器等全部不锈钢五金配件安装_x000D_ (4)楼梯间门、防火门均带视口_x000D_ (5)满足设计图纸、相关规范、招标文件及技术要求_x000D_ (6)建筑物超高增加费 | D100: 樘 | E100: 2 | F100: 1215.2269 | G100: 2430.4538 | H100: 2 | J100: 2368.8 | L100: 1215.2269 | M100: =+L100*K100 -> 0 | P100: =+O100*N100 -> 0 | R100: 1215.2269 | S100: =+R100*Q100 -> 0 | V100: =+U100*T100 -> 0 | Z100: 1215.2269 | AA100: 0 | AD100: 0
...

Sheet 周转料具
A1: 工程项目周转料具费计算表
A2: 工程名称：XXX项目
A3: 序号 | B3: 周转料具名称及型号 | C3: 项目特征 | D3: 单位 | E3: 预测工程竣工数据统计 | H3: 预测工程竣工数据统计 | K3: 本期数据统计 | Q3: 累计数据统计 | W3: 备注 | Y3: 累计数据统计
E4: 预算收入 | H4: 计划成本 | K4: 预算收入 | N4: 实际成本 | Q4: 预算收入 | T4: 实际成本 | Y4: 预算收入 | AB4: 实际成本
E5: 计算式或说明 | F5: 单价 | G5: 合价 | H5: 计算式或说明 | I5: 单价 | J5: 合价 | K5: 计算式或说明 | L5: 单价 | M5: 合价 | N5: 工程量 | O5: 单价 | P5: 合价 | Q5: 计算式或说明 | R5: 单价 | S5: 合价 | T5: 工程量 | U5: 单价 | V5: 合价 | Y5: 计算式或说明 | Z5: 单价 | AA5: 合价 | AB5: 工程量 | AC5: 单价 | AD5: 合价
A6: 一 | B6: 地下室 | G6: 3825141.9 | J6: 5411990.6 | M6: =+M7+M43+M50 -> 0 | P6: =+P7+P43+P50 -> 0 | S6: =+S7+S43+S50 -> 3661413.8 | V6: =+V7+V43+V50 -> 4747068.8 | AA6: 3661413.8 | AD6: 4658529.8
A7: 1 | B7: 模板工程 | G7: 3241531.1 | J7: 5164180.8 | M7: =SUM(M8:M41) -> 0 | P7: =SUM(P8:P41) -> 0 | S7: =SUM(S8:S41) -> 3552410.5 | V7: =SUM(V8:V42) -> 4535604.5 | AA7: 3552410.5 | AD7: 4447065.5
A8: 1.1 | B8: 垫层 | C8: (1)垫层_x000D_ (2)模板:木模板_x000D_ (3)满足设计图纸、相关规范、招标文件及技术要求 | D8: m2 | F8: 42.41 | G8: 7958.9424 | J8: 29235.2 | K8: =+Q8-Y8 -> 0 | L8: =+R8 -> 42.41 | M8: =+L8*K8 -> 0 | N8: =+K8 -> 0 | O8: =+U8 -> 0 | P8: =+O8*N8 -> 0 | Q8: 228.4 | R8: 42.41 | S8: =+R8*Q8 -> 9686.444 | T8: =+Q8 -> 228.4 | U8: 0 | V8: =+U8*T8 -> 0 | Y8: 228.4 | Z8: 42.41 | AA8: 9686.444 | AB8: 228.4 | AC8: 0 | AD8: 0
A9: 1.2 | B9: 基础 | C9: (1)基础（筏板、柱墩、桩承台、基础梁、集水坑）_x000D_ (2)模板:木模板_x000D_ (3)满足设计图纸、相关规范、招标文件及技术要求 | D9: m2 | F9: 54.26 | G9: 90776.64 | J9: 263061.76 | K9: =+Q9-Y9 -> 0 | L9: =+R9 -> 54.26 | M9: =+L9*K9 -> 0 | N9: =+K9 -> 0 | O9: =+U9 -> 88 | P9: =+O9*N9 -> 0 | Q9: 2055.17 | R9: 54.26 | S9: =+R9*Q9 -> 111513.52 | T9: =+Q9 -> 2055.17 | U9: 88 | V9: =+U9*T9 -> 180854.96 | Y9: 2055.17 | Z9: 54.26 | AA9: 111513.52 | AB9: 2055.17 | AC9: 88 | AD9: 180854.96
A10: 1.3 | B10: 电梯坑 | C10: (1)电梯坑_x000D_ (2)模板:木模板_x000D_ (3)满足设计图纸、相关规范、招标文件及技术要求 | D10: m2 | F10: 48.24 | G10: 7200.5291 | J10: 23142.4 | K10: =+Q10-Y10 -> 0 | L10: =+R10 -> 48.24 | M10: =+L10*K10 -> 0 | N10: =+K10 -> 0 | O10: =+U10 -> 88 | P10: =+O10*N10 -> 0 | Q10: 180.8 | R10: 48.24 | S10: =+R10*Q10 -> 8721.792 | T10: =+Q10 -> 180.8 | U10: 88 | V10: =+U10*T10 -> 15910.4 | Y10: 180.8 | Z10: 48.24 | AA10: 8721.792 | AB10: 180.8 | AC10: 88 | AD10: 15910.4
A11: 1.4 | B11: 基础梁 | C11: (1)基础梁_x000D_ (2)模板:木模板_x000D_ (3)满足设计图纸、相关规范、招标文件及技术要求 | D11: m2 | F11: 72.92 | G11: 201.17684 | J11: 437.76 | K11: =+Q11-Y11 -> 0 | L11: =+R11 -> 72.92 | M11: =+L11*K11 -> 0 | N11: =+K11 -> 0 | O11: =+U11 -> 88 | P11: =+O11*N11 -> 0 | Q11: 0 | R11: 72.92 | S11: =+R11*Q11 -> 0 | T11: =+Q11 -> 0 | U11: 88 | V11: =+U11*T11 -> 0 | Y11: 0 | Z11: 72.92 | AA11: 0 | AB11: 0 | AC11: 88 | AD11: 0
A12: 1.5 | B12: 矩形柱 | C12: (1)矩形柱_x000D_ (2)模板:木模板_x000D_ (3)支模高度≤4m_x000D_ (4)满足设计图纸、相关规范、招标文件及技术要求 | D12: m2 | F12: 74.99 | G12: 148904.11 | J12: 316263.68 | K12: =+Q12-Y12 -> 0 | L12: =+R12 -> 74.99 | M12: =+L12*K12 -> 0 | N12: =+K12 -> 0 | O12: =+U12 -> 88 | P12: =+O12*N12 -> 0 | Q12: 2470.81 | R12: 74.99 | S12: =+R12*Q12 -> 185286.04 | T12: =+Q12 -> 2470.81 | U12: 88 | V12: =+U12*T12 -> 217431.28 | Y12: 2470.81 | Z12: 74.99 | AA12: 185286.04 | AB12: 2470.81 | AC12: 88 | AD12: 217431.28
A13: 1.6 | B13: 矩形柱 | C13: (1)矩形柱_x000D_ (2)模板:木模板_x000D_ (3)4m<支模高度≤6m_x000D_ (4)满足设计图纸、相关规范、招标文件及技术要求 | D13: m2 | F13: 87.45 | G13: 159602.24 | J13: 291700.48 | K13: =+Q13-Y13 -> 0 | L13: =+R13 -> 87.45 | M13: =+L13*K13 -> 0 | N13: =+K13 -> 0 | O13: =+U13 -> 88 | P13: =+O13*N13 -> 0 | Q13: 2278.91 | R13: 87.45 | S13: =+R13*Q13 -> 199290.68 | T13: =+Q13 -> 2278.91 | U13: 88 | V13: =+U13*T13 -> 200544.08 | Y13: 2278.91 | Z13: 87.45 | AA13: 199290.68 | AB13: 2278.91 | AC13: 88 | AD13: 200544.08
A14: 1.7 | B14: 直形墙 内墙 | C14: (1)直形墙，厚度50cm内_x000D_ (2)模板:木模板_x000D_ (3)支模高度≤4m_x000D_ (4)满足设计图纸、相关规范、招标文件及技术要求 | D14: m2 | F14: 67.07 | G14: 335698.89 | J14: 787627.52 | K14: =+Q14-Y14 -> 0 | L14: =+R14 -> 67.07 | M14: =+L14*K14 -> 0 | N14: =+K14 -> 0 | O14: =+U14 -> 88 | P14: =+O14*N14 -> 0 | Q14: 6153.34 | R14: 67.07 | S14: =+R14*Q14 -> 412704.51 | T14: =+Q14 -> 6153.34 | U14: 88 | V14: =+U14*T14 -> 541493.92 | Y14: 6153.34 | Z14: 67.07 | AA14: 412704.51 | AB14: 6153.34 | AC14: 88 | AD14: 541493.92
A15: 1.8 | B15: 直形墙 内墙 | C15: (1)直形墙，厚度50cm内_x000D_ (2)模板:木模板_x000D_ (3)4m<支模高度≤6m_x000D_ (4)满足设计图纸、相关规范、招标文件及技术要求 | D15: m2 | F15: 77.91 | G15: 151517.52 | J15: 307166.72 | K15: =+Q15-Y15 -> 0 | L15: =+R15 -> 77.91 | M15: =+L15*K15 -> 0 | N15: =+K15 -> 0 | O15: =+U15 -> 88 | P15: =+O15*N15 -> 0 | Q15: 2399.74 | R15: 77.91 | S15: =+R15*Q15 -> 186963.74 | T15: =+Q15 -> 2399.74 | U15: 88 | V15: =+U15*T15 -> 211177.12 | Y15: 2399.74 | Z15: 77.91 | AA15: 186963.74 | AB15: 2399.74 | AC15: 88 | AD15: 211177.12
A16: 1.9 | B16: 直形墙 外墙 | C16: (1)直形墙，厚度50cm内_x000D_ (2)模板:木模板_x000D_ (3)支模高度≤4m_x000D_ (4)满足设计图纸、相关规范、招标文件及技术要求 | D16: m2 | F16: 65.01 | G16: 193814.19 | J16: 470859.52 | K16: =+Q16-Y16 -> 0 | L16: =+R16 -> 65.01 | M16: =+L16*K16 -> 0 | N16: =+K16 -> 0 | O16: =+U16 -> 88 | P16: =+O16*N16 -> 0 | Q16: 5530.72 | R16: 65.01 | S16: =+R16*Q16 -> 359552.11 | T16: =+Q16 -> 5530.72 | U16: 88 | V16: =+U16*T16 -> 486703.36 | Y16: 5530.72 | Z16: 65.01 | AA16: 359552.11 | AB16: 5530.72 | AC16: 88 | AD16: 486703.36
A17: 1.1 | B17: 直形墙 外墙 | C17: (1)直形墙，厚度50cm内_x000D_ (2)模板:木模板_x000D_ (3)4m<支模高度≤6m_x000D_ (4)满足设计图纸、相关规范、招标文件及技术要求 | D17: m2 | F17: 75.84 | G17: 168089.34 | J17: 351153.92 | K17: =+Q17-Y17 -> 0 | L17: =+R17 -> 75.84 | M17: =+L17*K17 -> 0 | N17: =+K17 -> 0 | O17: =+U17 -> 88 | P17: =+O17*N17 -> 0 | Q17: 2743.39 | R17: 75.84 | S17: =+R17*Q17 -> 208058.7 | T17: =+Q17 -> 2743.39 | U17: 88 | V17: =+U17*T17 -> 241418.32 | Y17: 2743.39 | Z17: 75.84 | AA17: 208058.7 | AB17: 2743.39 | AC17: 88 | AD17: 241418.32
A18: 1.11 | B18: 短肢剪力墙、电梯井壁 | C18: (1)电梯井壁_x000D_ (2)模板:木模板_x000D_ (3)支模高度≤4m_x000D_ (4)满足设计图纸、相关规范、招标文件及技术要求 | D18: m2 | F18: 78.2 | G18: 7874.2675 | J18: 16128 | K18: =+Q18-Y18 -> 0 | L18: =+R18 -> 78.2 | M18: =+L18*K18 -> 0 | N18: =+K18 -> 0 | O18: =+U18 -> 88 | P18: =+O18*N18 -> 0 | Q18: 126 | R18: 78.2 | S18: =+R18*Q18 -> 9853.2 | T18: =+Q18 -> 126 | U18: 88 | V18: =+U18*T18 -> 11088 | Y18: 126 | Z18: 78.2 | AA18: 9853.2 | AB18: 126 | AC18: 88 | AD18: 11088
A19: 1.12 | B19: 短肢剪力墙、电梯井壁 | C19: (1)电梯井壁_x000D_ (2)模板:木模板_x000D_ (3)4m<支模高度≤6m_x000D_ (4)满足设计图纸、相关规范、招标文件及技术要求 | D19: m2 | F19: 91.64 | G19: 14193.656 | J19: 24883.2 | K19: =+Q19-Y19 -> 0 | L19: =+R19 -> 91.64 | M19: =+L19*K19 -> 0 | N19: =+K19 -> 0 | O19: =+U19 -> 88 | P19: =+O19*N19 -> 0 | Q19: 194.4 | R19: 91.64 | S19: =+R19*Q19 -> 17814.816 | T19: =+Q19 -> 194.4 | U19: 88 | V19: =+U19*T19 -> 17107.2 | Y19: 194.4 | Z19: 91.64 | AA19: 17814.816 | AB19: 194.4 | AC19: 88 | AD19: 17107.2
... A36: 1.29 | B36: 门槛、反坎 | C36: (1)门槛、反坎_x000D_ (2)模板:木模板_x000D_ (3)满足设计图纸、相关规范、招标文件及技术要求 | D36: m2 | F36: 86.03 | G36: 55387.717 | J36: 0 | K36: =+Q36-Y36 -> 0 | L36: =+R36 -> 86.03 | M36: =+L36*K36 -> 0 | N36: =+K36 -> 0 | O36: =+U36 -> 88 | P36: =+O36*N36 -> 0 | Q36: 0 | R36: 86.03 | S36: =+R36*Q36 -> 0 | T36: =+Q36 -> 0 | U36: 88 | V36: =+U36*T36 -> 0 | Y36: 0 | Z36: 86.03 | AA36: 0 | AB36: 0 | AC36: 88 | AD36: 0
A37: 1.3 | B37: 梁顶架 | C37: (1)梁顶架 (2)模板:木模板 (3)梁截面高度≤1m (4)支模高度6M以内 (5)满足设计图纸、相关规范、招标文件及技术要求 | D37: m3 | F37: 15.97 | G37: 43546.102 | J37: 0 | K37: =+Q37-Y37 -> 0 | L37: =+R37 -> 15.97 | M37: =+L37*K37 -> 0 | N37: =+T37-AB37 -> 0 | O37: =+U37 -> 10 | P37: =+O37*N37 -> 0 | Q37: 0 | R37: 15.97 | S37: =+R37*Q37 -> 0 | T37: 39691.189 | U37: 10 | V37: =+U37*T37 -> 396911.89 | Y37: 0 | Z37: 15.97 | AA37: 0 | AB37: 39691.189 | AC37: 10 | AD37: 396911.89
A38: 1.31 | B38: 梁顶架 | C38: (1)梁顶架_x000D_ (2)模板:木模板_x000D_ (3)1m<梁截面高度≤1.5m_x000D_ (4)支模高度6M以内_x000D_ (5)满足设计图纸、相关规范、招标文件及技术要求 | D38: m3 | F38: 18.36 | G38: 2193.9717 | J38: 0 | K38: =+Q38-Y38 -> 0 | L38: =+R38 -> 18.36 | M38: =+L38*K38 -> 0 | N38: =+T38-AB38 -> 0 | O38: =+U38 -> 10 | P38: =+O38*N38 -> 0 | Q38: 0 | R38: 18.36 | S38: =+R38*Q38 -> 0 | T38: 0 | U38: 10 | V38: =+U38*T38 -> 0 | Y38: 0 | Z38: 18.36 | AA38: 0 | AB38: 0 | AC38: 10 | AD38: 0
A39: 1.32 | B39: 梁顶架 | C39: (1)梁顶架_x000D_ (2)模板:木模板_x000D_ (3)1.5m<梁截面高度≤2m_x000D_ (4)支模高度6M以内_x000D_ (5)满足设计图纸、相关规范、招标文件及技术要求 | D39: m3 | F39: 19.97 | G39: 56.219159 | J39: 0 | K39: =+Q39-Y39 -> 0 | L39: =+R39 -> 19.97 | M39: =+L39*K39 -> 0 | N39: =+T39-AB39 -> 0 | O39: =+U39 -> 10 | P39: =+O39*N39 -> 0 | Q39: 0 | R39: 19.97 | S39: =+R39*Q39 -> 0 | T39: 0 | U39: 10 | V39: =+U39*T39 -> 0 | Y39: 0 | Z39: 19.97 | AA39: 0 | AB39: 0 | AC39: 10 | AD39: 0
A40: 1.33 | B40: 板顶架 | C40: (1)板顶架_x000D_ (2)模板:木模板_x000D_ (3)支模高度6M以内_x000D_ (4)满足设计图纸、相关规范、招标文件及技术要求 | D40: m3 | F40: 15.97 | G40: 604783.65 | J40: 0 | K40: =+Q40-Y40 -> 0 | L40: =+R40 -> 15.97 | M40: =+L40*K40 -> 0 | N40: =+T40-AB40 -> 0 | O40: =+U40 -> 10 | P40: =+O40*N40 -> 0 | Q40: 0 | R40: 15.97 | S40: =+R40*Q40 -> 0 | T40: 0 | U40: 10 | V40: =+U40*T40 -> 0 | Y40: 0 | Z40: 15.97 | AA40: 0 | AB40: 0 | AC40: 10 | AD40: 0
A41: 1.34 | B41: 基础砖胎膜 | C41: (2)砖胎膜，120厚灰砂砖 (2)满足设计图纸、相关规范、招标文件及技术要求 | D41: m3 | F41: 680.16 | G41: 125188.73 | J41: 148941.13 | K41: =+Q41-Y41 -> 0 | L41: =+R41 -> 680.16 | M41: =+L41*K41 -> 0 | N41: =+K41 -> 0 | O41: =+U41 -> 390 | P41: =+O41*N41 -> 0 | Q41: 295.13 | R41: 680.16 | S41: =+R41*Q41 -> 200735.62 | T41: =+Q41 -> 295.13 | U41: 390 | V41: =+U41*T41 -> 115100.7 | Y41: 295.13 | Z41: 680.16 | AA41: 200735.62 | AB41: 295.13 | AC41: 390 | AD41: 115100.7
B42: 砖胎膜抹灰 | T42: =295.13/0.2*2 -> 2951.3 | U42: 30 | V42: =+U42*T42 -> 88539
A43: 2 | B43: 脚手架工程 | G43: 581448.41 | J43: 247809.75 | M43: =SUM(M44:M49) -> 0 | P43: =SUM(P44:P49) -> 0 | S43: =SUM(S44:S49) -> 109003.25 | V43: =SUM(V44:V49) -> 211464.32 | AA43: 109003.25 | AD43: 211464.32
A44: 2.1 | B44: 外脚手架 | C44: (1)搭设方式:外脚手架 双排落地式_x000D_ (2)搭设高度:搭设高度24m以内_x000D_ (3)满足设计图纸、相关规范、招标文件及技术要求 | D44: m2 | E44: 3304.13 | F44: 32.99 | G44: 87935.635 | J44: 247809.75 | K44: =+Q44-Y44 -> 0 | L44: =+R44 -> 32.99 | M44: =+L44*K44 -> 0 | N44: =+T44-AB44 -> 0 | O44: =+U44 -> 64 | P44: =+O44*N44 -> 0 | Q44: 3304.13 | R44: =+F44 -> 32.99 | S44: =+R44*Q44 -> 109003.25 | T44: =+Q44 -> 3304.13 | U44: 64 | V44: =+U44*T44 -> 211464.32 | Y44: 3304.13 | Z44: 32.99 | AA44: 109003.25 | AB44: 3304.13 | AC44: 64 | AD44: 211464.32
A45: 2.2 | B45: 里脚手架 | C45: (1)里脚手架（含有满堂脚手架部分）_x000D_ (2)搭设高度:4.2m以内_x000D_ (3)满足设计图纸、相关规范、招标文件及技术要求 | D45: m2 | E45: 10696.45 | F45: 7.35 | G45: 62291.408 | J45: 0 | K45: =+Q45-Y45 -> 0 | L45: =+R45 -> 7.35 | M45: =+L45*K45 -> 0 | N45: =+T45-AB45 -> 0 | O45: =+U45 -> 0 | P45: =+O45*N45 -> 0 | R45: =+F45 -> 7.35 | S45: =+R45*Q45 -> 0 | V45: =+U45*T45 -> 0 | Z45: 7.35 | AA45: 0 | AD45: 0
A46: 2.3 | B46: 里脚手架 | C46: (1)里脚手架（含有满堂脚手架部分）_x000D_ (2)搭设高度:4.2m-5.4m内_x000D_ (3)满足设计图纸、相关规范、招标文件及技术要求 | D46: m2 | E46: 8052.38 | F46: 9.53 | G46: 60564.42 | J46: 0 | K46: =+Q46-Y46 -> 0 | L46: =+R46 -> 9.53 | M46: =+L46*K46 -> 0 | N46: =+T46-AB46 -> 0 | O46: =+U46 -> 0 | P46: =+O46*N46 -> 0 | R46: =+F46 -> 9.53 | S46: =+R46*Q46 -> 0 | V46: =+U46*T46 -> 0 | Z46: 9.53 | AA46: 0 | AD46: 0
A47: 2.4 | B47: 电梯井架 | C47: (1)电梯井架_x000D_ (2)综合考虑_x000D_ (3)满足设计图纸、相关规范、招标文件及技术要求 | D47: 座 | E47: 4 | F47: 19769.46 | G47: 64228.241 | J47: 0 | K47: =+Q47-Y47 -> 0 | L47: =+R47 -> 19769.46 | M47: =+L47*K47 -> 0 | N47: =+T47-AB47 -> 0 | O47: =+U47 -> 0 | P47: =+O47*N47 -> 0 | R47: =+F47 -> 19769.46 | S47: =+R47*Q47 -> 0 | V47: =+U47*T47 -> 0 | Z47: 19769.46 | AA47: 0 | AD47: 0
A48: 2.5 | B48: 满堂脚手架 | C48: (1)满堂脚手架_x000D_ (2)搭设高度:5.2m内_x000D_ (3)满足设计图纸、相关规范、招标文件及技术要求 | D48: m2 | E48: 12189.97 | F48: 31.28 | G48: 303495.36 | J48: 0 | K48: =+Q48-Y48 -> 0 | L48: =+R48 -> 31.28 | M48: =+L48*K48 -> 0 | N48: =+T48-AB48 -> 0 | O48: =+U48 -> 0 | P48: =+O48*N48 -> 0 | R48: =+F48 -> 31.28 | S48: =+R48*Q48 -> 0 | V48: =+U48*T48 -> 0 | Z48: 31.28 | AA48: 0 | AD48: 0
A49: 2.6 | B49: 活动脚手架 | C49: (1)独立柱脚手架_x000D_ (2)搭设高度:综合考虑_x000D_ (3)满足设计图纸、相关规范、招标文件及技术要求 | D49: m2 | E49: 928.75 | F49: 4.04 | G49: 2933.3452 | J49: 0 | K49: =+Q49-Y49 -> 0 | L49: =+R49 -> 4.04 | M49: =+L49*K49 -> 0 | N49: =+T49-AB49 -> 0 | O49: =+U49 -> 0 | P49: =+O49*N49 -> 0 | R49: =+F49 -> 4.04 | S49: =+R49*Q49 -> 0 | V49: =+U49*T49 -> 0 | Z49: 4.04 | AA49: 0 | AD49: 0
A50: 3 | B50: 其他工程 | G50: 2162.3836 | M50: =+M51 -> 0 | P50: =+P51 -> 0 | S50: =+S51 -> 0 | V50: =+V51 -> 0 | AA50: 0 | AD50: 0
A51: 3.1 | B51: 止水对拉螺栓 | C51: (1)地下室外墙止水螺栓_x000D_ (2)综合考虑，含切割_x000D_ (3)满足设计图纸、相关规范、招标文件及技术要求 | D51: t | G51: 2162.3836 | L51: =+R51 -> 8189.8 | M51: =+L51*K51 -> 0 | P51: =+O51*N51 -> 0 | R51: 8189.8 | S51: =+R51*Q51 -> 0 | V51: =+U51*T51 -> 0 | Z51: 8189.8 | AA51: 0 | AD51: 0
A52: 二 | B52: 裙楼 | G52: 1103074.9 | J52: 1219366 | M52: =+M53+M76 -> 208812.68 | P52: =+P53+P76 -> 115347.38 | S52: =+S53+S76 -> 990445.42 | V52: =+V53+V76 -> 715306.4 | AA52: 781632.73 | AD52: 599959.02
A53: 1 | B53: 模板工程 | G53: 826227.84 | J53: 945144.6 | M53: =SUM(M54:M75) -> 0 | P53: =SUM(P54:P75) -> 0 | S53: =SUM(S54:S75) -> 781632.73 | V53: =SUM(V54:V75) -> 599959.02 | AA53: 781632.73 | AD53: 599959.02
A54: 1.1 | B54: 矩形柱 | C54: (1)矩形柱 (2)模板:木模板 (3)4m<支模高度≤6m (4)满足设计图纸、相关规范、招标文件及技术要求 (5)建筑物超高增加费 | D54: m2 | F54: 98.29 | G54: 171173.49 | J54: 257322.6 | K54: =+Q54-Y54 -> 0 | L54: =+R54 -> 98.29 | M54: =+L54*K54 -> 0 | N54: =+K54 -> 0 | O54: =+U54 -> 78 | P54: =+O54*N54 -> 0 | Q54: 2111.7 | R54: =+F54 -> 98.29 | S54: =+R54*Q54 -> 207558.99 | T54: =+Q54 -> 2111.7 | U54: 78 | V54: =+U54*T54 -> 164712.6 | Y54: 2111.7 | Z54: 98.29 | AA54: 207558.99 | AB54: 2111.7 | AC54: 78 | AD54: 164712.6
A55: 1.2 | B55: 直形墙 | C55: (1)直形墙，厚度50cm内 (2)模板:木模板 (3)4m<支模高度≤6m (4)满足设计图纸、相关规范、招标文件及技术要求 (5)建筑物超高增加费 | D55: m2 | F55: 86.67 | G55: 78227.908 | J55: 131912.2 | K55: =+Q55-Y55 -> 0 | L55: =+R55 -> 86.67 | M55: =+L55*K55 -> 0 | N55: =+K55 -> 0 | O55: =+U55 -> 78 | P55: =+O55*N55 -> 0 | Q55: 1117.9 | R55: =+F55 -> 86.67 | S55: =+R55*Q55 -> 96888.393 | T55: =+Q55 -> 1117.9 | U55: 78 | V55: =+U55*T55 -> 87196.2 | Y55: 1117.9 | Z55: 86.67 | AA55: 96888.393 | AB55: 1117.9 | AC55: 78 | AD55: 87196.2
A56: 1.3 | B56: 短肢剪力墙、电梯井壁 | C56: (1)电梯井壁 (2)模板:木模板 (3)4m<支模高度≤6m (4)满足设计图纸、相关规范、招标文件及技术要求 (5)建筑物超高增加费 | D56: m2 | F56: 103.37 | G56: 14006.744 | J56: 20117.82 | K56: =+Q56-Y56 -> 0 | L56: =+R56 -> 103.37 | M56: =+L56*K56 -> 0 | N56: =+K56 -> 0 | O56: =+U56 -> 78 | P56: =+O56*N56 -> 0 | Q56: 170.49 | R56: =+F56 -> 103.37 | S56: =+R56*Q56 -> 17623.551 | T56: =+Q56 -> 170.49 | U56: 78 | V56: =+U56*T56 -> 13298.22 | Y56: 170.49 | Z56: 103.37 | AA56: 17623.551 | AB56: 170.49 | AC56: 78 | AD56: 13298.22
A57: 1.4 | B57: 矩形梁 | C57: (1)矩形梁 (2)模板:木模板 (3)梁高≤50cm (4)满足设计图纸、相关规范、招标文件及技术要求 (5)建筑物超高增加费 | D57: m2 | F57: 81.2 | G57: 5310.982 | J57: 9596.94 | K57: =+Q57-Y57 -> 0 | L57: =+R57 -> 81.2 | M57: =+L57*K57 -> 0 | N57: =+K57 -> 0 | O57: =+U57 -> 78 | P57: =+O57*N57 -> 0 | Q57: 81.33 | R57: =+F57 -> 81.2 | S57: =+R57*Q57 -> 6603.996 | T57: =+Q57 -> 81.33 | U57: 78 | V57: =+U57*T57 -> 6343.74 | Y57: 81.33 | Z57: 81.2 | AA57: 6603.996 | AB57: 81.33 | AC57: 78 | AD57: 6343.74
A58: 1.5 | B58: 矩形梁 | C58: (1)矩形梁 (2)模板:木模板 (3)50cm<梁高≤100cm (4)满足设计图纸、相关规范、招标文件及技术要求 (5)建筑物超高增加费 | D58: m2 | F58: 88.86 | G58: 114800.98 | J58: 189978.82 | K58: =+Q58-Y58 -> 0 | L58: =+R58 -> 88.86 | M58: =+L58*K58 -> 0 | N58: =+K58 -> 0 | O58: =+U58 -> 78 | P58: =+O58*N58 -> 0 | Q58: 1506.99 | R58: =+F58 -> 88.86 | S58: =+R58*Q58 -> 133911.13 | T58: =+Q58 -> 1506.99 | U58: 78 | V58: =+U58*T58 -> 117545.22 | Y58: 1506.99 | Z58: 88.86 | AA58: 133911.13 | AB58: 1506.99 | AC58: 78 | AD58: 117545.22
A59: 1.6 | B59: 矩形梁 | C59: (1)矩形梁 (2)模板:木模板 (3)梁高≥100cm (4)满足设计图纸、相关规范、招标文件及技术要求 (5)建筑物超高增加费 | D59: m2 | F59: 93.4 | G59: 7025.056 | J59: 11035.36 | K59: =+Q59-Y59 -> 0 | L59: =+R59 -> 93.4 | M59: =+L59*K59 -> 0 | N59: =+K59 -> 0 | O59: =+U59 -> 78 | P59: =+O59*N59 -> 0 | Q59: 93.52 | R59: =+F59 -> 93.4 | S59: =+R59*Q59 -> 8734.768 | T59: =+Q59 -> 93.52 | U59: 78 | V59: =+U59*T59 -> 7294.56 | Y59: 93.52 | Z59: 93.4 | AA59: 8734.768 | AB59: 93.52 | AC59: 78 | AD59: 7294.56
A60: 1.7 | B60: 有梁板 | C60: (1)有梁板 (2)模板:木模板 (3)板厚12cm (4)满足设计图纸、相关规范、招标文件及技术要求 (5)建筑物超高增加费 | D60: m2 | F60: 84.56 | G60: 16218.875 | J60: 28122.94 | K60: =+Q60-Y60 -> 0 | L60: =+R60 -> 84.56 | M60: =+L60*K60 -> 0 | N60: =+K60 -> 0 | O60: =+U60 -> 78 | P60: =+O60*N60 -> 0 | Q60: 238.33 | R60: =+F60 -> 84.56 | S60: =+R60*Q60 -> 20153.185 | T60: =+Q60 -> 238.33 | U60: 78 | V60: =+U60*T60 -> 18589.74 | Y60: 238.33 | Z60: 84.56 | AA60: 20153.185 | AB60: 238.33 | AC60: 78 | AD60: 18589.74
A61: 1.8 | B61: 有梁板 | C61: (1)有梁板 (2)模板:木模板 (3)板厚15cm (4)满足设计图纸、相关规范、招标文件及技术要求 (5)建筑物超高增加费 | D61: m2 | F61: 85.95 | G61: 82971.755 | J61: 141406.48 | K61: =+Q61-Y61 -> 0 | L61: =+R61 -> 85.95 | M61: =+L61*K61 -> 0 | N61: =+K61 -> 0 | O61: =+U61 -> 78 | P61: =+O61*N61 -> 0 | Q61: 1125.36 | R61: =+F61 -> 85.95 | S61: =+R61*Q61 -> 96724.692 | T61: =+Q61 -> 1125.36 | U61: 78 | V61: =+U61*T61 -> 87778.08 | Y61: 1125.36 | Z61: 85.95 | AA61: 96724.692 | AB61: 1125.36 | AC61: 78 | AD61: 87778.08
A62: 1.9 | B62: 构造柱 | C62: (1)构造柱 (2)模板:木模板 (3)支模高度≤4m (4)满足设计图纸、相关规范、招标文件及技术要求 (5)建筑物超高增加费 | D62: m2 | F62: 84.07 | G62: 30813.066 | J62: 0 | K62: =+Q62-Y62 -> 0 | L62: =+R62 -> 84.07 | M62: =+L62*K62 -> 0 | N62: =+K62 -> 0 | O62: =+U62 -> 78 | P62: =+O62*N62 -> 0 | R62: =+F62 -> 84.07 | S62: =+R62*Q62 -> 0 | T62: =+Q62 -> 0 | U62: 78 | V62: =+U62*T62 -> 0 | Z62: 84.07 | AA62: 0 | AB62: 0 | AC62: 78 | AD62: 0
A63: 1.1 | B63: 构造柱 | C63: (1)矩形柱 (2)模板:木模板 (3)4m<支模高度≤6m (4)满足设计图纸、相关规范、招标文件及技术要求 (5)建筑物超高增加费 | D63: m2 | F63: 98.29 | G63: 7849.4747 | J63: 0 | K63: =+Q63-Y63 -> 0 | L63: =+R63 -> 98.29 | M63: =+L63*K63 -> 0 | N63: =+K63 -> 0 | O63: =+U63 -> 78 | P63: =+O63*N63 -> 0 | R63: =+F63 -> 98.29 | S63: =+R63*Q63 -> 0 | T63: =+Q63 -> 0 | U63: 78 | V63: =+U63*T63 -> 0 | Z63: 98.29 | AA63: 0 | AB63: 0 | AC63: 78 | AD63: 0
A64: 1.11 | B64: 楼梯 | C64: (1)直形楼梯 (2)模板:木模板 (3)满足设计图纸、相关规范、招标文件及技术要求 (4)建筑物超高增加费 | D64: m2 | F64: 160.82 | G64: 19239.918 | J64: 17643.36 | K64: =+Q64-Y64 -> 0 | L64: =+R64 -> 160.82 | M64: =+L64*K64 -> 0 | N64: =+K64 -> 0 | O64: =+U64 -> 78 | P64: =+O64*N64 -> 0 | Q64: 149.52 | R64: =+F64 -> 160.82 | S64: =+R64*Q64 -> 24045.806 | T64: =+Q64 -> 149.52 | U64: 78 | V64: =+U64*T64 -> 11662.56 | Y64: 149.52 | Z64: 160.82 | AA64: 24045.806 | AB64: 149.52 | AC64: 78 | AD64: 11662.56
A65: 1.12 | B65: 圈梁 | C65: (1)圈梁 (2)模板:木模板 (3)满足设计图纸、相关规范、招标文件及技术要求 (4)建筑物超高增加费 | D65: m2 | F65: 92.78 | G65: 9791.3308 | J65: 0 | K65: =+Q65-Y65 -> 0 | L65: =+R65 -> 92.78 | M65: =+L65*K65 -> 0 | N65: =+K65 -> 0 | O65: =+U65 -> 78 | P65: =+O65*N65 -> 0 | R65: =+F65 -> 92.78 | S65: =+R65*Q65 -> 0 | T65: =+Q65 -> 0 | U65: 78 | V65: =+U65*T65 -> 0 | Z65: 92.78 | AA65: 0 | AB65: 0 | AC65: 78 | AD65: 0
A66: 1.13 | B66: 过梁 | C66: (1)过梁 (2)模板:木模板 (3)满足设计图纸、相关规范、招标文件及技术要求 (4)建筑物超高增加费 | D66: m2 | F66: 108.08 | G66: 1641.3209 | J66: 0 | K66: =+Q66-Y66 -> 0 | L66: =+R66 -> 108.08 | M66: =+L66*K66 -> 0 | N66: =+K66 -> 0 | O66: =+U66 -> 78 | P66: =+O66*N66 -> 0 | R66: =+F66 -> 108.08 | S66: =+R66*Q66 -> 0 | T66: =+Q66 -> 0 | U66: 78 | V66: =+U66*T66 -> 0 | Z66: 108.08 | AA66: 0 | AB66: 0 | AC66: 78 | AD66: 0
A67: 1.14 | B67: 栏板 | C67: (1)栏板 (2)模板:木模板 (3)满足设计图纸、相关规范、招标文件及技术要求 (4)建筑物超高增加费 | D67: m2 | F67: 88.61 | G67: 3778.6087 | J67: 6276.42 | K67: =+Q67-Y67 -> 0 | L67: =+R67 -> 88.61 | M67: =+L67*K67 -> 0 | N67: =+K67 -> 0 | O67: =+U67 -> 78 | P67: =+O67*N67 -> 0 | R67: =+F67 -> 88.61 | S67: =+R67*Q67 -> 0 | T67: =+Q67 -> 0 | U67: 78 | V67: =+U67*T67 -> 0 | Z67: 88.61 | AA67: 0 | AB67: 0 | AC67: 78 | AD67: 0
A68: 1.15 | B68: 天沟、檐沟 | C68: (1)天沟、檐沟 (2)模板:木模板 (3)满足设计图纸、相关规范、招标文件及技术要求 (4)建筑物超高增加费 | D68: m2 | F68: 116.3 | G68: 41349.808 | J68: 52692.9 | K68: =+Q68-Y68 -> 0 | L68: =+R68 -> 116.3 | M68: =+L68*K68 -> 0 | N68: =+K68 -> 0 | O68: =+U68 -> 78 | P68: =+O68*N68 -> 0 | R68: =+F68 -> 116.3 | S68: =+R68*Q68 -> 0 | T68: =+Q68 -> 0 | U68: 78 | V68: =+U68*T68 -> 0 | Z68: 116.3 | AA68: 0 | AB68: 0 | AC68: 78 | AD68: 0
A69: 1.16 | B69: 雨篷、悬挑板、阳台板 | C69: (1)雨篷、悬挑板、阳台板 (2)模板:木模板 (3)满足设计图纸、相关规范、招标文件及技术要求 (4)建筑物超高增加费 | D69: m2 | F69: 131.07 | G69: 70785.023 | J69: 79038.76 | K69: =+Q69-Y69 -> 0 | L69: =+R69 -> 131.07 | M69: =+L69*K69 -> 0 | N69: =+K69 -> 0 | O69: =+U69 -> 78 | P69: =+O69*N69 -> 0 | R69: =+F69 -> 131.07 | S69: =+R69*Q69 -> 0 | T69: =+Q69 -> 0 | U69: 78 | V69: =+U69*T69 -> 0 | Z69: 131.07 | AA69: 0 | AB69: 0 | AC69: 78 | AD69: 0
A70: 1.17 | B70: 门槛、反坎 | C70: (1)门槛、反坎 (2)模板:木模板 (3)满足设计图纸、相关规范、招标文件及技术要求 (4)建筑物超高增加费 | D70: m2 | F70: 96.91 | G70: 9342.8645 | J70: 0 | K70: =+Q70-Y70 -> 0 | L70: =+R70 -> 96.91 | M70: =+L70*K70 -> 0 | N70: =+K70 -> 0 | O70: =+U70 -> 78 | P70: =+O70*N70 -> 0 | R70: =+F70 -> 96.91 | S70: =+R70*Q70 -> 0 | T70: =+Q70 -> 0 | U70: 78 | V70: =+U70*T70 -> 0 | Z70: 96.91 | AA70: 0 | AB70: 0 | AC70: 78 | AD70: 0
A71: 1.18 | B71: 梁顶架 | C71: (1)梁顶架 (2)模板:木模板 (3)梁截面高度≤1m (4)支模高度6M以内 (5)满足设计图纸、相关规范、招标文件及技术要求 (6)建筑物超高增加费 | D71: m3 | F71: 18.2 | G71: 21562.86 | J71: 0 | K71: =+Q71-Y71 -> 0 | L71: =+R71 -> 18.2 | M71: =+L71*K71 -> 0 | N71: =+K71 -> 0 | O71: =+U71 -> 10 | P71: =+O71*N71 -> 0 | Q71: 1373.63 | R71: =+F71 -> 18.2 | S71: =+R71*Q71 -> 25000.066 | T71: =+Q71 -> 1373.63 | U71: 10 | V71: =+U71*T71 -> 13736.3 | Y71: 1373.63 | Z71: 18.2 | AA71: 25000.066 | AB71: 1373.63 | AC71: 10 | AD71: 13736.3
A72: 1.19 | B72: 梁顶架 | C72: (1)梁顶架 (2)模板:木模板 (3)1m<梁截面高度≤1.5m (4)支模高度6M以内 (5)满足设计图纸、相关规范、招标文件及技术要求 (6)建筑物超高增加费 | D72: m3 | F72: 20.92 | G72: 8280.8935 | J72: 0 | K72: =+Q72-Y72 -> 0 | L72: =+R72 -> 20.92 | M72: =+L72*K72 -> 0 | N72: =+K72 -> 0 | O72: =+U72 -> 10 | P72: =+O72*N72 -> 0 | Q72: 500.91 | R72: =+F72 -> 20.92 | S72: =+R72*Q72 -> 10479.037 | T72: =+Q72 -> 500.91 | U72: 10 | V72: =+U72*T72 -> 5009.1 | Y72: 500.91 | Z72: 20.92 | AA72: 10479.037 | AB72: 500.91 | AC72: 10 | AD72: 5009.1
A73: 1.2 | B73: 梁顶架 | C73: (1)梁顶架 (2)模板:木模板 (3)1.5m<梁截面高度≤2m (4)支模高度6M以内 (5)满足设计图纸、相关规范、招标文件及技术要求 (6)建筑物超高增加费 | D73: m3 | F73: 22.77 | G73: 12.587993 | J73: 0 | K73: =+Q73-Y73 -> 0 | L73: =+R73 -> 22.77 | M73: =+L73*K73 -> 0 | N73: =+K73 -> 0 | O73: =+U73 -> 10 | P73: =+O73*N73 -> 0 | Q73: 0.7 | R73: =+F73 -> 22.77 | S73: =+R73*Q73 -> 15.939 | T73: =+Q73 -> 0.7 | U73: 10 | V73: =+U73*T73 -> 7 | Y73: 0.7 | Z73: 22.77 | AA73: 15.939 | AB73: 0.7 | AC73: 10 | AD73: 7
A74: 1.21 | B74: 板顶架 | C74: (1)板顶架 (2)模板:木模板 (3)支模高度6M以内 (4)满足设计图纸、相关规范、招标文件及技术要求 (5)建筑物超高增加费 | D74: m3 | F74: 18.2 | G74: 25303.595 | J74: 0 | K74: =+Q74-Y74 -> 0 | L74: =+R74 -> 18.2 | M74: =+L74*K74 -> 0 | N74: =+K74 -> 0 | O74: =+U74 -> 10 | P74: =+O74*N74 -> 0 | Q74: 1760.96 | R74: =+F74 -> 18.2 | S74: =+R74*Q74 -> 32049.472 | T74: =+Q74 -> 1760.96 | U74: 10 | V74: =+U74*T74 -> 17609.6 | Y74: 1760.96 | Z74: 18.2 | AA74: 32049.472 | AB74: 1760.96 | AC74: 10 | AD74: 17609.6
A75: 1.22 | B75: 板顶架 | C75: (1)板顶架 (2)模板:木模板 (3)6m<支模高度≤8m (4)满足设计图纸、相关规范、招标文件及技术要求 (5)建筑物超高增加费 | D75: m3 | F75: 20.71 | G75: 86740.687 | J75: 0 | K75: =+Q75-Y75 -> 0 | L75: =+R75 -> 20.71 | M75: =+L75*K75 -> 0 | N75: =+K75 -> 0 | O75: =+U75 -> 10 | P75: =+O75*N75 -> 0 | Q75: 4917.61 | R75: =+F75 -> 20.71 | S75: =+R75*Q75 -> 101843.7 | T75: =+Q75 -> 4917.61 | U75: 10 | V75: =+U75*T75 -> 49176.1 | Y75: 4917.61 | Z75: 20.71 | AA75: 101843.7 | AB75: 4917.61 | AC75: 10 | AD75: 49176.1
A76: 2 | B76: 脚手架工程 | G76: =SUM(G77:G84) -> 276847.07 | J76: =SUM(J77:J84) -> 274221.43 | M76: =SUM(M77:M84) -> 208812.68 | N76: =+K76 -> 0 | O76: =+U76 -> 0 | P76: =SUM(P77:P84) -> 115347.38 | S76: =SUM(S77:S84) -> 208812.68 | V76: =SUM(V77:V84) -> 115347.38 | AA76: 0 | AD76: 0
A77: 2.1 | B77: 外脚手架 | D77: m2 | E77: 3392.57 | F77: 51.86 | G77: 140904.18 | J77: 254442.75 | K77: =+Q77-Y77 -> 3392.57 | L77: =+R77 -> 51.86 | M77: =+L77*K77 -> 175938.68 | N77: =+K77 -> 3392.57 | O77: =+U77 -> 34 | P77: =+O77*N77 -> 115347.38 | Q77: =+E77 -> 3392.57 | R77: =+F77 -> 51.86 | S77: =+R77*Q77 -> 175938.68 | T77: =+E77 -> 3392.57 | U77: 34 | V77: =+U77*T77 -> 115347.38 | Z77: 51.86 | AA77: 0 | AD77: 0
A78: 2.2 | B78: 安全网 | D78: m2 | E78: 3392.57 | F78: 9.69 | G78: 28251.626 | J78: 19778.683 | K78: =+Q78-Y78 -> 3392.57 | L78: =+R78 -> 9.69 | M78: =+L78*K78 -> 32874.003 | N78: =+K78 -> 3392.57 | O78: =+U78 -> 0 | P78: =+O78*N78 -> 0 | Q78: =+E78 -> 3392.57 | R78: =+F78 -> 9.69 | S78: =+R78*Q78 -> 32874.003 | V78: =+U78*T78 -> 0 | Z78: 9.69 | AA78: 0 | AD78: 0
A79: 2.3 | B79: 里脚手架 | D79: m2 | E79: 2198.64 | F79: 14.05 | G79: 24335.77 | J79: 0 | K79: =+Q79-Y79 -> 0 | L79: =+R79 -> 14.05 | M79: =+L79*K79 -> 0 | N79: =+K79 -> 0 | O79: =+U79 -> 0 | P79: =+O79*N79 -> 0 | R79: =+F79 -> 14.05 | S79: =+R79*Q79 -> 0 | V79: =+U79*T79 -> 0 | Z79: 14.05 | AA79: 0 | AD79: 0
A80: 2.4 | B80: 里脚手架 | D80: m2 | E80: 100.1 | F80: 17.31 | G80: 1362.4046 | J80: 0 | K80: =+Q80-Y80 -> 0 | L80: =+R80 -> 17.31 | M80: =+L80*K80 -> 0 | N80: =+K80 -> 0 | O80: =+U80 -> 0 | P80: =+O80*N80 -> 0 | R80: =+F80 -> 17.31 | S80: =+R80*Q80 -> 0 | V80: =+U80*T80 -> 0 | Z80: 17.31 | AA80: 0 | AD80: 0
A81: 2.5 | B81: 里脚手架 | D81: m2 | E81: 3126.92 | F81: 10.82 | G81: 26662.236 | J81: 0 | K81: =+Q81-Y81 -> 0 | L81: =+R81 -> 10.82 | M81: =+L81*K81 -> 0 | N81: =+K81 -> 0 | O81: =+U81 -> 0 | P81: =+O81*N81 -> 0 | R81: =+F81 -> 10.82 | S81: =+R81*Q81 -> 0 | V81: =+U81*T81 -> 0 | Z81: 10.82 | AA81: 0 | AD81: 0
A82: 2.6 | B82: 里脚手架 | D82: m2 | E82: 310.4 | F82: 26.63 | G82: 6500.4122 | J82: 0 | K82: =+Q82-Y82 -> 0 | L82: =+R82 -> 26.63 | M82: =+L82*K82 -> 0 | N82: =+K82 -> 0 | O82: =+U82 -> 0 | P82: =+O82*N82 -> 0 | R82: =+F82 -> 26.63 | S82: =+R82*Q82 -> 0 | V82: =+U82*T82 -> 0 | Z82: 26.63 | AA82: 0 | AD82: 0
A83: 2.7 | B83: 满堂脚手架 | D83: m2 | E83: 1655.47 | F83: 35.29 | G83: 46382.261 | J83: 0 | K83: =+Q83-Y83 -> 0 | L83: =+R83 -> 35.29 | M83: =+L83*K83 -> 0 | N83: =+K83 -> 0 | O83: =+U83 -> 0 | P83: =+O83*N83 -> 0 | R83: =+F83 -> 35.29 | S83: =+R83*Q83 -> 0 | V83: =+U83*T83 -> 0 | Z83: 35.29 | AA83: 0 | AD83: 0
A84: 2.8 | B84: 满堂脚手架 | D84: m2 | E84: 71.9 | F84: 42.88 | G84: 2448.1806 | J84: 0 | K84: =+Q84-Y84 -> 0 | L84: =+R84 -> 42.88 | M84: =+L84*K84 -> 0 | N84: =+K84 -> 0 | O84: =+U84 -> 0 | P84: =+O84*N84 -> 0 | R84: =+F84 -> 42.88 | S84: =+R84*Q84 -> 0 | V84: =+U84*T84 -> 0 | Z84: 42.88 | AA84: 0 | AD84: 0
A85: 三 | B85: 1#塔楼 | G85: 5079423.4 | J85: 4362951.8 | M85: =+M86+M112 -> 1045537 | P85: =+P86+P112 -> 261045.17 | S85: =+S86+S112 -> 2124737.9 | V85: =+V86+V112 -> 389815.34 | AA85: 1079200.9 | AD85: 432944.75
A86: 1 | B86: 模板工程 | G86: 2761149.5 | J86: 3354456.4 | M86: =SUM(M87:M111) -> 402948.76 | P86: =SUM(P87:P111) -> 261045.17 | S86: =SUM(S87:S111) -> 1466946.1 | V86: =SUM(V87:V111) -> 228956.53 | AA86: 1063997.3 | AD86: 228956.53
A87: 1.1 | B87: 矩形柱 | D87: m2 | F87: 84.07 | G87: 104879.88 | J87: 183727.18 | K87: =+Q87-Y87 -> 0 | L87: =+R87 -> 84.07 | M87: =+L87*K87 -> 0 | N87: =+K87 -> 0 | O87: =+U87 -> 78 | P87: =+O87*N87 -> 0 | Q87: 1145.9968 | R87: =+F87 -> 84.07 | S87: =+R87*Q87 -> 96343.951 | T87: =+Q87 -> 1145.9968 | U87: 78 | V87: =+U87*T87 -> 89387.75 | Y87: 1145.9968 | Z87: 84.07 | AA87: 96343.951 | AB87: 1145.9968 | AC87: 78 | AD87: 89387.75
A88: 1.2 | B88: 直形墙 | D88: m2 | F88: 74.41 | G88: 61420.041 | J88: 120204.24 | K88: =+Q88-Y88 -> 0 | L88: =+R88 -> 74.41 | M88: =+L88*K88 -> 0 | N88: =+K88 -> 0 | O88: =+U88 -> 78 | P88: =+O88*N88 -> 0 | Q88: 769.4431 | R88: =+F88 -> 74.41 | S88: =+R88*Q88 -> 57254.261 | T88: =+Q88 -> 769.4431 | U88: 78 | V88: =+U88*T88 -> 60016.562 | Y88: 769.4431 | Z88: 74.41 | AA88: 57254.261 | AB88: 769.4431 | AC88: 78 | AD88: 60016.562
A89: 1.3 | B89: 短肢剪力墙、电梯井壁 | D89: m2 | F89: 88.66 | G89: 121834.05 | J89: 203266.8 | K89: =+Q89-Y89 -> 0 | L89: =+R89 -> 88.66 | M89: =+L89*K89 -> 0 | N89: =+K89 -> 0 | O89: =+U89 -> 78 | P89: =+O89*N89 -> 0 | R89: =+F89 -> 88.66 | S89: =+R89*Q89 -> 0 | T89: =+Q89 -> 0 | U89: 78 | V89: =+U89*T89 -> 0 | Z89: 88.66 | AA89: 0 | AB89: 0 | AC89: 78 | AD89: 0
A90: 1.4 | B90: 短肢剪力墙、电梯井壁 | D90: m2 | F90: 103.37 | G90: 6137.0391 | J90: 8814.6 | K90: =+Q90-Y90 -> 0 | L90: =+R90 -> 103.37 | M90: =+L90*K90 -> 0 | N90: =+K90 -> 0 | O90: =+U90 -> 78 | P90: =+O90*N90 -> 0 | R90: =+F90 -> 103.37 | S90: =+R90*Q90 -> 0 | T90: =+Q90 -> 0 | U90: 78 | V90: =+U90*T90 -> 0 | Z90: 103.37 | AA90: 0 | AB90: 0 | AC90: 78 | AD90: 0
A91: 1.5 | B91: 矩形梁 | D91: m2 | F91: 81.2 | G91: 41203.373 | J91: 74454.46 | K91: =+Q91-Y91 -> 0 | L91: =+R91 -> 81.2 | M91: =+L91*K91 -> 0 | N91: =+K91 -> 0 | O91: =+U91 -> 78 | P91: =+O91*N91 -> 0 | Q91: =345.4854+95.8757 -> 441.3611 | R91: =+F91 -> 81.2 | S91: =+R91*Q91 -> 35838.521 | T91: =+Q91 -> 441.3611 | U91: 78 | V91: =+U91*T91 -> 34426.166 | Y91: 441.3611 | Z91: 81.2 | AA91: 35838.521 | AB91: 441.3611 | AC91: 78 | AD91: 34426.166
A92: 1.6 | B92: 矩形梁 | D92: m2 | F92: 88.86 | G92: 1222.1746 | J92: 2022.52 | K92: =+Q92-Y92 -> 0 | L92: =+R92 -> 88.86 | M92: =+L92*K92 -> 0 | N92: =+K92 -> 0 | O92: =+U92 -> 78 | P92: =+O92*N92 -> 0 | R92: =+F92 -> 88.86 | S92: =+R92*Q92 -> 0 | T92: =+Q92 -> 0 | U92: 78 | V92: =+U92*T92 -> 0 | Z92: 88.86 | AA92: 0 | AB92: 0 | AC92: 78 | AD92: 0
A93: 1.7 | B93: 矩形梁 | D93: m2 | F93: 93.4 | G93: 5178.6502 | J93: 8134.92 | K93: =+Q93-Y93 -> 0 | L93: =+R93 -> 93.4 | M93: =+L93*K93 -> 0 | N93: =+K93 -> 0 | O93: =+U93 -> 78 | P93: =+O93*N93 -> 0 | R93: =+F93 -> 93.4 | S93: =+R93*Q93 -> 0 | T93: =+Q93 -> 0 | U93: 78 | V93: =+U93*T93 -> 0 | Z93: 93.4 | AA93: 0 | AB93: 0 | AC93: 78 | AD93: 0
A94: 1.8 | B94: 有梁板 | D94: m2 | F94: 84.56 | G94: 4302.9391 | J94: 7461.14 | K94: =+Q94-Y94 -> 0 | L94: =+R94 -> 84.56 | M94: =+L94*K94 -> 0 | N94: =+K94 -> 0 | O94: =+U94 -> 78 | P94: =+O94*N94 -> 0 | Q94: 452.1384 | R94: =+F94 -> 84.56 | S94: =+R94*Q94 -> 38232.823 | T94: =+Q94 -> 452.1384 | U94: 78 | V94: =+U94*T94 -> 35266.795 | Y94: 452.1384 | Z94: 84.56 | AA94: 38232.823 | AB94: 452.1384 | AC94: 78 | AD94: 35266.795
A95: 1.9 | B95: 有梁板 | D95: m2 | F95: 85.03 | G95: 24287.617 | J95: 41868.76 | K95: =+Q95-Y95 -> 0 | L95: =+R95 -> 85.03 | M95: =+L95*K95 -> 0 | N95: =+K95 -> 0 | O95: =+U95 -> 78 | P95: =+O95*N95 -> 0 | R95: =+F95 -> 85.03 | S95: =+R95*Q95 -> 0 | T95: =+Q95 -> 0 | U95: 78 | V95: =+U95*T95 -> 0 | Z95: 85.03 | AA95: 0 | AB95: 0 | AC95: 78 | AD95: 0
A96: 1.1 | B96: 有梁板 | D96: m2 | F96: 85.95 | G96: 8957.9806 | J96: 15266.84 | K96: =+Q96-Y96 -> 0 | L96: =+R96 -> 85.95 | M96: =+L96*K96 -> 0 | N96: =+K96 -> 0 | O96: =+U96 -> 78 | P96: =+O96*N96 -> 0 | R96: =+F96 -> 85.95 | S96: =+R96*Q96 -> 0 | T96: =+Q96 -> 0 | U96: 78 | V96: =+U96*T96 -> 0 | Z96: 85.95 | AA96: 0 | AB96: 0 | AC96: 78 | AD96: 0
A97: 1.11 | B97: 后浇带 | D97: m2 | F97: 108.2 | G97: 981.5678 | J97: 1355.82 | K97: =+Q97-Y97 -> 0 | L97: =+R97 -> 108.2 | M97: =+L97*K97 -> 0 | N97: =+K97 -> 0 | O97: =+U97 -> 78 | P97: =+O97*N97 -> 0 | Q97: 27.803 | R97: =+F97 -> 108.2 | S97: =+R97*Q97 -> 3008.2846 | T97: =+Q97 -> 27.803 | U97: 78 | V97: =+U97*T97 -> 2168.634 | Y97: 27.803 | Z97: 108.2 | AA97: 3008.2846 | AB97: 27.803 | AC97: 78 | AD97: 2168.634
A98: 1.12 | B98: 构造柱 | D98: m2 | F98: 84.07 | G98: 24326.991 | J98: 0 | K98: =+Q98-Y98 -> 0 | L98: =+R98 -> 84.07 | M98: =+L98*K98 -> 0 | N98: =+K98 -> 0 | O98: =+U98 -> 78 | P98: =+O98*N98 -> 0 | R98: =+F98 -> 84.07 | S98: =+R98*Q98 -> 0 | T98: =+Q98 -> 0 | U98: 78 | V98: =+U98*T98 -> 0 | Z98: 84.07 | AA98: 0 | AB98: 0 | AC98: 78 | AD98: 0
A99: 1.13 | B99: 楼梯 | D99: m2 | F99: 160.82 | G99: 8539.0649 | J99: 0 | K99: =+Q99-Y99 -> 0 | L99: =+R99 -> 160.82 | M99: =+L99*K99 -> 0 | N99: =+K99 -> 0 | O99: =+U99 -> 78 | P99: =+O99*N99 -> 0 | R99: =+F99 -> 160.82 | S99: =+R99*Q99 -> 0 | T99: =+Q99 -> 0 | U99: 78 | V99: =+U99*T99 -> 0 | Z99: 160.82 | AA99: 0 | AB99: 0 | AC99: 78 | AD99: 0
A100: 1.14 | B100: 圈梁 | D100: m2 | F100: 92.78 | G100: 676.82352 | J100: 0 | K100: =+Q100-Y100 -> 0 | L100: =+R100 -> 92.78 | M100: =+L100*K100 -> 0 | N100: =+K100 -> 0 | O100: =+U100 -> 78 | P100: =+O100*N100 -> 0 | R100: =+F100 -> 92.78 | S100: =+R100*Q100 -> 0 | T100: =+Q100 -> 0 | U100: 78 | V100: =+U100*T100 -> 0 | Z100: 92.78 | AA100: 0 | AB100: 0 | AC100: 78 | AD100: 0
A101: 1.15 | B101: 过梁 | D101: m2 | F101: 108.08 | G101: 2559.8986 | J101: 0 | K101: =+Q101-Y101 -> 0 | L101: =+R101 -> 108.08 | M101: =+L101*K101 -> 0 | N101: =+K101 -> 0 | O101: =+U101 -> 78 | P101: =+O101*N101 -> 0 | R101: =+F101 -> 108.08 | S101: =+R101*Q101 -> 0 | T101: =+Q101 -> 0 | U101: 78 | V101: =+U101*T101 -> 0 | Z101: 108.08 | AA101: 0 | AB101: 0 | AC101: 78 | AD101: 0
A102: 1.16 | B102: 栏板 | D102: m2 | F102: 88.61 | G102: 94043.951 | J102: 156210.76 | K102: =+Q102-Y102 -> 0 | L102: =+R102 -> 88.61 | M102: =+L102*K102 -> 0 | N102: =+K102 -> 0 | O102: =+U102 -> 78 | P102: =+O102*N102 -> 0 | Q102: 38.751 | R102: =+F102 -> 88.61 | S102: =+R102*Q102 -> 3433.7261 | T102: =+Q102 -> 38.751 | U102: 78 | V102: =+U102*T102 -> 3022.578 | Y102: 38.751 | Z102: 88.61 | AA102: 3433.7261 | AB102: 38.751 | AC102: 78 | AD102: 3022.578
A103: 1.17 | B103: 天沟、檐沟 | D103: m2 | F103: 116.3 | G103: 6599.4867 | J103: 8409.86 | K103: =+Q103-Y103 -> 0 | L103: =+R103 -> 116.3 | M103: =+L103*K103 -> 0 | N103: =+K103 -> 0 | O103: =+U103 -> 78 | P103: =+O103*N103 -> 0 | Q103: 59.8467 | R103: =+F103 -> 116.3 | S103: =+R103*Q103 -> 6960.1712 | T103: =+Q103 -> 59.8467 | U103: 78 | V103: =+U103*T103 -> 4668.0426 | Y103: 59.8467 | Z103: 116.3 | AA103: 6960.1712 | AB103: 59.8467 | AC103: 78 | AD103: 4668.0426
A104: 1.18 | B104: 雨篷、悬挑板、阳台板 | D104: m2 | F104: 131.07 | G104: 625.61186 | J104: 698.56 | K104: =+Q104-Y104 -> 0 | L104: =+R104 -> 131.07 | M104: =+L104*K104 -> 0 | N104: =+K104 -> 0 | O104: =+U104 -> 78 | P104: =+O104*N104 -> 0 | R104: =+F104 -> 131.07 | S104: =+R104*Q104 -> 0 | T104: =+Q104 -> 0 | U104: 78 | V104: =+U104*T104 -> 0 | Z104: 131.07 | AA104: 0 | AB104: 0 | AC104: 78 | AD104: 0
A105: 1.19 | B105: 门槛、反坎 | D105: m2 | F105: 96.91 | G105: 94781.664 | J105: 0 | K105: =+Q105-Y105 -> 0 | L105: =+R105 -> 96.91 | M105: =+L105*K105 -> 0 | N105: =+K105 -> 0 | O105: =+U105 -> 78 | P105: =+O105*N105 -> 0 | R105: =+F105 -> 96.91 | S105: =+R105*Q105 -> 0 | T105: =+Q105 -> 0 | U105: 78 | V105: =+U105*T105 -> 0 | Z105: 96.91 | AA105: 0 | AB105: 0 | AC105: 78 | AD105: 0
A106: 1.2 | B106: 矩形柱 铝模 | D106: m2 | F106: 74.54 | G106: 575665.22 | J106: 662914.7 | K106: =+Q106-Y106 -> 1676.1688 | L106: =+R106 -> 74.54 | M106: =+L106*K106 -> 124941.62 | N106: =+K106 -> 1676.1688 | O106: =+U106 -> 48 | P106: =+O106*N106 -> 80456.102 | Q106: 5503.7388 | R106: =+F106 -> 74.54 | S106: =+R106*Q106 -> 410248.69 | T106: 0 | U106: 48 | V106: =+U106*T106 -> 0 | Y106: 3827.57 | Z106: 74.54 | AA106: 285307.07 | AB106: 0 | AC106: 18 | AD106: 0
A107: 1.21 | B107: 直形墙 铝模 | D107: m2 | F107: 71.95 | G107: 903897.27 | J107: 1078243.6 | K107: =+Q107-Y107 -> 1549.9608 | L107: =+R107 -> 71.95 | M107: =+L107*K107 -> 111519.68 | N107: =+K107 -> 1549.9608 | O107: =+U107 -> 48 | P107: =+O107*N107 -> 74398.118 | Q107: 5573.4397 | R107: =+F107 -> 71.95 | S107: =+R107*Q107 -> 401008.99 | T107: 0 | U107: 48 | V107: =+U107*T107 -> 0 | Y107: 4023.4789 | Z107: 71.95 | AA107: 289489.31 | AB107: 0 | AC107: 18 | AD107: 0
A108: 1.22 | B108: 矩形梁 铝模 | D108: m2 | F108: 79.31 | G108: 258705.08 | J108: 280496.3 | K108: =+Q108-Y108 -> 1187.4547 | L108: =+R108 -> 79.31 | M108: =+L108*K108 -> 94177.032 | N108: =+K108 -> 1187.4547 | O108: =+U108 -> 48 | P108: =+O108*N108 -> 56997.826 | Q108: 2370.1745 | R108: =+F108 -> 79.31 | S108: =+R108*Q108 -> 187978.54 | T108: 0 | U108: 48 | V108: =+U108*T108 -> 0 | Y108: 1182.7198 | Z108: 79.31 | AA108: 93801.507 | AB108: 0 | AC108: 18 | AD108: 0
A109: 1.23 | B109: 有梁板 铝模 | D109: m2 | F109: 70.02 | G109: 398993.32 | J109: 489318.2 | K109: =+Q109-Y109 -> 984.7728 | L109: =+R109 -> 70.02 | M109: =+L109*K109 -> 68953.791 | N109: =+K109 -> 984.7728 | O109: =+U109 -> 48 | P109: =+O109*N109 -> 47269.094 | Q109: 3029.1424 | R109: =+F109 -> 70.02 | S109: =+R109*Q109 -> 212100.55 | T109: 0 | U109: 48 | V109: =+U109*T109 -> 0 | Y109: 2044.3696 | Z109: 70.02 | AA109: 143146.76 | AB109: 0 | AC109: 18 | AD109: 0
A110: 1.24 | B110: 梁后浇带 铝模 | D110: m2 | F110: 94.88 | G110: 290.32585 | J110: 263.2 | K110: =+Q110-Y110 -> 0 | L110: =+R110 -> 94.88 | M110: =+L110*K110 -> 0 | N110: =+K110 -> 0 | O110: =+U110 -> 48 | P110: =+O110*N110 -> 0 | R110: =+F110 -> 94.88 | S110: =+R110*Q110 -> 0 | T110: 0 | U110: 48 | V110: =+U110*T110 -> 0 | Z110: 94.88 | AA110: 0 | AB110: 0 | AC110: 18 | AD110: 0
A111: 1.25 | B111: 板后浇带 铝模 | D111: m2 | F111: 83.74 | G111: 11039.487 | J111: 11323.9 | K111: =+Q111-Y111 -> 40.084 | L111: =+R111 -> 83.74 | M111: =+L111*K111 -> 3356.6342 | N111: =+K111 -> 40.084 | O111: =+U111 -> 48 | P111: =+O111*N111 -> 1924.032 | Q111: 173.604 | R111: =+F111 -> 83.74 | S111: =+R111*Q111 -> 14537.599 | T111: 0 | U111: 48 | V111: =+U111*T111 -> 0 | Y111: 133.52 | Z111: 83.74 | AA111: 11180.965 | AB111: 0 | AC111: 18 | AD111: 0
A112: 2 | B112: 脚手架工程 | G112: 2318273.9 | J112: 1008495.5 | M112: =SUM(M113:M117) -> 642588.28 | P112: =+O112*N112 -> 0 | S112: =SUM(S113:S117) -> 657791.8 | V112: =SUM(V113:V117) -> 160858.81 | AA112: 15203.515 | AD112: 203988.22
A113: 2.1 | B113: 整体提升架 | D113: m2 | E113: =+G113/F113 -> 13577.777 | F113: 160.91 | G113: 2184800.2 | J113: 983848.8 | K113: =+Q113-Y113 -> 3993.464 | L113: =+R113 -> 160.91 | M113: =+L113*K113 -> 642588.28 | N113: =+K113 -> 3993.464 | O113: =+U113 -> 36 | P113: =+O113*N113 -> 143764.7 | Q113: =+T113 -> 3993.464 | R113: 160.91 | S113: =+R113*Q113 -> 642588.28 | T113: =+E113/34*10 -> 3993.464 | U113: 36 | V113: =+U113*T113 -> 143764.7 | Z113: 160.91 | AA113: 0 | AB113: 5191.5031 | AC113: 36 | AD113: 186894.11
A114: 2.2 | B114: 外脚手架 | D114: m2 | E114: =+G114/F114 -> 244.20157 | F114: 51.86 | G114: 12664.294 | J114: 22869 | K114: =+Q114-Y114 -> 0 | L114: =+R114 -> 51.86 | M114: =+L114*K114 -> 0 | N114: =+K114 -> 0 | O114: =+U114 -> 70 | P114: =+O114*N114 -> 0 | Q114: =+E114 -> 244.20157 | R114: 51.86 | S114: =+R114*Q114 -> 12664.294 | T114: 244.20157 | U114: =34+36 -> 70 | V114: =+U114*T114 -> 17094.11 | Y114: 244.20157 | Z114: 51.86 | AA114: 12664.294 | AB114: 244.20157 | AC114: 70 | AD114: 17094.11
A115: 2.3 | B115: 安全网 | D115: m2 | E115: =+G115/F115 -> 262.04553 | F115: 9.69 | G115: 2539.2212 | J115: 1777.6836 | K115: =+Q115-Y115 -> 0 | L115: =+R115 -> 9.69 | M115: =+L115*K115 -> 0 | N115: =+K115 -> 0 | O115: =+U115 -> 0 | P115: =+O115*N115 -> 0 | Q115: =+E115 -> 262.04553 | R115: 9.69 | S115: =+R115*Q115 -> 2539.2212 | T115: 262.04553 | V115: =+U115*T115 -> 0 | Y115: 262.04553 | Z115: 9.69 | AA115: 2539.2212 | AB115: 262.04553 | AD115: 0
A116: 2.4 | B116: 里脚手架 | D116: m2 | E116: =+G116/F116 -> 12645.333 | F116: 8.33 | G116: 105335.63 | J116: 0 | K116: =+Q116-Y116 -> 0 | L116: =+R116 -> 8.33 | M116: =+L116*K116 -> 0 | N116: =+K116 -> 0 | O116: =+U116 -> 0 | P116: =+O116*N116 -> 0 | R116: 8.33 | S116: =+R116*Q116 -> 0 | V116: =+U116*T116 -> 0 | Z116: 8.33 | AA116: 0 | AD116: 0
...

Sheet 安全文明施工费
A1: 工程项目安全文明施工费计算表
A2: 工程名称：XXX项目
A3: 序号 | B3: 分部分项名称 | C3: 单位 | D3: 预测工程竣工数据统计 | H3: 本期数据统计 | M3: 累计数据统计 | R3: 备注 | T3: 上次累计数据统计
D4: 预算收入 | F4: 计划成本 | H4: 预算收入 | J4: 实际成本 | M4: 预算收入 | O4: 实际成本 | T4: 实际成本
D5: 计算式或说明 | E5: 合价 | F5: 计算式或说明 | G5: 合价 | H5: 计算式或说明 | I5: 合价 | J5: 工程量 | K5: 单价 | L5: 合价 | M5: 计算式或说明 | N5: 合价 | O5: 工程量 | P5: 单价 | Q5: 合价 | T5: 工程量 | U5: 单价 | V5: 合价
A6: 一 | B6: 安全文明施工措施费 | E6: 3721871.1 | G6: 4196897.5 | H6: =汇总表!G25/汇总表!D25 -> 0.038887904 | I6: =H6*E6 -> 144735.76 | L6: =SUM(L7:L21) -> 181184.86 | M6: =汇总表!K25/汇总表!D25 -> 0.40973993 | N6: =M6*E6 -> 1524999.2 | Q6: =SUM(Q7:Q21) -> 2145787.4 | V6: 1964602.5
A7: 1 | B7: 运输物流 （惠州市齐顺物流有限公司） | C7: 元 | L7: =+Q7-V7 -> 24434.495 | Q7: 129680.61 | V7: 105246.12
A8: 2 | B8: 安全劳保用品 （广州利源建材有限公司） | C8: 元 | L8: =+Q8-V8 -> 5478.0531 | Q8: 91313.637 | V8: 85835.584
A9: 3 | B9: 箱房 （安捷诚栋国际集成房屋有限公司） | C9: 元 | L9: =+Q9-V9 -> 0 | Q9: 25816 | V9: 25816
A10: 4 | B10: 配电箱 （深圳市弘泰电气设备有限公司） | C10: 元 | L10: =+Q10-V10 -> 0 | Q10: 14381.619 | V10: 14381.619
A11: 5 | B11: 安全网 （广州利源建材有限公司） | C11: 元 | L11: =+Q11-V11 -> 5520 | Q11: 55684.956 | V11: 50164.956
A12: 6 | B12: 消防器材 （深圳市泰禾荣实业有限公司） | C12: 元 | L12: =+Q12-V12 -> 0 | Q12: 67211.363 | V12: 67211.363
A13: 7 | B13: 安全文明施工费 （广州世金建筑劳务有限公司） | C13: 元 | J13: =+O13-T13 -> 3632 | K13: 25 | L13: =+J13*K13 -> 90800 | O13: =4595*3+1950+454*2*16 -> 30263 | P13: 25 | Q13: =+O13*P13 -> 756575 | T13: 26631 | U13: 25 | V13: 665775
A14: 8 | B14: 物业 （武汉炜弘物业管理有限公司） | C14: 元 | L14: =+Q14-V14 -> -22847.575 | Q14: 380792.92 | V14: 403640.49
A15: 9 | B15: 监控网络 （深圳千诺千寻科技有限公司） | C15: 元 | L15: =+Q15-V15 -> -524.27184 | Q15: 17475.728 | V15: 18000
A16: 10 | B16: 热水器 （深圳市九恒科技有限公司） | C16: 元 | L16: =+Q16-V16 -> 2700 | Q16: 8100 | V16: 5400
A17: 11 | B17: 冲孔网 （广东粤晟通建筑设备租赁有限公司） | C17: 元 | L17: =+Q17-V17 -> 0 | Q17: 72576 | V17: 72576
A18: 12 | B18: 电缆线 （深圳中缆电缆集团有限公司司） | C18: 元 | L18: =+Q18-V18 -> 3681.4159 | Q18: 25796.46 | V18: 22115.044
A19: 13 | B19: 生活区水电费 | C19: 元 | L19: =+Q19-V19 -> 33118.1 | Q19: 295491.44 | V19: 262373.34
A20: 14 | B20: 材料调拨（调入） | C20: 元 | L20: =+Q20-V20 -> 38824.64 | Q20: 348757.97 | V20: 309933.33
A21: 15 | B21: 材料调拨（调出） | C21: 元 | L21: =+Q21-V21 -> 0 | Q21: -143866.33 | V21: -143866.33
A22: 二 | B22: CI、标准化 | L22: =SUM(L23:L25) -> 82227.195 | Q22: =SUM(Q23:Q25) -> 682626.85 | V22: 600399.66
A23: 1 | B23: 标准化 （广州炜通建材有限公司） | C23: 元 | L23: =+Q23-V23 -> 37384.336 | Q23: 341102.27 | V23: 303717.94
A24: 2 | B24: 标准化 （广东中筑建筑科技有限公司） | C24: 元 | L24: =+Q24-V24 -> 0 | Q24: 51232.796 | V24: 51232.796
A25: 3 | B25: CI物资 （武汉当加禾盛建筑安装工程有限公司） | C25: 元 | L25: =+Q25-V25 -> 44842.858 | Q25: 290291.78 | V25: 245448.92
A26: 三 | B26: 零星材料 | L26: =SUM(L27:L27) -> 0 | Q26: =SUM(Q27:Q27) -> 226587.75 | V26: 226587.75
A27: 1 | B27: 零星材料 （中建电子商务有限责任公司） | C27: 元 | L27: =+Q27-V27 -> 0 | Q27: 226587.75 | V27: 226587.75
A28: 四 | B28: 临时设施 | L28: =SUM(L29:L31) -> 100000 | Q28: =SUM(Q29:Q35) -> 1107521.7 | V28: 994914.81 | Z28: 临建混凝土 | AA28: 33.5 | AB28: 11486.05 | AC28: 48.5 | AD28: =+AC28*AA28 -> 1624.75
A29: 1 | B29: 租房 | C29: 元 | L29: =+Q29-V29 -> 100000 | Q29: 853583.33 | R29: 10万/月 | V29: 753583.33 | AA29: 数量 | AB29: 材料费 | AC29: 人工单价 | AD29: 人工费
A30: 2 | B30: 围挡 （广西华之通装饰工程有限公司） | C30: 元 | L30: =+Q30-V30 -> 0 | Q30: 22800 | V30: 22800 | Z30: 总混凝土 | AA30: 303 | AB30: 129540.57 | AC30: 48.5 | AD30: =+AC30*AA30 -> 14695.5
A31: 3 | B31: 临建基础（混凝土） | C31: 元 | L31: =+Q31-V31 -> 0 | Q31: 1624.75 | V31: 1624.75 | Z31: 塔吊钢筋 | AA31: 16.489 | AB31: 57691.5 | AC31: 1290 | AD31: =+AC31*AA31 -> 21270.81
A32: 4 | B32: 办公家具 （深圳市金海马网络科技有限公司） | C32: 元 | L32: =+Q32-V32 -> 0 | Q32: 46460 | V32: 46460 | Z32: 塔吊混凝土 | AA32: 269.5 | AB32: 118054.52
A33: 5 | B33: 临建空调 （广州信欧电子科技有限公司） | C33: 元 | L33: =+Q33-V33 -> 0 | Q33: 41307 | V33: 41307
A34: 6 | B34: 临建水电材料 （深圳市粤威龙贸易有限公司） | C34: 元 | L34: =+Q34-V34 -> 12606.894 | Q34: 128671.63 | V34: 116064.73
A35: 7 | B35: 临建水泵 （河南盛之佳建材有限公司） | C35: 元 | L35: =+Q35-V35 -> 0 | Q35: 13075 | V35: 13075
B36: 合计 | E36: =+E22+E6 -> 3721871.1 | G36: =+G22+G6 -> 4196897.5 | I36: =+I28+I26+I22+I6 -> 144735.76 | L36: =+L28+L26+L22+L6 -> 363412.05 | N36: =+N28+N26+N22+N6 -> 1524999.2 | Q36: =+Q28+Q26+Q22+Q6 -> 4162523.7 | V36: 3786504.7

Sheet 施工措施费
A1: 工程项目施工措施费计算表
A2: 工程名称：XXX项目
A3: 序号 | B3: 分部分项名称 | C3: 单位 | D3: 预测工程竣工数据统计 | F3: 本期数据统计 | K3: 累计数据统计 | P3: 备注 | S3: 上次累计
D4: 计划成本 | F4: 预算收入 | H4: 实际成本 | K4: 预算收入 | M4: 实际成本 | S4: 实际成本
D5: 计算式或说明 | E5: 合价 | F5: 计算式或说明 | G5: 合价 | H5: 工程量 | I5: 单价 | J5: 合价 | K5: 计算式或说明 | L5: 合价 | M5: 工程量 | N5: 单价 | O5: 合价 | S5: 合价
A6: 1 | B6: 建筑垃圾外运 | C6: 元 | E6: 451279.3 | O6: =233352.68/1.03 -> 226556
A7: 2 | B7: 材料检验试验费（正非） | C7: 元 | E7: 270767.58 | O7: =21842.1/1.06 -> 20605.755 | S7: 21842.1
A8: 3 | B8: 材料检验试验费（龙岗区质检站） | C8: 元 | O8: =(6600+24140+30520+21240+38620+20900)/1.06 -> 133981.13 | S8: 121120
A9: 4 | B9: 智慧工地 （品茗） | C9: 元 | E9: 225639.65 | O9: =176127.46/1.13 -> 155865.01 | S9: 176127.46
A10: 5 | B10: 竣工场内清理费 | C10: 元 | E10: 135383.79 | J10: =+O10-S10 -> 0
A11: 6 | B11: 省市级优质工地 | C11: 元 | E11: 225639.65 | J11: =+O11-S11 -> 0
A12: 7 | B12: 生活垃圾外运 | C12: 元 | E12: 108000 | J12: =+O12-S12 -> 0
A13: 8 | B13: 地磅 | C13: 元 | E13: 50000 | J13: =+O13-S13 -> 0
A14: 9 | B14: 现场污水处理 | C14: 元 | E14: 90000 | J14: =+O14-S14 -> 0
A15: 10 | B15: 路口开设 | C15: 元 | E15: 100000 | J15: =+O15-S15 -> 0
A16: 11 | B16: 临水接驳 （深圳市银锋达市政工程有限公司） | C16: 元 | O16: =70000/1.03 -> 67961.165 | S16: 70000
A17: 12 | B17: 变压器费用（深圳市立筑建设工程有限公司） | C17: 元 | O17: =310000/1.09 -> 284403.67 | S17: 310000
A18: 13 | B18: 广联达 | C18: 元 | O18: =(8880+9380)/1.06 -> 17226.415 | S18: 18260
A19: 14 | B19: 中建工程产业技术研究院有限公司 | C19: 元 | O19: =183250/1.06 -> 172877.36 | S19: 183250
A20: 15 | B20: 报警（金鼎） | C20: 元 | J20: =+O20-S20 -> 8867.93 | O20: 8867.93
A21: 16 | B21: ……
B22: 合计 | E22: =SUM(E6:E21) -> 1656710 | G22: =SUM(G6:G21) -> 0 | J22: =SUM(J6:J21) -> 8867.93 | L22: =SUM(L6:L21) -> 0 | O22: =SUM(O6:O21) -> 1088344.4 | S22: 900599.56

Sheet 现场经费
A1: 工程项目标价分离现场经费计算表
A2: (M001-15)
A3: 工程名称：XXX项目
A4: 序号 | B4: 费用项目 | C4: 计算依据 | D4: 预测工程竣工计划成本（不含税） | E4: 本期金额（元） （不含税） | F4: 累计金额（元） （不含税） | G4: 备注 | I4: 上次累计（元） （不含税）
A5: 1 | B5: 工资总额 | C5: 按项目部员工工资总额计算 | D5: 7140600 | E5: =+F5-I5 -> 102122.56 | F5: =389799.58+2259993.28 -> 2649792.9 | I5: 2547670.3
A6: 2 | B6: 职工福利费 | C6: 每人每年3500元计算 | D6: 134750 | E6: =+F6-I6 -> 0 | F6: 345487.7 | I6: 345487.7
A7: 3 | B7: 工会经费 | C7: 按（工资总额+五险一金）的2%计算 | D7: 171504.83 | E7: =+F7-I7 -> 1041.36 | F7: 6558.29 | I7: 5516.93
A8: 4 | B8: 职工教育经费 | C8: 按（工资总额+五险一金）的1.5%计算 | D8: 128628.62 | E8: =+F8-I8 -> 0 | F8: 686.53 | I8: 686.53
A9: 5 | B9: 失业保险金 | C9: 按（工资总额-区域补贴）*0.56% | D9: 28775.04 | E9: =+F9-I9 -> 2226.86 | F9: 9674.98 | I9: 7448.12
A10: 6 | B10: 生育保险 | C10: 按（工资总额-区域补贴）*0.45% | D10: 23122.8 | E10: =+F10-I10 -> 936.32 | F10: 5292.5 | I10: 4356.18
A11: 7 | B11: 工伤保险费 | C11: 按（工资总额-区域补贴）*0.39% | D11: 20039.76 | E11: =+F11-I11 -> 1115.92 | F11: 6814.29 | I11: 5698.37
A12: 8 | B12: 医疗保险 | C12: 按（工资总额-区域补贴）*5.2% | D12: 26719.68 | E12: =+F12-I12 -> 15910.93 | F12: =111865.23+514.19 -> 112379.42 | I12: 96468.49
A13: 9 | B13: 职工养老保险金 | C13: 按（工资总额-区域补贴）*14% | D13: 719376 | E13: =+F13-I13 -> 39201.38 | F13: 246827.64 | I13: 207626.26
A14: 10 | B14: 住房公积金 | C14: 按（工资总额-区域补贴）*12% | D14: 616608 | E14: =+F14-I14 -> 51329.09 | F14: =210474.8+191555.19 -> 402029.99 | I14: 350700.9
A15: 11 | B15: 企业年金 | C15: 公司暂未执行 | D15: 0 | E15: =+F15-I15 -> 0 | F15: 0 | I15: 0
A16: 12 | B16: 临时工、辅助岗位 | C16: 按实际计算，含薪酬、五险一金；另加50元/每人每月 | D16: 662000 | E16: =+F16-I16 -> -424124.64 | I16: 424124.64
A17: 13 | B17: 冷暖补贴 | C17: 按文件执行 | D17: 54000 | E17: =+F17-I17 -> 0
A18: 14 | B18: 工作餐补贴 | C18: 按文件执行 | D18: 15435 | E18: =+F18-I18 -> 0
A19: 15 | B19: 办公费 | C19: 按400-500元/人月（含空调、固定电话、宽带网等）计算 | D19: 184800 | E19: =+F19-I19 -> 0 | F19: 30331.5 | I19: 30331.5
A20: 16 | B20: 差旅费 | C20: 合同额0.15%~0.2% | D20: 222227.42 | E20: =+F20-I20 -> 0 | F20: 9069.33 | I20: 9069.33
A21: 17 | B21: 业务招待费 | C21: 按自行完成产值0.1%~0.15% | D21: 111113.71 | E21: =+F21-I21 -> 0 | F21: =56340 -> 56340 | I21: 56340
A22: 18 | B22: 固定资产折旧及摊销费 | C22: 按实际计算 | D22: / | E22: =+F22-I22 -> 0
A23: 19 | B23: 中介机构费 | C23: 按相关文件、双方合同计算 | D23: / | E23: =+F23-I23 -> 0
A24: 20 | B24: 物业费 | C24: 按实际计算 | D24: 1831200 | E24: =+F24-I24 -> 0
A25: 21 | B25: 广告宣传费 | C25: 按实际计算 | D25: / | E25: =+F25-I25 -> 0
A26: 22 | B26: 上级管理费 | C26: 按自行完成产值0.6% | D26: / | E26: =+F26-I26 -> 0
A27: 23 | B27: 诉讼费 | C27: 按实际计算 | D27: / | E27: =+F27-I27 -> 0
A28: 24 | B28: 工程保修费 | C28: 按自行完成产值0.5%~1%计算 | D28: 833352.82 | E28: =+F28-I28 -> 0
A29: 25 | B29: 合同印花税及其它税费 | C29: 按合同额万分之三 | D29: 33334.113 | E29: =+F29-I29 -> 0
A30: 26 | B30: 市场交易费 | C30: 按实际计算 | D30: / | E30: =+F30-I30 -> 0
A31: 27 | B31: 工程保险费 | C31: 按实际计算 | D31: 131114.18 | E31: =+F31-I31 -> -64695.31 | F31: 234781.66 | I31: 299476.97
A32: 28 | B32: 卫生费 | C32: 根据当地文件计算 | D32: / | E32: =+F32-I32 -> 0
A33: 29 | B33: 建管费 | C33: 根据当地文件计算 | D33: / | E33: =+F33-I33 -> 0
A34: 30 | B34: 工程履约保函手续费 | C34: 按实际计算 | D34: 20000.468 | E34: =+F34-I34 -> 0
A35: 31 | B35: 图纸复印 | C35: 设计院出蓝图，每套3000元 | D35: 12000 | E35: =+F35-I35 -> 0
A36: 32 | B36: 竣工资料 | C36: 复印装订等资料1.5-2.5万元包干 | D36: 80000 | E36: =+F36-I36 -> 0
A37: 33 | B37: 前期投入费用 | C37: 按自行完成产值1% | D37: / | E37: =+F37-I37 -> 0
A38: 34 | B38: 财务费用 | E38: =+F38-I38 -> -16782.69 | F38: 62715.15 | G38: 手续费 | I38: 79497.84
A39: 35 | B39: 摊销费 | E39: =+F39-I39 -> -81704 | I39: 81704
A40: 36 | B40: 其他 | E40: =+F40-I40 -> -355574.37 | F40: 6952.36 | I40: 362526.73
A41: 合计 | D41: =SUM(D5:D40) -> 13200702 | E41: =SUM(E5:E40) -> -728996.59 | F41: =SUM(F5:F40)+600000 -> 4785734.2 | I41: 4914730.8

Sheet 管理费、利润、规费、税金
A1: 工程项目管理费、利润、规费、税金费用表
A2: 工程名称：XXX项目
A3: 序号 | B3: 管理费、利润、规费 税金费用明细 | C3: 单位 | D3: 预测工程竣工数据统计 | F3: 本期数据统计 | H3: 累计数据统计 | J3: 备注
D4: 预算收入 | E4: 计划成本 | F4: 预算收入 | G4: 实际成本 | H4: 预算收入 | I4: 实际成本
A5: 1 | B5: 管理费（含工程保险） | C5: 元 | D5: 4884475.9 | E5: 13200702 | F5: =D5*汇总表!$G$25/汇总表!$D$25 -> 189947.03 | G5: =现场经费!$E$41 -> -728996.59 | H5: =汇总表!$K$25/汇总表!$D$25*D5 -> 2001364.8 | I5: =现场经费!F41 -> 4785734.2
A6: 2 | B6: 利润 | C6: 元 | D6: 4867994.6 | F6: =D6*汇总表!$G$25/汇总表!$D$25 -> 189306.11 | H6: =汇总表!$K$25/汇总表!$D$25*D6 -> 1994611.8
A7: 3 | B7: 规费 | C7: 元 | D7: 5142966.4 | F7: =D7*汇总表!$G$25/汇总表!$D$25 -> 199999.18 | H7: =汇总表!$K$25/汇总表!$D$25*D7 -> 2107278.7
A8: 4 | B8: 税金 | C8: 元 | J8: （销项税-进项税）*12%
B13: 合计 | D13: =SUM(D5:D12) -> 14895437 | E13: =SUM(E5:E12) -> 13200702 | F13: =SUM(F5:F12) -> 579252.32 | G13: =SUM(G5:G12) -> -728996.59 | H13: =SUM(H5:H12) -> 6103255.2 | I13: =SUM(I5:I12) -> 4785734.2

Sheet 让利
A1: 工程项目让利费用计算表
A2: 工程名称：XXX项目
A3: 序号 | B3: 分部分项名称 | C3: 单位 | D3: 预测工程竣工数据统计 | G3: 本期数据统计 | J3: 累计数据统计 | M3: 备注
D4: 预算收入 | F4: 预计成本 | G4: 预算收入 | I4: 实际成本 | J4: 预算收入 | L4: 实际成本
D5: 计算式或说明 | E5: 合价 | F5: 合计 | G5: 计算式或说明 | H5: 合价 | I5: 合价 | J5: 计算式或说明 | K5: 合价 | L5: 合价
B17: 合计

Sheet 总包服务费
A1: 工程项目总包服务费用计算表
A2: 工程名称：XXX项目
A3: 序号 | B3: 分部分项名称 | C3: 单位 | D3: 预测工程竣工数据统计 | G3: 本期数据统计 | J3: 累计数据统计 | M3: 备注
D4: 预算收入 | F4: 预计成本 | G4: 预算收入 | I4: 实际成本 | J4: 预算收入 | L4: 实际成本
D5: 计算式或说明 | E5: 合价 | F5: 合计 | G5: 计算式或说明 | H5: 合价 | I5: 合价 | J5: 计算式或说明 | K5: 合价 | L5: 合价
A6: 1 | B6: 机电配合费 | C6: 元 | I6: =-专业分包费!O581*0.02 -> 15870.872 | L6: =-专业分包费!U581*0.02 -> -25477.751
B17: 合计 | I17: =SUM(I6:I16) -> 15870.872 | L17: =SUM(L6:L16) -> -25477.751

Sheet 指定分包
A1: 工程项目指定分包计算表
A2: 工程名称：XXX项目
A3: 序号 | B3: 分部分项名称 | C3: 单位 | D3: 预测工程竣工数据统计 | F3: 本期数据统计 | I3: 累计数据统计 | L3: 备注
D4: 预算收入 | F4: 预算收入 | H4: 实际成本 | I4: 预算收入 | K4: 实际成本
D5: 计算式或说明 | E5: 合价 | F5: 计算式或说明 | G5: 合价 | H5: 合价 | I5: 计算式或说明 | J5: 合价 | K5: 合价
A6: 1 | B6: 专业工程暂估价 | C6: 项
A7: 2 | B7: 扣除专业工程暂估价中防水卷材 4mm 材料费 | C7: m2
A8: 3 | B8: 扣除专业工程暂估价中防水卷材 3mm 材料费 | C8: m2
A9: 4 | B9: 扣除专业工程暂估价中蜂巢芯 材料费 | C9: 个
A10: 5 | B10: 扣除专业工程暂估价中底板防水 人工费 | C10: m2
A11: 6 | B11: 扣除专业工程暂估价中集水坑及电梯井防水人工费 | C11: m2
A12: 7 | B12: 扣除专业工程暂估价中锚杆防水人工费 | C12: 个
B13: 合计 | D13: 0 | E13: =SUM(E6:E12) -> 0

Sheet 其它
A1: 工程项目其他费用计算表
A2: 工程名称：XXX项目
A3: 序号 | B3: 费用名称 | C3: 单位 | D3: 预测工程竣工数据统计 | J3: 本期数据统计 | P3: 累计数据统计 | V3: 备注
D4: 预算收入 | G4: 预计成本 | J4: 预算收入 | M4: 实际成本 | P4: 预算收入 | S4: 实际成本
D5: 工程量 | E5: 单价 | F5: 合价 | G5: 工程量 | H5: 单价 | I5: 合价 | J5: 工程量 | K5: 单价 | L5: 合价 | M5: 工程量 | N5: 单价 | O5: 合价 | P5: 工程量 | Q5: 单价 | R5: 合价 | S5: 工程量 | T5: 单价 | U5: 合价
A6: 1 | B6: 前期投入费用 | H6: 土建合同额*1% | I6: 1111137.1
A7: 2 | B7: 暂列金额 | F7: 3091743.1 | I7: 3091743.1
A8: 3 | B8: 暂估价 | F8: 293577.98 | I8: 293577.98
V9: 土方签证
V10: 世金签证
B22: 合计 | F22: =SUM(F6:F11) -> 3385321.1 | I22: =SUM(I6:I11) -> 4496458.2 | L22: =SUM(L6:L11) -> 0 | O22: =SUM(O6:O11) -> 0 | R22: =SUM(R6:R11) -> 0 | U22: =SUM(U6:U11) -> 0

Sheet 开源效益
C1: 中国建筑 项目管理表格
C2: 项目商务策划书
A4: 项目名称：XXX项目 | F4: 策划情况 | K4: 策划后 | R4: 策划前
K5: 收入 | N5: 成本 | Q5: 利润 | R5: 收入 | U5: 成本 | X5: 利润
A6: 序号 | B6: 策划专项名称 | C6: 策划内容 | D6: 策划状态 | E6: 策划目标 （元） | F6: 收入变化情况 | G6: 成本变化情况 | H6: 策划前盈亏 | I6: 策划效益 | J6: 直接效益 | K6: 工程量 （收入） | L6: 单价 （收入） | M6: 合价 （收入） | N6: 工程量 （成本） | O6: 单价 （成本） | P6: 合价 （成本） | R6: 工程量 （收入） | S6: 单价 （收入） | T6: 合价 （收入） | U6: 工程量（成本） | V6: 单价 （成本） | W6: 合价 （成本）
A7: 一 | B7: 设计策划 | E7: =SUM(E8:E27) -> #REF! | F7: =SUM(F8:F27) -> 412342.12 | G7: =SUM(G8:G27) -> #REF! | H7: =SUM(H8:H27) -> #REF! | I7: =SUM(I8:I27) -> #REF! | J7: =SUM(J8:J27) -> #REF! | M7: =SUM(M8:M27) -> 2650170.7 | P7: =SUM(P8:P27) -> #REF! | Q7: =SUM(Q8:Q27) -> #REF! | T7: =SUM(T8:T27) -> 2237828.6 | W7: =SUM(W8:W27) -> #REF! | X7: =SUM(X8:X27) -> #REF!
A8: 1 | B8: 土方侧壁回填策划 | C8: 图纸约定采用灰土、级配砂石、素土分层回填，沟通业主采用素土回填，与业主单位进行沟通，以施工进度为优化条件，提出做法变更，将原设计要求的三种材料分层回填修改成素土分层夯实回填 | D8: 已实施 | E8: =I8 -> #REF! | F8: =M8-T8 -> 0 | G8: =P8-W8 -> #REF! | H8: =X8 -> #REF! | I8: =Q8-X8 -> #REF! | J8: =Q8 -> #REF! | K8: 0 | L8: 0 | M8: =K8*L8 -> 0 | N8: 1 | O8: ='[2]1.1土方侧壁回填'!F21 -> #REF! | P8: =N8*O8 -> #REF! | Q8: =M8-P8 -> #REF! | R8: 0 | S8: 0 | T8: =R8*S8 -> 0 | U8: 1 | V8: ='[2]1.1土方侧壁回填'!F7 -> #REF! | W8: =U8*V8 -> #REF! | X8: =T8-W8 -> #REF!
A9: 2 | B9: 砖胎膜材料优化 | C9: 原图纸中砖胎膜材料为实心砖，优化为加气混凝土砌块 | D9: 已实施 | E9: =I9 -> 39818.514 | F9: =M9-T9 -> 0 | G9: =P9-W9 -> -39818.514 | H9: =X9 -> -24174.288 | I9: =Q9-X9 -> 39818.514 | J9: =Q9 -> 15644.226 | K9: 1 | L9: ='[3]1.2砖胎膜材料优化'!F26 -> 147030.19 | M9: =K9*L9 -> 147030.19 | N9: 1 | O9: ='[3]1.2砖胎膜材料优化'!F21 -> 131385.96 | P9: =N9*O9 -> 131385.96 | Q9: =M9-P9 -> 15644.226 | R9: 1 | S9: ='[3]1.2砖胎膜材料优化'!F12 -> 147030.19 | T9: =R9*S9 -> 147030.19 | U9: 1 | V9: ='[3]1.2砖胎膜材料优化'!F7 -> 171204.48 | W9: =U9*V9 -> 171204.48 | X9: =T9-W9 -> -24174.288
A10: 3 | B10: 直螺纹连接优化 | C10: 原图纸混凝土墙、柱、梁、板钢筋＞16时，采用Ⅱ级接头，转换柱、梁钢筋＞18时，采用Ⅱ级接头，经沟通设计，所有钢筋≥16时，均采用Ⅱ级接头机械连接 | D10: 正在实施 | E10: =I10 -> 35370.183 | F10: =M10-T10 -> 0 | G10: =P10-W10 -> -35370.183 | H10: =X10 -> -41689.103 | I10: =Q10-X10 -> 35370.183 | J10: =Q10 -> -6318.92 | K10: 0 | L10: 0 | M10: =K10*L10 -> 0 | N10: 1 | O10: ='[3]1.3直螺纹连接优化'!F21 -> 6318.92 | P10: =N10*O10 -> 6318.92 | Q10: =M10-P10 -> -6318.92 | R10: 0 | S10: 0 | T10: =R10*S10 -> 0 | U10: 1 | V10: ='[3]1.3直螺纹连接优化'!F7 -> 41689.103 | W10: =U10*V10 -> 41689.103 | X10: =T10-W10 -> -41689.103
A11: 4 | B11: 铝模深化修改外墙结构 | C11: 1.通过铝模深化，ALC墙板改为现浇外墙，实际施工取消外墙20mm厚抹灰、3厚高分子益胶泥 | D11: 放弃 | E11: =I11 -> 118427.84 | F11: =M11-T11 -> 0 | G11: =P11-W11 -> -118427.84 | H11: =X11 -> -118427.84 | I11: =Q11-X11 -> 118427.84 | J11: =Q11 -> 0 | K11: 0 | L11: 0 | M11: =K11*L11 -> 0 | N11: 1 | O11: ='[3]1.4铝模深化修改外墙结构'!F21 -> 0 | P11: =N11*O11 -> 0 | Q11: =M11-P11 -> 0 | R11: 0 | S11: 0 | T11: =R11*S11 -> 0 | U11: 1 | V11: ='[3]1.4铝模深化修改外墙结构'!F7 -> 118427.84 | W11: =U11*V11 -> 118427.84 | X11: =T11-W11 -> -118427.84
A12: 5 | B12: 铝模深化修改二次结构 | C12: 1.通过铝模深化，可以将二次结构深化到铝模中，一次浇筑完成，避免后期二次支模，节约工期增加效益。 2.采用铝模代替传统模板施工/铝模深化设计，构造柱、下挂梁（板）、滴水线、预留强弱电箱、水槽等位置。 | D12: 正在实施 | E12: =I12 -> 71348.43 | F12: =M12-T12 -> 0 | G12: =P12-W12 -> -71348.43 | H12: =X12 -> -96899.516 | I12: =Q12-X12 -> 71348.43 | J12: =Q12 -> -25551.086 | K12: 0 | L12: 0 | M12: =K12*L12 -> 0 | N12: 1 | O12: =+'[4]1.5铝模深化修改二次结构 '!F21 -> 25551.086 | P12: =N12*O12 -> 25551.086 | Q12: =M12-P12 -> -25551.086 | R12: 0 | S12: 0 | T12: =R12*S12 -> 0 | U12: 1 | V12: =+'[4]1.5铝模深化修改二次结构 '!F7 -> 96899.516 | W12: =U12*V12 -> 96899.516 | X12: =T12-W12 -> -96899.516
A13: 6 | B13: 铝模深化优化装饰做法 | C13: 1.飘板放坡铝模一次成型，减少二次砂浆抹面。 2、外窗取消四边企口预留，取消窗下口砂浆塞缝，取消窗边外侧抹灰； 3.将窗框处做法优化为预埋钢附框，减少窗周边塞缝工序，降低渗漏风险。 | D13: 正在实施 | E13: =I13 -> 52136.266 | F13: =M13-T13 -> 0 | G13: =P13-W13 -> -52136.266 | H13: =X13 -> -52136.266 | I13: =Q13-X13 -> 52136.266 | J13: =Q13 -> 0 | K13: 0 | L13: 0 | M13: =K13*L13 -> 0 | N13: 1 | O13: =+'[4]1.6铝模深化优化装饰做法 '!F21 -> 0 | P13: =N13*O13 -> 0 | Q13: =M13-P13 -> 0 | R13: 0 | S13: 0 | T13: =R13*S13 -> 0 | U13: 1 | V13: =+'[4]1.6铝模深化优化装饰做法 '!F7 -> 52136.266 | W13: =U13*V13 -> 52136.266 | X13: =T13-W13 -> -52136.266
A14: 7 | B14: 承台模板优化 | C14: 图纸变标高处底板大样，侧壁竖向模板采用混凝土浇筑；考虑现场施工便利，将竖向模板改为蒸压加气块砖胎膜。 | D14: 已实施 | E14: =I14 -> 30000 | F14: =M14-T14 -> 0 | G14: =P14-W14 -> -30000 | H14: =X14 -> -30000 | I14: =Q14-X14 -> 30000 | J14: =Q14 -> 0 | K14: 0 | L14: 0 | M14: =K14*L14 -> 0 | N14: 1 | O14: =+'[4]1.7承台模板优化 '!F21 -> 0 | P14: =N14*O14 -> 0 | Q14: =M14-P14 -> 0 | R14: 0 | S14: 0 | T14: =R14*S14 -> 0 | U14: 1 | V14: =+'[4]1.7承台模板优化 '!F7 -> 30000 | W14: =U14*V14 -> 30000 | X14: =T14-W14 -> -30000
A15: 8 | B15: 天棚JS取消 | C15: 天棚JS为亏损项，上层卫生间、厨房已做地面防水，JS防潮层无意义，可沟通业主取消，双方都可以省成本 | D15: 未实施 | E15: =I15 -> 84447.101 | F15: =M15-T15 -> -68907.199 | G15: =P15-W15 -> -153354.3 | H15: =X15 -> -84447.101 | I15: =Q15-X15 -> 84447.101 | J15: =Q15 -> 0 | K15: 0 | L15: =+'[4]1.8天棚JS取消 '!F26 -> 0 | M15: =K15*L15 -> 0 | N15: 1 | O15: =+'[4]1.8天棚JS取消 '!F21 -> 0 | P15: =N15*O15 -> 0 | Q15: =M15-P15 -> 0 | R15: 1 | S15: =+'[4]1.8天棚JS取消 '!F12 -> 68907.199 | T15: =R15*S15 -> 68907.199 | U15: 1 | V15: =+'[4]1.8天棚JS取消 '!F7 -> 153354.3 | W15: =U15*V15 -> 153354.3 | X15: =T15-W15 -> -84447.101
A16: 9 | B16: 防水做法优化 | C16: 原图纸防水做法为“3.0厚自粘聚合物改性沥青防水卷材，2.0厚非固化橡胶沥青防水涂膜”，防水工序倒置，对施工基层要求高，经与设计及建设单位沟通，防水做法改为1.5厚湿铺防水卷材+3.0厚自粘聚合物改性沥青防水卷材，且增加50mm厚防水保护层 | D16: 已实施 | E16: =I16 -> 164418.82 | F16: =M16-T16 -> 325308.37 | G16: =P16-W16 -> 160889.55 | H16: =X16 -> 138321.54 | I16: =Q16-X16 -> 164418.82 | J16: =Q16 -> 302740.36 | K16: 1 | L16: =+'[4]1.9防水做法优化 '!F28 -> 725567.71 | M16: =K16*L16 -> 725567.71 | N16: 1 | O16: =+'[4]1.9防水做法优化 '!F23 -> 422827.35 | P16: =N16*O16 -> 422827.35 | Q16: =M16-P16 -> 302740.36 | R16: 1 | S16: =+'[4]1.9防水做法优化 '!F12 -> 400259.34 | T16: =R16*S16 -> 400259.34 | U16: 1 | V16: =+'[4]1.9防水做法优化 '!F7 -> 261937.8 | W16: =U16*V16 -> 261937.8 | X16: =T16-W16 -> 138321.54
A17: 10 | B17: 天然石粉 | C17: 将地下室抹灰腻子涂料墙面修改为天然石粉墙面，腻子涂料顶棚修改为天然石粉顶棚，利用成本降低、施工进度、表面质量及耐久性为切入点，将地下室内墙及天棚变更为天然石粉，仅变更做法，不改变合同价款，降低成本，利润再扩大 | D17: 放弃 | E17: =I17 -> 659912.94 | F17: =M17-T17 -> 0 | G17: =P17-W17 -> -659912.94 | H17: =X17 -> 150405.62 | I17: =Q17-X17 -> 659912.94 | J17: =Q17 -> 810318.56 | K17: 0 | L17: 1 | M17: =+'[4]1.10天然石粉 '!F26 -> 1565264.8 | N17: 1 | O17: =+'[4]1.10天然石粉 '!F21 -> 754946.24 | P17: =N17*O17 -> 754946.24 | Q17: =M17-P17 -> 810318.56 | R17: 1 | S17: =+'[4]1.10天然石粉 '!F12 -> 1565264.8 | T17: =R17*S17 -> 1565264.8 | U17: 1 | V17: =+'[4]1.10天然石粉 '!F7 -> 1414859.2 | W17: =U17*V17 -> 1414859.2 | X17: =T17-W17 -> 150405.62
A18: 11 | B18: 楼梯间踢脚工艺优化 | C18: 踢1楼梯间及前室踢脚线为5mmM20水泥砂浆抹面压光，该做法较难控制质量，沟通设计及建设单位，踢1踢脚改为涂料施工，增加收益 | D18: 正在实施 | E18: =I18 -> 4206.5 | F18: =M18-T18 -> -21032.5 | G18: =P18-W18 -> -25239 | H18: =X18 -> -10936.9 | I18: =Q18-X18 -> 4206.5 | J18: =Q18 -> -6730.4 | K18: 0 | L18: 1 | M18: =+'[4]1.11楼梯间踢脚工艺优化 '!F26 -> 35334.6 | N18: 1 | O18: =+'[4]1.11楼梯间踢脚工艺优化 '!F21 -> 42065 | P18: =N18*O18 -> 42065 | Q18: =M18-P18 -> -6730.4 | R18: 1 | S18: =+'[4]1.11楼梯间踢脚工艺优化 '!F12 -> 56367.1 | T18: =R18*S18 -> 56367.1 | U18: 1 | V18: =+'[4]1.11楼梯间踢脚工艺优化 '!F7 -> 67304 | W18: =U18*V18 -> 67304 | X18: =T18-W18 -> -10936.9
A19: 12 | B19: 幕墙工程策划 | C19: 幕墙深化设计： 1.铝合金龙骨、铝型材及连接套芯采用3063-Y6型； 2.根据铝板及防火岩棉安装位置，铝板取消防火漆，防火岩棉采用不小于80kg/m³容重； 3.空调格栅截面厚度由2mm降低至1.6mm； 4.横向装饰线条固定后植埋件螺栓优化为M6，间距由650mm优化为1500mm； 5.节点F4024裙楼吊顶龙骨由300×100×6优化为200×100+100×100×2.5； 6.塔楼造型楼板节点优化，取消竖向接缝，改为横向接缝，即可消除渗漏隐患又能减少铝板20%用量（F5002/F5004/F5006/F5008.1节点） 幕墙工程将可优化项放入招标前置相较于标价分离成本降低 | D19: 正在实施 | E19: =I19 -> 1512200 | F19: =M19-T19 -> 0 | G19: =P19-W19 -> -1512200 | H19: =X19 -> -1512200 | I19: =Q19-X19 -> 1512200 | J19: =Q19 -> 0 | K19: 0 | L19: 0 | M19: =K19*L19 -> 0 | N19: 0 | O19: 0 | P19: =N19*O19 -> 0 | Q19: =M19-P19 -> 0 | R19: 0 | S19: 0 | T19: =R19*S19 -> 0 | U19: 1 | V19: 1512200 | W19: =U19*V19 -> 1512200 | X19: =T19-W19 -> -1512200
A20: 13 | B20: 氟碳喷涂优化 | C20: 栏杆喷涂方式由氟碳喷涂改为粉末喷涂 | D20: 放弃 | E20: =I20 -> 10000 | F20: =M20-T20 -> 0 | G20: =P20-W20 -> -10000 | H20: =X20 -> -10000 | I20: =Q20-X20 -> 10000 | J20: =Q20 -> 0 | K20: 0 | L20: 0 | M20: =K20*L20 -> 0 | N20: 1 | O20: ='[5]1.13减少入岩长度'!F26 -> 0 | P20: =N20*O20 -> 0 | Q20: =M20-P20 -> 0 | R20: 0 | S20: 0 | T20: =R20*S20 -> 0 | U20: 1 | V20: 10000 | W20: =U20*V20 -> 10000 | X20: =T20-W20 -> -10000
A21: 14 | B21: 17层外凸板优化 | C21: 17层避难层因消防面积，结构设计外凸600-1000mm板，沟通设计及业主将钢筋混凝土外凸板优化为钢结构施工，避免后期做悬挑脚手架或三角钢支撑施工，降低施工安全风险、节省工期、降低施工难度 | D21: 正在实施 | F21: =M21-T21 -> 0 | G21: =P21-W21 -> -91040.418 | H21: =X21 -> -91040.418 | I21: =Q21-X21 -> 91040.418 | J21: =Q21 -> 0 | L21: 1 | M21: =K21*L21 -> 0 | N21: 0 | O21: 0 | P21: =N21*O21 -> 0 | Q21: =M21-P21 -> 0 | R21: 0 | S21: 0 | T21: =R21*S21 -> 0 | U21: 1 | V21: =+'[4]1.1417层外凸板优化 '!F7 -> 91040.418 | W21: =U21*V21 -> 91040.418 | X21: =T21-W21 -> -91040.418
A22: 15 | B22: 钢筋翻样优化 | C22: 钢筋翻样优化明细节点详见四优化清单做法 | D22: 正在实施 | E22: =I22 -> 913844.4 | F22: =M22-T22 -> 0 | G22: =P22-W22 -> -913844.4 | H22: =X22 -> -11423055 | I22: =Q22-X22 -> 913844.4 | J22: =Q22 -> -10509211 | K22: 0 | L22: 0 | M22: =K22*L22 -> 0 | N22: 1 | O22: =+'[4]1.15钢筋翻样优化 '!F21 -> 10509211 | P22: =N22*O22 -> 10509211 | Q22: =M22-P22 -> -10509211 | R22: 0 | S22: 0 | T22: =R22*S22 -> 0 | U22: 1 | V22: =+'[4]1.15钢筋翻样优化 '!F7 -> 11423055 | W22: =U22*V22 -> 11423055 | X22: =T22-W22 -> -11423055
A23: 16 | B23: 装配式构件 | C23: 1.根据深圳市住建局文件要求，板配筋间距不能小于150mm，联动设计，对现浇板、叠合板板钢筋进行调整，满足规定要求扩大钢筋收益 | D23: 正在实施 | F23: =M23-T23 -> 111536.52 | G23: =P23-W23 -> 0 | H23: =X23 -> 0 | I23: =Q23-X23 -> 111536.52 | J23: =Q23 -> 111536.52 | K23: 1 | L23: =+'[4]1.16装配式构件 '!F26 -> 111536.52 | M23: =K23*L23 -> 111536.52 | N23: 1 | O23: =+'[4]1.16装配式构件 '!F21 -> 0 | P23: =N23*O23 -> 0 | Q23: =M23-P23 -> 111536.52 | R23: 0 | S23: =+'[4]1.16装配式构件 '!F13 -> 0 | T23: =R23*S23 -> 0 | U23: 1 | V23: =+'[4]1.16装配式构件 '!F7 -> 0 | W23: =U23*V23 -> 0 | X23: =T23-W23 -> 0
A24: 17 | B24: 屋面结构变更 | C24: 1.屋面以上电梯井砌筑墙改为现浇结构，减短施工时间，降低施工难度，正式电梯提前插入施工，节省工期20天. | D24: 未实施 | E24: =I24 -> 48240 | F24: =M24-T24 -> 0 | G24: =P24-W24 -> -48240 | H24: =X24 -> -1372000 | I24: =Q24-X24 -> 48240 | J24: =Q24 -> -1323760 | K24: 0 | L24: 0 | M24: =K24*L24 -> 0 | N24: 1 | O24: =+'[4]1.17屋面结构变更 '!F22 -> 1323760 | P24: =N24*O24 -> 1323760 | Q24: =M24-P24 -> -1323760 | R24: 0 | S24: 0 | T24: =R24*S24 -> 0 | U24: 1 | V24: =+'[4]1.17屋面结构变更 '!F8 -> 1372000 | W24: =U24*V24 -> 1372000 | X24: =T24-W24 -> -1372000
A25: 18 | B25: 涂料施工说明变更 | C25: 1.地下室机电风管、消防管等为银灰色，而天棚颜色为深灰色，沟通设计明确此部分机电管道需要喷涂，将其计入涂料工程量； 2.外墙排水立管与墙面真石漆颜色不一致，沟通设计为保证外立面效果将管道同墙面一起喷涂，将其计入外墙真石漆工程量。 | D25: 未实施 | E25: =I25 -> 39200 | F25: =M25-T25 -> 64800 | G25: =P25-W25 -> 25600 | H25: =X25 -> 0 | I25: =Q25-X25 -> 39200 | J25: =Q25 -> 39200 | K25: 1 | L25: =+'[4]1.18涂料施工说明变更 '!F27 -> 64800 | M25: =K25*L25 -> 64800 | N25: 1 | O25: =+'[4]1.18涂料施工说明变更 '!F22 -> 25600 | P25: =N25*O25 -> 25600 | Q25: =M25-P25 -> 39200 | R25: 0 | S25: 0 | T25: =R25*S25 -> 0 | U25: =S25*T25 -> 0 | V25: =T25*U25 -> 0 | W25: =U25*V25 -> 0 | X25: =T25-W25 -> 0
A26: 19 | B26: 混凝土标号修正 | C26: 地下室消防水池与剪力墙相连时无法分开浇筑，均需添加抗渗剂，沟通设计与消防水池相连的剪力墙统一添加抗渗剂 | D26: 未实施 | E26: =I26 -> 636.93 | F26: =M26-T26 -> 636.93 | G26: =P26-W26 -> 0 | H26: =X26 -> 0 | I26: =Q26-X26 -> 636.93 | J26: =Q26 -> 636.93 | K26: 1 | L26: =+'[4]1.19混凝土标号修正 '!F27 -> 636.93 | M26: =K26*L26 -> 636.93 | N26: 0 | O26: 0 | P26: 0 | Q26: =M26-P26 -> 636.93 | R26: 0 | S26: 0 | T26: =R26*S26 -> 0 | U26: =S26*T26 -> 0 | V26: =T26*U26 -> 0 | W26: =U26*V26 -> 0 | X26: =T26-W26 -> 0
A27: 20 | B27: 陶粒混凝土做法优化 | C27: 以发泡混凝土自重、抗渗性、保温效果均优于陶粒混凝土为由，沟通业主将沉箱卫生间、降板阳台部位的陶粒混凝土回填优化发泡混凝土填充，降低成本 | D27: 未实施 | E27: =I27 -> 18359.15 | F27: =M27-T27 -> 0 | G27: =P27-W27 -> -18359.15 | H27: =X27 -> -59397.25 | I27: =Q27-X27 -> 18359.15 | J27: =Q27 -> -41038.1 | K27: 0 | L27: 0 | M27: 0 | N27: 1 | O27: =+'[4]1.20陶粒混凝土做法优化 '!F22 -> 41038.1 | P27: =N27*O27 -> 41038.1 | Q27: =M27-P27 -> -41038.1 | R27: 0 | S27: 0 | T27: 0 | U27: 1 | V27: =+'[4]1.20陶粒混凝土做法优化 '!F8 -> 59397.25 | W27: =U27*V27 -> 59397.25 | X27: =T27-W27 -> -59397.25
A28: 二 | B28: 方案策划 | E28: =SUM(E29:E50) -> 4199753.1 | F28: =SUM(F29:F50) -> 1503854.3 | G28: =SUM(G29:G50) -> -2695898.8 | H28: =SUM(H29:H50) -> -4671683.4 | I28: =SUM(I29:I50) -> 4199753.1 | J28: =SUM(J29:J50) -> -471930.37 | M28: =SUM(M29:M50) -> 1774007.7 | P28: =SUM(P29:P50) -> 2245938.1 | Q28: =SUM(Q29:Q50) -> -471930.37 | T28: =SUM(T29:T50) -> 270153.45 | W28: =SUM(W29:W50) -> 4941836.9 | X28: =SUM(X29:X50) -> -4671683.4
A29: 1 | B29: 材料堆场永临结合 | C29: 1.进场时已沟通原桩基单位，确定免费保留西侧临建硬化场地，已沟通完成设计复核钢筋加工场受力满足项目材料加工、堆放及周转受力需求；2.场内可用场地无法满足钢筋加工厂和材料堆放的全部需求，优化总进度计划及地下室阶段施工部署，将B区底板浇筑完成后，设置成临时的加工厂及材料堆场，不影响主楼区关键线路施工，节省因外部租赁场地产生的费用，降低临建施工成本。 | D29: 已实施 | E29: =I29 -> 118941.13 | F29: =M29-T29 -> 0 | G29: =P29-W29 -> -118941.13 | H29: =X29 -> -118941.13 | I29: =Q29-X29 -> 118941.13 | J29: =Q29 -> 0 | K29: 0 | L29: 0 | M29: =K29*L29 -> 0 | N29: 1 | O29: ='[3]2.1材料堆场永临结合'!F21 -> 0 | P29: =N29*O29 -> 0 | Q29: =M29-P29 -> 0 | R29: 0 | S29: 0 | T29: =R29*S29 -> 0 | U29: 1 | V29: ='[3]2.1材料堆场永临结合'!F7 -> 118941.13 | W29: =U29*V29 -> 118941.13 | X29: =T29-W29 -> -118941.13
A30: 2 | B30: 塔吊基础和筏板重叠 | C30: 塔吊基础设置在地下室车库范围内，明确塔吊基础标高和底板标高的关系；塔吊基础完成面考虑建筑做法厚度进行深化,避免后期破除。塔吊基础与底板共用，钢筋贯通，节约塔吊基础施工成本； | D30: 已实施 | E30: =I30 -> 133169.74 | F30: =M30-T30 -> 0 | G30: =P30-W30 -> -133169.74 | H30: =X30 -> -133169.74 | I30: =Q30-X30 -> 133169.74 | J30: =Q30 -> 0 | K30: 0 | L30: 0 | M30: =K30*L30 -> 0 | N30: 1 | O30: ='[3]2.1材料堆场永临结合'!F22 -> 0 | P30: =N30*O30 -> 0 | Q30: =M30-P30 -> 0 | R30: 0 | S30: 0 | T30: =R30*S30 -> 0 | U30: 1 | V30: ='[3]2.2塔吊基础与筏板重叠'!F7 -> 133169.74 | W30: =U30*V30 -> 133169.74 | X30: =T30-W30 -> -133169.74
A31: 3 | B31: 施工电梯基础优化 | C31: 依照方案设计，施工电梯基础采用顶板增加结构梁形式，提高顶板荷载，节省施工电梯钢筋混凝土基础施工（7m×5m×0.2m），提高基础下顶板承载力，取消地下室三层回顶，节省材料租赁费，机电管线一次施工成型，节省工期 | D31: 已实施 | E31: =I31 -> 36903.248 | F31: =M31-T31 -> 0 | G31: =P31-W31 -> -36903.248 | H31: =X31 -> -36903.248 | I31: =Q31-X31 -> 36903.248 | J31: =Q31 -> 0 | K31: 0 | L31: 0 | M31: =K31*L31 -> 0 | N31: 1 | O31: ='[3]2.3施工电梯基础优化'!F22 -> 0 | P31: =N31*O31 -> 0 | Q31: =M31-P31 -> 0 | R31: 0 | S31: 0 | T31: =R31*S31 -> 0 | U31: 1 | V31: ='[3]2.3施工电梯基础优化'!F8 -> 36903.248 | W31: =U31*V31 -> 36903.248 | X31: =T31-W31 -> -36903.248
A32: 4 | B32: 材料堆场受力复核 | C32: 1.根据平面布置，PC构件及临时材料堆场地下室顶板钢筋通过设计验算，取消地下室回顶措施，加快地下室装饰装修及机电安装穿插，节省工期及材料租赁费用，面积300㎡。 | D32: 已实施 | E32: =I32 -> 29280 | F32: =M32-T32 -> 0 | G32: =P32-W32 -> -29280 | H32: =X32 -> -29280 | I32: =Q32-X32 -> 29280 | J32: =Q32 -> 0 | K32: 0 | L32: 0 | M32: =K32*L32 -> 0 | N32: 1 | O32: ='[3]2.4材料堆场受力复核'!F22 -> 0 | P32: =N32*O32 -> 0 | Q32: =M32-P32 -> 0 | R32: 0 | S32: 0 | T32: =R32*S32 -> 0 | U32: 1 | V32: ='[3]2.4材料堆场受力复核'!F8 -> 29280 | W32: =U32*V32 -> 29280 | X32: =T32-W32 -> -29280
A33: 5 | B33: 地下水用于养护 | C33: 根据项目调拨加压水箱，将地下水收集后接入加压水箱，然后利用加压水箱输送至作业面用于养护、冲洗等作业 | D33: 已实施 | E33: =I33 -> 50000 | F33: =M33-T33 -> 0 | G33: =P33-W33 -> -50000 | H33: =X33 -> -50000 | I33: =Q33-X33 -> 50000 | J33: =Q33 -> 0 | K33: 0 | L33: 0 | M33: =K33*L33 -> 0 | N33: 1 | O33: 0 | P33: =N33*O33 -> 0 | Q33: =M33-P33 -> 0 | R33: 0 | S33: 0 | T33: =R33*S33 -> 0 | U33: 1 | V33: 50000 | W33: =U33*V33 -> 50000 | X33: =T33-W33 -> -50000
A34: 6 | B34: 临建租赁周期 | C34: 封顶后办公室搬至1#楼裙楼，节约1.5年办公区租赁周期，降低临建成本 | D34: 未实施 | E34: =I34 -> 900000 | F34: =M34-T34 -> 0 | G34: =P34-W34 -> -900000 | H34: =X34 -> -900000 | I34: =Q34-X34 -> 900000 | J34: =Q34 -> 0 | K34: 0 | L34: 0 | M34: =K34*L34 -> 0 | N34: 1 | O34: ='[3]2.6临建周期缩短'!F22 -> 0 | P34: =N34*O34 -> 0 | Q34: =M34-P34 -> 0 | R34: 0 | S34: 0 | T34: =R34*S34 -> 0 | U34: 1 | V34: ='[3]2.6临建周期缩短'!F8 -> 900000 | W34: =U34*V34 -> 900000 | X34: =T34-W34 -> -900000
